Workbook

Sheet Cover
C2: GATX Corporation: Financial Statement Model
C3: $ mm except per share
C5: Company name | D5: GATX Corporation
C6: Ticker | D6: GATX
C7: Circ break 1=off, 0=on (no circular interest in this build) | D7: 1
C8: Latest closing share price | D8: =Drivers!C179 -> 162.78
C9: Share price date | D9: 46303
C10: Latest fiscal year end | D10: 46022
C11: Shares outstanding (millions, diluted 2026E) | D11: =Drivers!C77 -> 35.8
A13: x | C13: CONTENTS
C14: Sheet | D14: No. | E14: What it does
C15: Cover | D15: 1 | E15: This sheet: contents, version log, checks, rating, sources
C16: Drivers | D16: 2 | E16: All inputs (blue) + assumptions + derived cells with citation column
C17: Historicals | D17: 3 | E17: 5-6 years IS + BS from FY2020-2025 10-Ks, each year cited to its own filing
C18: 3 Statement Forecast | D18: 4 | E18: Full IS/BS/CFS 2025A-2035E, revolver-plug cash mechanic, balance check row 62
C19: Debt & Interest | D19: 5 | E19: Q2 2026 10-Q maturity ladder rolled forward; interest by fixed/floating buckets
C20: Legacy Cohort Model | D20: 6 | E20: 5 vintage cohorts (2021-2025) + base fleet, rate compounds at Terminal_LPI in 2031E+
C21: Acquired Pool | D21: 7 | E21: Wells Fargo pool (98,535 cars); blended rate reprices expiring fraction at LPI
C22: GABX Mini P&L | D22: 8 | E22: JV P&L direct from 10-Q Note 7; ownership steps 30% → 33.5% → +7%/tranche
C23: Segment P&L | D23: 9 | E23: Rail NA / Rail Intl / Engine Leasing / Other rollup into consolidated revenue
C24: Disposition Engine | D24: 10 | E24: Cars sold + scrapped × gain-per-car; 2026 legacy dispo tied to guidance
C25: Thesis Test | D25: 11 | E25: Sources vs uses grid; LPI × new-issue-rate sensitivity; kill-criterion tests
C26: Valuation | D26: 12 | E26: P/E scenario weighting (bear/base/bull) → probability-weighted target price
... C36: Summary | D36: 22 | E36: Headline summary table; error-cell check
A38: x | C38: VERSION LOG
C39: Version | D39: Date | E39: What changed
C40: v1 | D40: 2026-09-24 | E40: Initial IS build; 2025A from FY2025 10-K
C41: v2 | D41: 2026-09-24 | E41: BS added; historical years cited to their own 10-Ks
C42: v3 | D42: 2026-09-24 | E42: CFS added; revolver plug; balance check row
C43: v4 | D43: 2026-09-24 | E43: Legacy Cohort Model added; 5 vintages + base fleet
C44: v5 | D44: 2026-09-24 | E44: Acquired Pool (Wells Fargo) added
C45: v6 | D45: 2026-09-24 | E45: Full rebuild per user rules (no removal, no invention, WF in 2026 CFI)
C46: v7 | D46: 2026-09-24 | E46: Fixed/floating debt split; interest by bucket per 10-Q p.42
C47: v8 | D47: 2026-09-24 | E47: Valuation inputs (v8): FactSet peers, NTM P/E, dividend yield
C48: v9 | D48: 2026-09-25 | E48: Sections 1-3: dispositions engine, GABX ownership/fees, 2028-2030 extension
C49: v10 | D49: 2026-09-25 | E49: Fix 1: Rail NA other rev anchored $160M (no fee double-count); Fix 3: dispo reconciliation
C50: v11 | D50: 2026-09-25 | E50: GABX P&L build refined; Note 7 direct link
... C61: v23 | D61: 2026-09-28 | E61: Terminal state 2031E-2035E rebuilt bottom-up (Terminal_LPI 2%, Terminal_fleet_growth 1%, D&A from PP&E/life, capex per WO with 15% taper, D/(D+E) target-held); Cover rebuilt in WSP layout
A63: x | C63: CHECKS SUMMARY (at-a-glance workbook health)
C64: Check | D64: Value | E64: Target / Source
C65: Balance check sum (11 years, must = 0) | D65: =SUM('3 Statement Forecast'!D62:N62) -> 0 | E65: 0.00 — 3SF row 62
C66: Cash BS vs CFS EOP max diff (must = 0) | D66: =MAX(ABS('3 Statement Forecast'!D36+'3 Statement Forecast'!D37-'3 Statement Forecast'!D93),ABS('3 Statement Forecast'!E36+'3 Statement Forecast'!E37-'3 Statement Forecast'!E93),ABS('3 Statement Forecast'!F36+'3 Statement Forecast'!F37-'3 Statement Forecast'!F93),ABS('3 Statement Forecast'!G36+'3 Statement Forecast'!G37-'3 Statement Forecast'!G93),ABS('3 Statement Forecast'!H36+'3 Statement Forecast'!H37-'3 Statement Forecast'!H93),ABS('3 Statement Forecast'!I36+'3 Statement Forecast'!I37-'3 Statement Forecast'!I93),ABS('3 Statement Forecast'!J36+'3 Statement Forecast'!J37-'3 Statement Forecast'!J93),ABS('3 Statement Forecast'!K36+'3 Statement Forecast'!K37-'3 Statement Forecast'!K93),ABS('3 Statement Forecast'!L36+'3 Statement Forecast'!L37-'3 Statement Forecast'!L93),ABS('3 Statement Forecast'!M36+'3 Statement Forecast'!M37-'3 Statement Forecast'!M93),ABS('3 Statement Forecast'!N36+'3 Statement Forecast'!N37-'3 Statement Forecast'!N93)) -> 0 | E66: 0.00 — 3SF row 36+37 vs row 93
C67: RI Check 1 max abs (must = 0) | D67: ='Residual Income'!D74 -> 0 | E67: 0.00 — RI!D74
C68: RI Check 2 max abs (forecast years, must = 0) | D68: ='Residual Income'!D75 -> 70.990329 | E68: 0.00 — RI!D75
C69: NAV pool tie 2025A (must = 0) | D69: =NAV!D25 -> 0 | E69: 0.00 — NAV!D25 (pool sum vs 3SF PP&E)
C70: NAV pool tie 2026E (must = 0) | D70: =NAV!E25 -> 0 | E70: 0.00 — NAV!E25
C71: FCFE identity delta max ($M) | D71: =MAX(ABS(FCFE!D102),ABS(FCFE!D103),ABS(FCFE!D104),ABS(FCFE!D105),ABS(FCFE!D106)) -> 0 | E71: ~0 — FCFE!D102:D106 (v14/15 identity)
C72: Summary sheet error cells (must = 0) | D72: =COUNTIF(Summary!A1:H105,"#*") -> 0 | E72: 0 — Summary!A1:H105
C73: v23 Item 1: Capex |YoY|% max (must ≤ 15%) | D73: ='3 Statement Forecast'!D116 -> 0.15 | E73: ≤ 0.15 — 3SF!D116
C74: v23 Item 1: EPS CAGR in [g+LPI, ROE×retention]? | D74: ='3 Statement Forecast'!D127 -> TRUE | E74: TRUE — 3SF!D127
C75: v23 Item 1: Implied LPI 2035E ≈ Terminal_LPI? | D75: =ROUND('Legacy Cohort Model'!N46-Drivers!$C$704,3) -> -0.026 | E75: ≈ 0 — LCM!N46 vs Drivers!C704
C76: v23 Item 1: D/(D+E) 2035E vs 2030E target |delta| ≤ 0.5pp? | D76: =IF(ABS('3 Statement Forecast'!N117-Drivers!$C$709)<=0.005,"OK","DRIFT") -> DRIFT | E76: OK — 3SF!N117 vs Drivers!C709
C77: AUDIT: audit_fsm.py fails count (pre-registered EPS = 1) | D77: 1 | E77: 1 pre-registered EPS FAIL (guidance vs model dispo gains); 8 PASS
A79: x | C79: RATING (linked to Rating sheet)
C80: Rating | D80: =Rating!D29 -> HOLD
C81: Probability-weighted target price ($/sh) | D81: =Rating!D18 -> 162.56567
C82: Current price ($/sh) | D82: =Rating!D19 -> 162.78
C83: Expected 12-month total return | D83: =Rating!D24 -> 0.0149015
C84: BUY threshold | D84: =Rating!D27 -> 0.15
C85: SELL threshold | D85: =Rating!D28 -> -0.05
A87: x | C87: SOURCES (vault filings folders)
C88: research/coverage/rail/gatx-10ks/ — 10-K filings FY2019-FY2025
C89: research/coverage/rail/gatx-filings/ — Q2 2026 10-Q, earnings release 2026-07-30, transcripts
C90: research/coverage/rail/gatx-consensus/ — FactSet + TipRanks + FXEmpire consensus + Consensus Bridge
C91: research/coverage/rail/factset/ — lessor-rail-comps snapshot 2026-09-21, valuation series
C92: research/coverage/rail/gatx-fleet-composition.md — Rail NA fleet mix, GATX 2026 Company Overview p.30
C93: research/coverage/rail/gatx-lease-pricing-history.md — LPI 2016-2025 series (Terminal_LPI = 2.0% anchor)
C94: research/coverage/rail/gatx-rates-and-credit-2026-09-24.md — 10y UST, bond YTW (DCF inputs)
C95: research/coverage/rail/railcar-supply-2026-09.md — RSI orders/deliveries/backlog (Terminal_fleet_growth = 1.0% anchor)
C96: research/coverage/rail/gatx-valuation.md + peer-lessors.md — cross-check valuation methods
C97: research/coverage/rail/falsified.md — falsified-claim ledger (FALS-01/02/03/08)
C98: reference/methodology/dcf-mechanics.md + dcf-wacc-and-inputs.md — DCF discipline
C99: monitoring/THRESHOLDS.md — kill-criteria (new-issue rate 6.00%; LPI break-even)
... C102: Iterative calculation OFF (Circ_break D7=1). Save with F9 recalc if any input changed.
C103: v27: Scenario snapshot STALE check (must = NOT STALE) | D103: =Valuation!E167 -> STALE | E103: NOT STALE — Valuation C1 block
C104: v27: Base snapshot equals live 2027E EPS (must = 0) | D104: =Valuation!E168 -> 0.25660188 | E104: 0 — Valuation C1 base-equals-live

Sheet Drivers
B1: GATX FSM v6 — DRIVERS (blue = input; source on every row)
B3: Driver | C3: Value | O3: Source
A4: x | B4: --- FLEET ---
B5: RailNA_ex_boxcars_YE2025 | C5: 100593 | O5: FY2025 10-K p.31: Rail NA railcars ex-boxcars ending 100,593
B6: RailNA_boxcars_YE2025 | C6: 7032 | O6: FY2025 10-K p.33: boxcars ending 7,032
B7: RailNA_utilization_YE2025 | C7: 0.99 | O7: FY2025 10-K p.31: 99.0% ex-boxcars
B8: RailNA_renewal_success_2025 | C8: 0.873 | O8: FY2025 10-K p.31: 87.3%
B9: LPI_FY2025 | C9: 0.219 | O9: FY2025 10-K p.32: +21.9%
A10: x | B10: --- LEGACY COHORTS (5 vintages) ---
B11: Cohort_2021_cars | C11: 20000 | O11: Company Overview deck p.30 (2021 renewal count)
B12: Cohort_2022_cars | C12: 18500 | O12: Deck p.30
B13: Cohort_2023_cars | C13: 18700 | O13: Deck p.30
B14: Cohort_2024_cars | C14: 19400 | O14: Deck p.30
B15: Cohort_2025_cars | C15: 21500 | O15: FY2025 10-K p.31 (21,500 renewed FY2025)
B16: Legacy_base_fleet_cars | C16: 2493 | O16: Derived: 100,593 ex-boxcars − 5 cohorts × 98,100
B17: Cohort_2021_rate_pre | C17: 6800 | O17: Assumption: 2021 vintage low (LPI down cycle 2016-21)
B18: Cohort_2022_rate_pre | C18: 7200 | O18: Assumption: modest recovery
B19: Cohort_2023_rate_pre | C19: 7500 | O19: Assumption: continued recovery
B20: Cohort_2024_rate_pre | C20: 7900 | O20: Assumption
B21: Cohort_2025_rate_pre | C21: 8100 | O21: Assumption: near current avg
B22: Legacy_base_rate | C22: 8300 | O22: Assumption: base fleet at current avg
B23: Cohort_calibration_factor (RETIRED v36) | C23: 1.2387 | D23: v36 2026-10-07: RETIRED. New engine on Legacy Cohort Model rows 55-68 builds from disclosed 2025A target (C45=954.2) directly; no calibration factor needed. Value 1.2387 preserved for history (blue input annotation). Prior use: scaled 5 pre-rates in cohort build; cohort build retained as reference only. | O23: RETIRED v36: new engine ties to Drivers!C45 directly via Legacy Cohort Model!D65. Value 1.2387 kept as history.
A24: x | B24: --- ACQUIRED POOL (Wells Fargo, closed 1/1/26) ---
B25: Acquired_pool_cars | C25: 98535 | O25: Deck p.23: ~98,535 acquired via GABX
B26: Acquired_pool_H1_2026_rev | C26: 271.5 | O26: 10-Q Note 7 p.11: GABX total revenue H1 2026 (also = GABX Mini P&L C4)
B27: Acquired_pool_renewal_pct_2027 | C27: 0.17 | O27: Assumption: 17% of acquired fleet expiring in 2027
B28: Acquired_pool_renewal_pct_2028 | C28: 0.17 | O28: Assumption: level
A29: x | B29: --- LPI + RENEWAL SUCCESS ---
B30: LPI_Q1_2026 | C30: 0.223 | O30: Q2 release 5-qtr table
B31: LPI_Q2_2026 | C31: 0.168 | O31: Q2 release: LPI +16.8%
B32: LPI_FY2026 | C32: 0.185 | O32: Assumption: blend Q1 22.3%, Q2 16.8%, H2 mid-cycle
B33: LPI_FY2027 | C33: =CHOOSE(Drivers!$C$736,Drivers!$D$740,Drivers!$E$740,Drivers!$F$740) -> 0.15 | O33: Assumption: decel from Q2 2026 print
B34: LPI_FY2028 | C34: =CHOOSE(Drivers!$C$736,Drivers!$D$741,Drivers!$E$741,Drivers!$F$741) -> 0.1 | O34: Assumption
B35: LPI_FY2029 | C35: =CHOOSE(Drivers!$C$736,Drivers!$D$742,Drivers!$E$742,Drivers!$F$742) -> 0.05 | O35: Assumption: cycle turn
B36: LPI_FY2030 | C36: =CHOOSE(Drivers!$C$736,Drivers!$D$743,Drivers!$E$743,Drivers!$F$743) -> -0.02 | O36: Assumption: cycle low
B37: Renewal_success_FY2026 | C37: =CHOOSE(Drivers!$C$736,Drivers!$D$746,Drivers!$E$746,Drivers!$F$746) -> 0.808 | O37: Assumption: avg Q1 79.1% + Q2 82.6%
B38: Renewal_success_FY2027 | C38: =CHOOSE(Drivers!$C$736,Drivers!$D$747,Drivers!$E$747,Drivers!$F$747) -> 0.85 | O38: Assumption: normalizing
B39: Renewal_phasing_factor | C39: 0.842 | O39: Assumption: mid-year timing convention
B40: Failed_renewal_market_rate | C40: 8100 | O40: Assumption: failed renewals re-lease at market
A41: x | B41: --- SEGMENT REVENUE 2025A ---
B42: RailNA_lease_rev_2025 | C42: 1049.1 | O42: FY2025 10-K p.31: railcars 954.2 + boxcars 58.5 + locos 36.4
B43: RailNA_boxcar_rev_2025 | C43: 58.5 | O43: FY2025 10-K p.31
B44: RailNA_loco_rev_2025 | C44: 36.4 | O44: FY2025 10-K p.31
B45: RailNA_cohort_target_2025 | C45: 954.2 | O45: Rail NA lease 1,049.1 − boxcars 58.5 − locos 36.4 (= railcars)
B46: RailNA_other_rev_2025 | C46: 137.3 | O46: FY2025 10-K segment; derived
B47: RailIntl_lease_rev_2025 | C47: 366.1 | O47: FY2025 10-K segment
B48: RailIntl_other_rev_2025 | C48: 22.3 | O48: FY2025 10-K segment
B49: EngineL_lease_rev_2025 | C49: 38.2 | O49: FY2025 10-K segment
B50: EngineL_non_ded_rev_2025 | C50: 86.7 | O50: FY2025 10-K p.60 IS
B51: Other_seg_rev_2025 | C51: 40.7 | O51: FY2025 10-K segment
A52: x | B52: --- 2026 GUIDANCE (Q2 release + transcript) ---
B53: Guided_EPS_low | C53: 9.9 | O53: Q2 2026 release
B54: Guided_EPS_high | C54: 10.3 | O54: Q2 2026 release
B55: Guided_EPS_midpoint | C55: 10.1 | O55: Derived midpoint
B56: Dispo_2026_GATX_legacy | C56: =CHOOSE(Drivers!$C$736,Drivers!$D$749,Drivers!$E$749,Drivers!$F$749) -> 130 | O56: Q2 transcript: "well ahead of $130M" originally, held for base case
B57: Dispo_2026_JV | C57: =CHOOSE(Drivers!$C$736,Drivers!$D$751,Drivers!$E$751,Drivers!$F$751) -> 70 | O57: Q2 transcript: "$70M full-year target for JV, unchanged"
B58: Dispo_2027_GATX_legacy | C58: =CHOOSE(Drivers!$C$736,Drivers!$D$750,Drivers!$E$750,Drivers!$F$750) -> 140 | O58: Assumption: modest normalization
B59: Dispo_2027_JV | C59: =CHOOSE(Drivers!$C$736,Drivers!$D$752,Drivers!$E$752,Drivers!$F$752) -> 70 | O59: Q2 transcript: JV FY guide $70M — carried forward to 2027E
A60: x | B60: --- GABX (10-Q Note 7 p.11) ---
B61: GABX_Q2_revenue | C61: 136.6 | O61: 10-Q Note 7 p.11
B62: GABX_Q2_expenses | C62: -108.6 | O62: 10-Q Note 7 p.11 (incl. $12.4M mgmt fee paid to GATX)
B63: GABX_Q2_dispo_gains | C63: 21.9 | O63: 10-Q Note 7 p.11
B64: GABX_Q2_interest | C64: -36.6 | O64: 10-Q Note 7 p.11
B65: GABX_Q2_tax | C65: -2.5 | O65: 10-Q Note 7 p.11
B66: GABX_Q2_NI | C66: 10.8 | O66: 10-Q Note 7 p.11 (verification)
B67: GABX_H1_revenue | C67: 271.5 | O67: 10-Q Note 7 p.11
B68: GABX_H1_expenses | C68: -208.8 | O68: 10-Q Note 7 p.11
B69: GABX_H1_dispo | C69: 23.9 | O69: 10-Q Note 7 p.11
B70: GABX_H1_interest | C70: -80.5 | O70: 10-Q Note 7 p.11
B71: GABX_H1_tax | C71: -4.4 | O71: 10-Q Note 7 p.11
B72: GABX_H1_NI | C72: 1.7 | O72: 10-Q Note 7 p.11 (verification)
B73: GABX_JV_share_GATX | C73: =Drivers!$C$251 -> 0.33535 | D73: v38 rewire: was 0.3 hard-code. Now points to current ownership C251 (33.535%). Phase A1 2026-10-08. | O73: 10-Q Note 7 p.10 (pre-first-call; 33.5% post-6/30/26)
A74: x | B74: --- TAX + SHARES + DIVIDENDS ---
B75: Effective_tax_rate_2026 | C75: 0.263 | O75: H1 2026 effective: $47.2M / $179.3M
B76: Effective_tax_rate_2027 | C76: 0.24 | O76: Assumption: normalizes
B77: Diluted_shares_2026 | C77: 35.8 | O77: Q2 2026 release
B78: Diluted_shares_2027 | C78: =Drivers!$C$77-Drivers!$C$725 -> 35.22652 | O78: v24: 2027E shares = 2026E filed - shares_repurchased_2027 (Item 3). Retirement mechanic starts 2027E.
B79: Dividend_per_share_2026 | C79: 2.64 | O79: Q2 2026 release: $0.66/qtr × 4
B80: Dividend_per_share_2027 | C80: 2.74 | O80: Assumption: 3.8% raise (106yr history)
B81: Buyback_2026 | C81: 100 | O81: Assumption
B82: Buyback_2027 | C82: 100 | O82: Assumption
B83: SBC_annual | C83: 28 | O83: FY2025 10-K equity roll: APIC delta ~$28M/yr (share-based comp effects)
B84: NCI_distributions_2026 | C84: 100 | O84: Assumption: 10-Q Note 7 H1 cash flow $49.9M distributions to Brookfield × ~2
B85: NCI_distributions_2027 | C85: 100 | O85: Assumption
B86: Dispo_book_2026 | C86: 150 | O86: Assumption: proceeds − gains = ~$150M book value of assets sold
B87: Dispo_book_2027 | C87: 150 | O87: Assumption
B88: Non_GABX_debt_growth_2027 | C88: 400 | O88: Assumption: non-GABX debt grows by $400M from Q2 2026 balance to fund 2027 organic capex net of internal cash generation. Replaces retired Core_debt_2027_increment; non-circular (does NOT reference the cash-flow plug).
A89: x | B89: --- DEBT LADDER (10-Q p.42) ---
B90: Debt_maturity_2026R | C90: 633.8 | O90: 10-Q p.42 remainder-of-year 2026
B91: Debt_maturity_2027 | C91: 848.1 | O91: 10-Q p.42
B92: Debt_maturity_2028 | C92: 819.4 | O92: 10-Q p.42
B93: Debt_maturity_2029 | C93: 850 | O93: 10-Q p.42
B94: Debt_maturity_2030 | C94: 2576.4 | O94: 10-Q p.42 (incl. GABX $1,881.1M)
B95: Debt_maturity_thereafter | C95: 6615.2 | O95: 10-Q p.42
B96: Interest_scheduled_2026R | C96: 294.2 | O96: 10-Q p.42 interest schedule
B97: Interest_scheduled_2027 | C97: 542.1 | O97: 10-Q p.42 (full-year 2027 interest at 6/30/26 rates)
B98: Interest_scheduled_2028 | C98: 511.1 | O98: 10-Q p.42
B99: Debt_YE2025_recourse | C99: 12451.7 | O99: FY2025 10-K p.58: recourse debt
B100: Debt_YE2025_bank | C100: 82.2 | O100: FY2025 10-K p.58: bank credit facilities
B101: Debt_YE2025_total | C101: 12533.9 | O101: FY2025 10-K p.58
...

Sheet Historicals
C2: ="Financial Statement Model - "&Cover!$D$5 -> Financial Statement Model - GATX Corporation
C3: $ mm except per share
C5: Company name | D5: =Cover!$D$5 -> GATX Corporation
C6: Ticker | D6: =Cover!$D$6 -> GATX
C7: Circ break 1=off, 0=on | D7: =Cover!$D$7 -> 1
C8: Latest closing share price | D8: =Cover!$D$8 -> 162.78
C9: Share price date | D9: =Cover!$D$9 -> 46303
C10: Latest fiscal year end | D10: =Cover!$D$10 -> 46022
C11: Shares outstanding (millions) | D11: =Cover!$D$11 -> 35.8
C13: HISTORICALS 2020-2025 — each BS/IS/CFS line from that year's own 10-K
A15: x | C15: INCOME STATEMENT ($M) — FY2022 10-K for 2020-22, FY2025 10-K for 2023-25 | D15: 2020A | E15: 2021A | F15: 2022A | G15: 2023A | H15: 2024A | I15: 2025A
C16: Lease revenue | D16: 1087.5 | E16: 1140.5 | F16: 1154.6 | G16: 1251.4 | H16: 1381.1 | I16: 1486.2 | P16: FY2022 10-K p.60 (2020-22 columns); FY2025 10-K p.60 (2023-25).
C17: Non-dedicated engine revenue | D17: 0 | E17: 0 | F17: 1.5 | G17: 37.6 | H17: 64.6 | I17: 86.7
C18: Marine operating revenue | D18: 15.6 | E18: 19.1 | F18: 18.9 | G18: 6.9 | H18: 0 | I18: 0
C19: Other revenue | D19: 106.1 | E19: 97.8 | F19: 98 | G19: 115 | H19: 139.8 | I19: 167.5
C20: Total Revenues | D20: 1209.2 | E20: 1257.4 | F20: 1273 | G20: 1410.9 | H20: 1585.5 | I20: 1740.4
C21: Maintenance expense | D21: -315.5 | E21: -297.1 | F21: -292.7 | G21: -344.8 | H21: -381.6 | I21: -427.7
C22: Marine operating expense | D22: -19.7 | E22: -17.5 | F22: -14.1 | G22: -6.5 | H22: 0 | I22: 0
C23: Depreciation expense | D23: -330.5 | E23: -364.4 | F23: -357.5 | G23: -376.3 | H23: -402.4 | I23: -431.8
C24: Operating lease expense | D24: -49.3 | E24: -39.2 | F24: -36.1 | G24: -36 | H24: -33.9 | I24: -28.9
C25: Other operating expense | D25: -35.3 | E25: -44 | F25: -37.4 | G25: -46.6 | H25: -57.7 | I25: -65.3
C26: SG&A | D26: -172 | E26: -198.3 | F26: -195 | G26: -212.7 | H26: -236.3 | I26: -252.6
C27: Total Expenses | D27: -922.3 | E27: -960.5 | F27: -932.8 | G27: -1022.9 | H27: -1111.9 | I27: -1206.3
C28: Net gain on asset dispositions | D28: 41.7 | E28: 105.9 | F28: 77.9 | G28: 130.3 | H28: 138.3 | I28: 136.9
... C36: Diluted EPS | D36: 4.28 | E36: 4.02 | F36: 4.36 | G36: 7.12 | H36: 7.78 | I36: 9.12
C39: BALANCE SHEET ($M) — each year from that year's own 10-K | D39: 2020A | E39: 2021A | F39: 2022A | G39: 2023A | H39: 2024A | I39: 2025A
C40: Cash and cash equivalents | D40: 292.2 | E40: 344.3 | F40: 303.7 | G40: 450.7 | H40: 401.6 | I40: 743 | P40: 2020: FY2020 10-K p.59. 2021: FY2021 10-K p.59. 2022: FY2022 10-K p.55. 2023: FY2023 10-K p.56. 2024: FY2024 10-K p.57. 2025: FY2025 10-K p.58.
C41: Restricted cash | D41: 0.4 | E41: 0.2 | F41: 0.3 | G41: 0.1 | H41: 0.2 | I41: 4241.9
C42: Short-term investments | D42: 0 | E42: 0 | F42: 148.5 | G42: 0 | H42: 0 | I42: 0
C43: Receivables (net) | D43: 142.2 | E43: 163.8 | F43: 162 | G43: 218.4 | H43: 199.1 | I43: 207.2
C44: Operating assets and facilities, gross | D44: 10484 | E44: 11163.6 | F44: 11675 | G44: 13081.9 | H44: 14330.6 | I44: 15662.6
C45: Accum depreciation | D45: -3313.3 | E45: -3378.8 | F45: -3424.7 | G45: -3670.7 | H45: -3880.9 | I45: -4251.7
C46: Operating assets and facilities, net | D46: 7170.7 | E46: 7784.8 | F46: 8250.3 | G46: 9411.2 | H46: 10449.7 | I46: 11410.9
C47: Right-of-use assets | D47: 335.9 | E47: 270.7 | F47: 243.5 | G47: 212 | H47: 165.4 | I47: 137.4
C48: Finance leases (as lessee) | D48: 37.5 | E48: 1.5 | F48: 0 | G48: 0 | H48: 0 | I48: 0
C49: Investments in Affiliated Companies | D49: 584.7 | E49: 588.4 | F49: 575.1 | G49: 627 | H49: 663.3 | I49: 732.3
C50: Goodwill | D50: 143.7 | E50: 123 | F50: 117.2 | G50: 120 | H50: 114.1 | I50: 126.3
C51: Other Assets | D51: 230.3 | E51: 265 | F51: 271.4 | G51: 286.6 | H51: 303.1 | I51: 400.5
C52: Total Assets | D52: 8937.6 | E52: 9541.7 | F52: 10072 | G52: 11326 | H52: 12296.5 | I52: 17999.5
... C70: Total Liabilities and Equity | D70: 8937.6 | E70: 9541.7 | F70: 10072 | G70: 11326 | H70: 12296.5 | I70: 17999.5
A73: x | C73: CASH FLOW STATEMENT ($M) | D73: 2020A | E73: 2021A | F73: 2022A | G73: 2023A | H73: 2024A | I73: 2025A
C74: Net income | D74: 150.2 | E74: 143.1 | F74: 155.9 | G74: 259.2 | H74: 284.2 | I74: 333.3 | P74: FY2025 10-K p.62 (2023-25 columns); FY2022 10-K p.62 (2020-22 columns).
C75: D&A | D75: 345.6 | E75: 380 | F75: 373 | G75: 392.1 | H75: 421.4 | I75: 452.3
C76: Other operating adjustments | D76: 37.7 | E76: -15.9 | F76: -92.1 | G76: -130.9 | H76: -137.8 | I76: -140
C77: Working capital + other | D77: 0 | E77: 0 | F77: 0 | G77: 0 | H77: 0 | I77: -11.8
C78: Net cash from operating | D78: 533.5 | E78: 507.2 | F78: 436.8 | G78: 520.4 | H78: 602.1 | I78: 648.1
C79: Portfolio investments & capex | D79: -1255.8 | E79: -1131.9 | F79: -1064 | G79: -1665 | H79: -1674.4 | I79: -1316.7
C80: Portfolio proceeds | D80: 31.1 | E80: 54.7 | F80: 26 | G80: 272.8 | H80: 230.6 | I80: 275
C81: Proceeds from other asset sales | D81: 0 | E81: 0 | F81: 0 | G81: 20.2 | H81: 24.9 | I81: 36.8
C82: Other investing (incl short-term inv) | D82: 151.2 | E82: 159.5 | F82: 133.1 | G82: 152.7 | H82: 2.2 | I82: -11.9
C83: Net cash used in investing | D83: -1073.5 | E83: -917.7 | F83: -904.9 | G83: -1219.3 | H83: -1416.7 | I83: -1016.8
C84: Net proceeds from debt (>90d) | D84: 0 | E84: 0 | F84: 0 | G84: 1420 | H84: 1295.6 | I84: 4841.5
C85: Repayments of debt (>90d) | D85: 0 | E85: 0 | F85: 0 | G85: -500 | H85: -413.5 | I85: -733.4
C86: Net change in short-term debt (<=90d) | D86: 0 | E86: 0 | F86: 0 | G86: -7.1 | H86: 0 | I86: 70.4
... C96: Cash + restricted EOP | D96: 292.6 | E96: 344.5 | F96: 304 | G96: 450.7 | H96: 401.8 | I96: 4984.9

Sheet 3 Statement Forecast
C2: ="Financial Statement Model - "&Cover!$D$5 -> Financial Statement Model - GATX Corporation
C3: $ mm except per share
C5: Company name | D5: =Cover!$D$5 -> GATX Corporation
C6: Ticker | D6: =Cover!$D$6 -> GATX
C7: Circ break 1=off, 0=on | D7: =Cover!$D$7 -> 1
C8: Latest closing share price | D8: =Cover!$D$8 -> 162.78
C9: Share price date | D9: =Cover!$D$9 -> 46303
C10: Latest fiscal year end | D10: =Cover!$D$10 -> 46022
C11: Shares outstanding (millions) | D11: =Cover!$D$11 -> 35.8
C13: GATX 3-STATEMENT FORECAST — 2025A from filings, 2026-27E from model. Revolver-plug.
D15: 2025A | E15: 2026E | F15: 2027E | G15: 2028E | H15: 2029E | I15: 2030E | J15: 2031E | K15: 2032E | L15: 2033E | M15: 2034E | N15: 2035E
A16: x | C16: INCOME STATEMENT ($M)
C17: Total revenue | D17: ='Segment P&L'!D36 -> 1740.4 | E17: ='Segment P&L'!E36 -> 2385.4547 | F17: ='Segment P&L'!F36 -> 2471.4791 | G17: ='Segment P&L'!G36 -> 2553.7116 | H17: ='Segment P&L'!H36 -> 2622.8806 | I17: ='Segment P&L'!I36 -> 2673.4938 | J17: ='Segment P&L'!J36 -> 2715.5694 | K17: ='Segment P&L'!K36 -> 2762.9249 | ... N17: ='Segment P&L'!N36 -> 2913.282
C18: Maintenance | D18: -427.7 | E18: =-E17*Drivers!$C$128 -> -599.54072 | F18: =-F17*Drivers!$C$128 -> -621.16139 | G18: =-G17*Drivers!$C$128 -> -641.82905 | H18: =-H17*Drivers!$C$128 -> -659.21342 | I18: =-I17*Drivers!$C$128 -> -671.93412 | J18: =-J17*Drivers!$C$128 -> -682.50906 | K18: =-K17*Drivers!$C$128 -> -694.41101 | L18: =-L17*Drivers!$C$128 -> -706.6518 | ... N18: =-N17*Drivers!$C$128 -> -732.20054
C19: Depreciation | D19: -431.8 | E19: =-Drivers!$C$124 -> -671.4 | F19: =-Drivers!$C$125 -> -720 | G19: =-Drivers!$C$303 -> -720 | H19: =-Drivers!$C$304 -> -720 | I19: =-Drivers!$C$305 -> -720 | J19: =-Drivers!$C$558 -> -720 | K19: =-Drivers!$C$559 -> -732.8353 | L19: =-Drivers!$C$560 -> -743.92318 | M19: =-Drivers!$C$561 -> -755.12194 | N19: =-Drivers!$C$562 -> -766.43269
C20: Operating lease expense | D20: -28.9 | E20: =-Drivers!$C$129 -> -29.6 | F20: =-Drivers!$C$129 -> -29.6 | G20: =-Drivers!$C$129 -> -29.6 | H20: =-Drivers!$C$129 -> -29.6 | I20: =-Drivers!$C$129 -> -29.6 | J20: =-Drivers!$C$129 -> -29.6 | K20: =-Drivers!$C$129 -> -29.6 | L20: =-Drivers!$C$129 -> -29.6 | ... N20: =-Drivers!$C$129 -> -29.6
C21: Other operating expense | D21: -65.3 | E21: =-E17*Drivers!$C$130 -> -95.418186 | F21: =-F17*Drivers!$C$130 -> -98.859162 | G21: =-G17*Drivers!$C$130 -> -102.14846 | H21: =-H17*Drivers!$C$130 -> -104.91523 | I21: =-I17*Drivers!$C$130 -> -106.93975 | J21: =-J17*Drivers!$C$130 -> -108.62278 | K21: =-K17*Drivers!$C$130 -> -110.517 | L21: =-L17*Drivers!$C$130 -> -112.46514 | ... N21: =-N17*Drivers!$C$130 -> -116.53128
C22: SG&A | D22: -252.6 | E22: =-E17*Drivers!$C$127 -> -288.64001 | F22: =-F17*Drivers!$C$127 -> -299.04897 | G22: =-G17*Drivers!$C$127 -> -308.9991 | H22: =-H17*Drivers!$C$127 -> -317.36856 | I22: =-I17*Drivers!$C$127 -> -323.49274 | J22: =-J17*Drivers!$C$127 -> -328.58389 | K22: =-K17*Drivers!$C$127 -> -334.31391 | L22: =-L17*Drivers!$C$127 -> -340.20706 | ... N22: =-N17*Drivers!$C$127 -> -352.50712
C23: Net gain on asset dispositions (legacy engine + GABX row 10) | D23: 136.9 | E23: ='Disposition Engine'!D44+'GABX Mini P&L'!G22 -> 210.5 | F23: ='Disposition Engine'!E44+'GABX Mini P&L'!H22 -> 210.5 | G23: ='Disposition Engine'!F44+'GABX Mini P&L'!I22 -> 210.49926 | H23: ='Disposition Engine'!G44+'GABX Mini P&L'!J22 -> 210.49926 | I23: ='Disposition Engine'!H44+'GABX Mini P&L'!K22 -> 210.49926 | J23: ='Disposition Engine'!I44+'GABX Mini P&L'!L22 -> 217.86674 | K23: ='Disposition Engine'!J44+'GABX Mini P&L'!M22 -> 220.40246 | L23: ='Disposition Engine'!K44+'GABX Mini P&L'!N22 -> 223.02694 | ... N23: ='Disposition Engine'!M44+'GABX Mini P&L'!P22 -> 228.55467
C24: Interest expense, net (from Debt sheet) | D24: ='Debt & Interest'!D31 -> -391.5 | E24: ='Debt & Interest'!E31 -> -588.82599 | F24: ='Debt & Interest'!F31 -> -615.70826 | G24: ='Debt & Interest'!G31 -> -642.39824 | H24: ='Debt & Interest'!H31 -> -669.29324 | I24: ='Debt & Interest'!I31 -> -715.76368 | J24: ='Debt & Interest'!J31 -> -727.51591 | K24: ='Debt & Interest'!K31 -> -739.77159 | ... N24: ='Debt & Interest'!N31 -> -767.65406
C25: Other income (expense) | D25: -0.4 | E25: =Drivers!$C$142 -> 10.4 | F25: =Drivers!$C$143 -> 10 | G25: =Drivers!$C$312 -> 10 | H25: =Drivers!$C$313 -> 10 | I25: =Drivers!$C$314 -> 10 | J25: =Drivers!$C$548 -> 10 | K25: =Drivers!$C$549 -> 10 | L25: =Drivers!$C$550 -> 10 | M25: =Drivers!$C$551 -> 10 | N25: =Drivers!$C$552 -> 10
C26: Pretax income (pre-affiliates) | D26: =D17+D18+D19+D20+D21+D22+D23+D24+D25 -> 279.1 | E26: =E17+E18+E19+E20+E21+E22+E23+E24+E25 -> 332.92975 | F26: =F17+F18+F19+F20+F21+F22+F23+F24+F25 -> 307.60128 | G26: =G17+G18+G19+G20+G21+G22+G23+G24+G25 -> 329.23602 | H26: =H17+H18+H19+H20+H21+H22+H23+H24+H25 -> 342.98945 | I26: =I17+I18+I19+I20+I21+I22+I23+I24+I25 -> 326.26273 | J26: =J17+J18+J19+J20+J21+J22+J23+J24+J25 -> 346.60448 | K26: =K17+K18+K19+K20+K21+K22+K23+K24+K25 -> 351.87855 | ... N26: =N17+N18+N19+N20+N21+N22+N23+N24+N25 -> 386.91098
C27: Income taxes | D27: -63.1 | E27: =-E26*Drivers!$C$75 -> -87.560524 | F27: =-F26*Drivers!$C$76 -> -73.824307 | G27: =-G26*Drivers!$C$273 -> -79.016644 | H27: =-H26*Drivers!$C$274 -> -82.317467 | I27: =-I26*Drivers!$C$275 -> -78.303055 | J27: =-J26*Drivers!$C$498 -> -83.185075 | K27: =-K26*Drivers!$C$499 -> -84.450851 | L27: =-L26*Drivers!$C$500 -> -86.980988 | M27: =-M26*Drivers!$C$501 -> -89.782969 | N27: =-N26*Drivers!$C$502 -> -92.858635
C28: Share of affiliates (RRPF), net of tax | D28: 117.3 | E28: =Drivers!$C$113 -> 140 | F28: =Drivers!$C$114 -> 150 | G28: =Drivers!$C$294 -> 150 | H28: =Drivers!$C$295 -> 150 | I28: =Drivers!$C$296 -> 150 | J28: =Drivers!$C$528 -> 150 | K28: =Drivers!$C$529 -> 150 | L28: =Drivers!$C$530 -> 150 | M28: =Drivers!$C$531 -> 150 | N28: =Drivers!$C$532 -> 150
C29: Net Income (consolidated) | D29: =D26+D27+D28 -> 333.3 | E29: =E26+E27+E28 -> 385.36922 | F29: =F26+F27+F28 -> 383.77697 | G29: =G26+G27+G28 -> 400.21937 | H29: =H26+H27+H28 -> 410.67198 | I29: =I26+I27+I28 -> 397.95967 | J29: =J26+J27+J28 -> 413.4194 | K29: =K26+K27+K28 -> 417.42769 | ... N29: =N26+N27+N28 -> 444.05234
C30: Less: NCI (from GABX Mini P&L) | D30: 0 | E30: =-'GABX Mini P&L'!G27 -> -17.01504 | F30: =-'GABX Mini P&L'!H27 -> -25.309791 | G30: =-'GABX Mini P&L'!I27 -> -29.719233 | H30: =-'GABX Mini P&L'!J27 -> -29.035726 | I30: =-'GABX Mini P&L'!K27 -> -23.440796 | J30: =-'GABX Mini P&L'!L27 -> -22.700665 | K30: =-'GABX Mini P&L'!M27 -> -20.445024 | L30: =-'GABX Mini P&L'!N27 -> -16.629065 | ... N30: =-'GABX Mini P&L'!P27 -> -4.1300084
C31: NI attributable to GATX | D31: =D29+D30 -> 333.3 | E31: =E29+E30 -> 368.35418 | F31: =F29+F30 -> 358.46718 | G31: =G29+G30 -> 370.50014 | H31: =H29+H30 -> 381.63625 | I31: =I29+I30 -> 374.51888 | J31: =J29+J30 -> 390.71874 | K31: =K29+K30 -> 396.98267 | ... N31: =N29+N30 -> 439.92234
C32: Diluted shares (M) | D32: 35.9 | E32: =Drivers!$C$77 -> 35.8 | F32: =Drivers!$C$78 -> 35.22652 | G32: =Drivers!$C$276 -> 34.672433 | H32: =Drivers!$C$277 -> 34.137083 | I32: =Drivers!$C$278 -> 33.619837 | J32: =Drivers!$C$503 -> 33.098466 | K32: =Drivers!$C$504 -> 32.586649 | L32: =Drivers!$C$505 -> 32.077407 | M32: =Drivers!$C$506 -> 31.56818 | N32: =Drivers!$C$507 -> 31.056618
C33: Diluted EPS | D33: =D31/D32 -> 9.2841226 | E33: =E31/E32 -> 10.289223 | F33: =F31/F32 -> 10.17606 | G33: =G31/G32 -> 10.685727 | H33: =H31/H32 -> 11.179521 | I33: =I31/I32 -> 11.139818 | J33: =J31/J32 -> 11.804739 | K33: =K31/K32 -> 12.182372 | ... N33: =N31/N32 -> 14.165172
A35: x | C35: BALANCE SHEET ($M) — 2025A from FY2025 10-K p.58
C36: Cash and cash equivalents | D36: 743 | E36: 747.1 | F36: 747.1 | G36: 747.1 | H36: 747.1 | I36: 747.1 | J36: =I36 -> 747.1 | K36: =J36 -> 747.1 | L36: =K36 -> 747.1 | M36: =L36 -> 747.1 | N36: =M36 -> 747.1
C37: Restricted cash | D37: 4241.9 | E37: 0.1 | F37: 0.1 | G37: 0.1 | H37: 0.1 | I37: 0.1 | J37: 0.1 | K37: 0.1 | L37: 0.1 | M37: 0.1 | N37: 0.1
C38: Receivables (net) | D38: 207.2 | E38: =D38*(E17/D17) -> 283.99575 | F38: =E38*(F17/E17) -> 294.23722 | G38: =F38*(G17/F17) -> 304.02726 | H38: =G38*(H17/G17) -> 312.26205 | I38: =H38*(I17/H17) -> 318.2877 | J38: =I38*(J17/I17) -> 323.29693 | K38: =J38*(K17/J17) -> 328.93475 | L38: =K38*(L17/K17) -> 334.73308 | ... N38: =M38*(N17/M17) -> 346.83523
C39: PP&E net (BOP + WF + capex − depr − dispo book) | D39: 11410.9 | E39: =D39+Drivers!$C$123+Drivers!$C$121+E19-Drivers!$C$86 -> 15830.5 | F39: =E39+Drivers!$C$122+F19-Drivers!$C$87 -> 16360.5 | G39: =F39+Drivers!$C$300+G19-Drivers!$C$288 -> 16890.5 | H39: =G39+Drivers!$C$301+H19-Drivers!$C$289 -> 17420.5 | I39: =H39+Drivers!$C$302+I19-Drivers!$C$290 -> 17950.5 | J39: =I39+Drivers!$C$563+J19-Drivers!$C$553 -> 18270.5 | K39: =J39+Drivers!$C$564+K19-Drivers!$C$554 -> 18546.935 | L39: =K39+Drivers!$C$565+L19-Drivers!$C$555 -> 18826.134 | M39: =L39+Drivers!$C$566+M19-Drivers!$C$556 -> 19108.125 | N39: =M39+Drivers!$C$567+N19-Drivers!$C$557 -> 19392.936
C40: Right-of-use assets (net) | D40: 137.4 | E40: 127.5 | F40: 120 | G40: 112.5 | H40: 105 | I40: 97.5 | J40: 90 | K40: 82.5 | L40: 75 | M40: 67.5 | N40: 60
C41: Investments in Affiliated Companies | D41: 732.3 | E41: =D41+Drivers!$C$113-Drivers!$C$115 -> 732.3 | F41: =E41+Drivers!$C$114-Drivers!$C$116 -> 752.3 | G41: =F41+Drivers!$C$294-Drivers!$C$297 -> 772.3 | H41: =G41+Drivers!$C$295-Drivers!$C$298 -> 792.3 | I41: =H41+Drivers!$C$296-Drivers!$C$299 -> 812.3 | J41: =I41+Drivers!$C$528-Drivers!$C$533 -> 832.3 | K41: =J41+Drivers!$C$529-Drivers!$C$534 -> 852.3 | L41: =K41+Drivers!$C$530-Drivers!$C$535 -> 872.3 | M41: =L41+Drivers!$C$531-Drivers!$C$536 -> 892.3 | N41: =M41+Drivers!$C$532-Drivers!$C$537 -> 912.3
C42: Goodwill | D42: 126.3 | E42: 126.3 | F42: 126.3 | G42: 126.3 | H42: 126.3 | I42: 126.3 | J42: 126.3 | K42: 126.3 | L42: 126.3 | M42: 126.3 | N42: 126.3
C43: Other Assets | D43: 400.5 | E43: =D43 -> 400.5 | F43: =E43 -> 400.5 | G43: =F43 -> 400.5 | H43: =G43 -> 400.5 | I43: =H43 -> 400.5 | J43: =I43 -> 400.5 | K43: =J43 -> 400.5 | L43: =K43 -> 400.5 | ... N43: =M43 -> 400.5
C44: Total Assets | D44: =D36+D37+D38+D39+D40+D41+D42+D43 -> 17999.5 | E44: =E36+E37+E38+E39+E40+E41+E42+E43 -> 18248.296 | F44: =F36+F37+F38+F39+F40+F41+F42+F43 -> 18801.037 | G44: =G36+G37+G38+G39+G40+G41+G42+G43 -> 19353.327 | H44: =H36+H37+H38+H39+H40+H41+H42+H43 -> 19904.062 | I44: =I36+I37+I38+I39+I40+I41+I42+I43 -> 20452.588 | J44: =J36+J37+J38+J39+J40+J41+J42+J43 -> 20790.097 | K44: =K36+K37+K38+K39+K40+K41+K42+K43 -> 21084.669 | ... N44: =N36+N37+N38+N39+N40+N41+N42+N43 -> 21986.071
C46: Accounts payable and accrued expenses | D46: 318.4 | E46: =D46*(E17/D17) -> 436.41046 | F46: =E46*(F17/E17) -> 452.14832 | G46: =F46*(G17/F17) -> 467.19247 | H46: =G46*(H17/G17) -> 479.8467 | I46: =H46*(I17/H17) -> 489.10619 | J46: =I46*(J17/I17) -> 496.80377 | K46: =J46*(K17/J17) -> 505.4673 | L46: =K46*(L17/K17) -> 514.37747 | ... N46: =M46*(N17/M17) -> 532.9746
C47: Total debt (from Debt sheet) | D47: 12533.9 | E47: ='Debt & Interest'!E27 -> 12516.956 | F47: ='Debt & Interest'!F27 -> 13017.969 | G47: ='Debt & Interest'!G27 -> 13493.695 | H47: ='Debt & Interest'!H27 -> 13952.432 | I47: ='Debt & Interest'!I27 -> 14418.254 | J47: ='Debt & Interest'!J27 -> 14661.143 | K47: ='Debt & Interest'!K27 -> 14851.717 | L47: ='Debt & Interest'!L27 -> 15035.772 | ... N47: ='Debt & Interest'!N27 -> 15386.04
C48: Operating lease obligations | D48: 154.3 | E48: 143.8 | F48: 135 | G48: 127 | H48: 119 | I48: 111 | J48: 103 | K48: 95 | L48: 87 | M48: 79 | N48: 71
C49: Deferred Income Taxes | D49: 1195.7 | E49: =D49*(1+Drivers!$C$134) -> 1207.657 | F49: =E49*(1+Drivers!$C$134) -> 1219.7336 | G49: =F49*(1+Drivers!$C$134) -> 1231.9309 | H49: =G49*(1+Drivers!$C$134) -> 1244.2502 | I49: =H49*(1+Drivers!$C$134) -> 1256.6927 | J49: =I49*(1+Drivers!$C$134) -> 1269.2596 | K49: =J49*(1+Drivers!$C$134) -> 1281.9522 | L49: =K49*(1+Drivers!$C$134) -> 1294.7718 | ... N49: =M49*(1+Drivers!$C$134) -> 1320.7967
C50: Other Liabilities | D50: 162.1 | E50: =D50*(E17/D17) -> 222.18007 | F50: =E50*(F17/E17) -> 230.19234 | G50: =F50*(G17/F17) -> 237.85144 | H50: =G50*(H17/G17) -> 244.29381 | I50: =H50*(I17/H17) -> 249.00789 | J50: =I50*(J17/I17) -> 252.9268 | K50: =J50*(K17/J17) -> 257.33746 | L50: =K50*(L17/K17) -> 261.8737 | ... N50: =M50*(N17/M17) -> 271.34165
C51: Total Liabilities | D51: =D46+D47+D48+D49+D50 -> 14364.4 | E51: =E46+E47+E48+E49+E50 -> 14527.004 | F51: =F46+F47+F48+F49+F50 -> 15055.043 | G51: =G46+G47+G48+G49+G50 -> 15557.67 | H51: =H46+H47+H48+H49+H50 -> 16039.823 | I51: =I46+I47+I48+I49+I50 -> 16524.061 | J51: =J46+J47+J48+J49+J50 -> 16783.133 | K51: =K46+K47+K48+K49+K50 -> 16991.474 | ... N51: =N46+N47+N48+N49+N50 -> 17582.153
C53: Common stock | D53: 42.9 | E53: =D53 -> 42.9 | F53: =E53 -> 42.9 | G53: =F53 -> 42.9 | H53: =G53 -> 42.9 | I53: =H53 -> 42.9 | J53: =I53 -> 42.9 | K53: =J53 -> 42.9 | L53: =K53 -> 42.9 | ... N53: =M53 -> 42.9
C54: Additional paid in capital | D54: 875.4 | E54: =D54+Drivers!$C$83-('GABX Mini P&L'!G31-IF('GABX Mini P&L'!G30>0,MIN(Drivers!$C$267,MAX(0,(D59+'GABX Mini P&L'!G27)-IF('GABX Mini P&L'!G30>0,MIN(Drivers!$C$84*'GABX Mini P&L'!G30,MAX(0,(D59+'GABX Mini P&L'!G27))),0))),0)) -> 880 | F54: =E54+Drivers!$C$83-('GABX Mini P&L'!H31-IF('GABX Mini P&L'!H30>0,MIN(Drivers!$C$268,MAX(0,(E59+'GABX Mini P&L'!H27)-IF('GABX Mini P&L'!H30>0,MIN(Drivers!$C$85*'GABX Mini P&L'!H30,MAX(0,(E59+'GABX Mini P&L'!H27))),0))),0)) -> 861.66337 | G54: =F54+Drivers!$C$83-('GABX Mini P&L'!I31-IF('GABX Mini P&L'!I30>0,MIN(Drivers!$C$268,MAX(0,(F59+'GABX Mini P&L'!I27)-IF('GABX Mini P&L'!I30>0,MIN(Drivers!$C$285*'GABX Mini P&L'!I30,MAX(0,(F59+'GABX Mini P&L'!I27))),0))),0)) -> 843.32673 | H54: =G54+Drivers!$C$83-('GABX Mini P&L'!J31-IF('GABX Mini P&L'!J30>0,MIN(Drivers!$C$268,MAX(0,(G59+'GABX Mini P&L'!J27)-IF('GABX Mini P&L'!J30>0,MIN(Drivers!$C$286*'GABX Mini P&L'!J30,MAX(0,(G59+'GABX Mini P&L'!J27))),0))),0)) -> 824.9901 | I54: =H54+Drivers!$C$83-('GABX Mini P&L'!K31-IF('GABX Mini P&L'!K30>0,MIN(Drivers!$C$268,MAX(0,(H59+'GABX Mini P&L'!K27)-IF('GABX Mini P&L'!K30>0,MIN(Drivers!$C$287*'GABX Mini P&L'!K30,MAX(0,(H59+'GABX Mini P&L'!K27))),0))),0)) -> 806.65347 | J54: =I54+Drivers!$C$83-('GABX Mini P&L'!L31-IF('GABX Mini P&L'!L30>0,MIN(Drivers!$C$268,MAX(0,(I59+'GABX Mini P&L'!L27)-IF('GABX Mini P&L'!L30>0,MIN(Drivers!$C$518*'GABX Mini P&L'!L30,MAX(0,(I59+'GABX Mini P&L'!L27))),0))),0)) -> 788.31683 | K54: =J54+Drivers!$C$83-('GABX Mini P&L'!M31-IF('GABX Mini P&L'!M30>0,MIN(Drivers!$C$268,MAX(0,(J59+'GABX Mini P&L'!M27)-IF('GABX Mini P&L'!M30>0,MIN(Drivers!$C$519*'GABX Mini P&L'!M30,MAX(0,(J59+'GABX Mini P&L'!M27))),0))),0)) -> 769.9802 | L54: =K54+Drivers!$C$83-('GABX Mini P&L'!N31-IF('GABX Mini P&L'!N30>0,MIN(Drivers!$C$268,MAX(0,(K59+'GABX Mini P&L'!N27)-IF('GABX Mini P&L'!N30>0,MIN(Drivers!$C$520*'GABX Mini P&L'!N30,MAX(0,(K59+'GABX Mini P&L'!N27))),0))),0)) -> 751.64356 | M54: =L54+Drivers!$C$83-('GABX Mini P&L'!O31-IF('GABX Mini P&L'!O30>0,MIN(Drivers!$C$268,MAX(0,(L59+'GABX Mini P&L'!O27)-IF('GABX Mini P&L'!O30>0,MIN(Drivers!$C$521*'GABX Mini P&L'!O30,MAX(0,(L59+'GABX Mini P&L'!O27))),0))),0)) -> 733.30693 | N54: =M54+Drivers!$C$83-('GABX Mini P&L'!P31-IF('GABX Mini P&L'!P30>0,MIN(Drivers!$C$268,MAX(0,(M59+'GABX Mini P&L'!P27)-IF('GABX Mini P&L'!P30>0,MIN(Drivers!$C$522*'GABX Mini P&L'!P30,MAX(0,(M59+'GABX Mini P&L'!P27))),0))),0)) -> 643.97997
C55: Retained earnings | D55: 3451.2 | E55: =D55+E31-Drivers!$C$79*E32 -> 3725.0422 | F55: =E55+F31-Drivers!$C$80*F32 -> 3986.9887 | G55: =F55+G31-Drivers!$C$279*G32 -> 4262.4864 | H55: =G55+H31-Drivers!$C$280*H32 -> 4550.587 | I55: =H55+I31-Drivers!$C$281*I32 -> 4832.9875 | J55: =I55+J31+J86 -> 5127.6033 | K55: =J55+K31+K86 -> 5426.9424 | L55: =K55+L31+L86 -> 5735.2002 | M55: =L55+M31+M86 -> 6054.2372 | N55: =M55+N31+N86 -> 6385.9542
C56: Accumulated OCI | D56: -104.6 | E56: =D56 -> -104.6 | F56: =E56 -> -104.6 | G56: =F56 -> -104.6 | H56: =G56 -> -104.6 | I56: =H56 -> -104.6 | J56: =I56 -> -104.6 | K56: =J56 -> -104.6 | L56: =K56 -> -104.6 | ... N56: =M56 -> -104.6
C57: Treasury stock | D57: -1514.4 | E57: =D57-Drivers!$C$81 -> -1614.4 | F57: =E57-Drivers!$C$82 -> -1714.4 | G57: =F57-Drivers!$C$282 -> -1814.4 | H57: =G57-Drivers!$C$283 -> -1914.4 | I57: =H57-Drivers!$C$284 -> -2014.4 | J57: =I57+J85 -> -2118.7255 | K57: =J57+K85 -> -2224.7236 | L57: =K57+L85 -> -2333.8798 | M57: =L57+M85 -> -2446.853 | N57: =M57+N85 -> -2564.3164
C58: Total GATX Shareholders Equity | D58: =D53+D54+D55+D56+D57 -> 2750.5 | E58: =E53+E54+E55+E56+E57 -> 2928.9422 | F58: =F53+F54+F55+F56+F57 -> 3072.5521 | G58: =G53+G54+G55+G56+G57 -> 3229.7131 | H58: =H53+H54+H55+H56+H57 -> 3399.4771 | I58: =I53+I54+I55+I56+I57 -> 3563.541 | J58: =J53+J54+J55+J56+J57 -> 3735.4947 | K58: =K53+K54+K55+K56+K57 -> 3910.499 | ... N58: =N53+N54+N55+N56+N57 -> 4403.9178
C59: Non-Controlling Interest | D59: 884.6 | E59: =(D59+'GABX Mini P&L'!G27)-IF('GABX Mini P&L'!G30>0,MIN(Drivers!$C$84*'GABX Mini P&L'!G30,MAX(0,(D59+'GABX Mini P&L'!G27))),0)-IF('GABX Mini P&L'!G30>0,MIN(Drivers!$C$267,MAX(0,(D59+'GABX Mini P&L'!G27)-IF('GABX Mini P&L'!G30>0,MIN(Drivers!$C$84*'GABX Mini P&L'!G30,MAX(0,(D59+'GABX Mini P&L'!G27))),0))),0) -> 792.35004 | F59: =(E59+'GABX Mini P&L'!H27)-IF('GABX Mini P&L'!H30>0,MIN(Drivers!$C$85*'GABX Mini P&L'!H30,MAX(0,(E59+'GABX Mini P&L'!H27))),0)-IF('GABX Mini P&L'!H30>0,MIN(Drivers!$C$268,MAX(0,(E59+'GABX Mini P&L'!H27)-IF('GABX Mini P&L'!H30>0,MIN(Drivers!$C$85*'GABX Mini P&L'!H30,MAX(0,(E59+'GABX Mini P&L'!H27))),0))),0) -> 673.44236 | G59: =(F59+'GABX Mini P&L'!I27)-IF('GABX Mini P&L'!I30>0,MIN(Drivers!$C$285*'GABX Mini P&L'!I30,MAX(0,(F59+'GABX Mini P&L'!I27))),0)-IF('GABX Mini P&L'!I30>0,MIN(Drivers!$C$268,MAX(0,(F59+'GABX Mini P&L'!I27)-IF('GABX Mini P&L'!I30>0,MIN(Drivers!$C$285*'GABX Mini P&L'!I30,MAX(0,(F59+'GABX Mini P&L'!I27))),0))),0) -> 565.94411 | H59: =(G59+'GABX Mini P&L'!J27)-IF('GABX Mini P&L'!J30>0,MIN(Drivers!$C$286*'GABX Mini P&L'!J30,MAX(0,(G59+'GABX Mini P&L'!J27))),0)-IF('GABX Mini P&L'!J30>0,MIN(Drivers!$C$268,MAX(0,(G59+'GABX Mini P&L'!J27)-IF('GABX Mini P&L'!J30>0,MIN(Drivers!$C$286*'GABX Mini P&L'!J30,MAX(0,(G59+'GABX Mini P&L'!J27))),0))),0) -> 464.76236 | I59: =(H59+'GABX Mini P&L'!K27)-IF('GABX Mini P&L'!K30>0,MIN(Drivers!$C$287*'GABX Mini P&L'!K30,MAX(0,(H59+'GABX Mini P&L'!K27))),0)-IF('GABX Mini P&L'!K30>0,MIN(Drivers!$C$268,MAX(0,(H59+'GABX Mini P&L'!K27)-IF('GABX Mini P&L'!K30>0,MIN(Drivers!$C$287*'GABX Mini P&L'!K30,MAX(0,(H59+'GABX Mini P&L'!K27))),0))),0) -> 364.98568 | J59: =(I59+'GABX Mini P&L'!L27)-IF('GABX Mini P&L'!L30>0,MIN(Drivers!$C$518*'GABX Mini P&L'!L30,MAX(0,(I59+'GABX Mini P&L'!L27))),0)-IF('GABX Mini P&L'!L30>0,MIN(Drivers!$C$268,MAX(0,(I59+'GABX Mini P&L'!L27)-IF('GABX Mini P&L'!L30>0,MIN(Drivers!$C$518*'GABX Mini P&L'!L30,MAX(0,(I59+'GABX Mini P&L'!L27))),0))),0) -> 271.46887 | K59: =(J59+'GABX Mini P&L'!M27)-IF('GABX Mini P&L'!M30>0,MIN(Drivers!$C$519*'GABX Mini P&L'!M30,MAX(0,(J59+'GABX Mini P&L'!M27))),0)-IF('GABX Mini P&L'!M30>0,MIN(Drivers!$C$268,MAX(0,(J59+'GABX Mini P&L'!M27)-IF('GABX Mini P&L'!M30>0,MIN(Drivers!$C$519*'GABX Mini P&L'!M30,MAX(0,(J59+'GABX Mini P&L'!M27))),0))),0) -> 182.69642 | L59: =(K59+'GABX Mini P&L'!N27)-IF('GABX Mini P&L'!N30>0,MIN(Drivers!$C$520*'GABX Mini P&L'!N30,MAX(0,(K59+'GABX Mini P&L'!N27))),0)-IF('GABX Mini P&L'!N30>0,MIN(Drivers!$C$268,MAX(0,(K59+'GABX Mini P&L'!N27)-IF('GABX Mini P&L'!N30>0,MIN(Drivers!$C$520*'GABX Mini P&L'!N30,MAX(0,(K59+'GABX Mini P&L'!N27))),0))),0) -> 97.108014 | M59: =(L59+'GABX Mini P&L'!O27)-IF('GABX Mini P&L'!O30>0,MIN(Drivers!$C$521*'GABX Mini P&L'!O30,MAX(0,(L59+'GABX Mini P&L'!O27))),0)-IF('GABX Mini P&L'!O30>0,MIN(Drivers!$C$268,MAX(0,(L59+'GABX Mini P&L'!O27)-IF('GABX Mini P&L'!O30>0,MIN(Drivers!$C$521*'GABX Mini P&L'!O30,MAX(0,(L59+'GABX Mini P&L'!O27))),0))),0) -> 13.097138 | N59: =(M59+'GABX Mini P&L'!P27)-IF('GABX Mini P&L'!P30>0,MIN(Drivers!$C$522*'GABX Mini P&L'!P30,MAX(0,(M59+'GABX Mini P&L'!P27))),0)-IF('GABX Mini P&L'!P30>0,MIN(Drivers!$C$268,MAX(0,(M59+'GABX Mini P&L'!P27)-IF('GABX Mini P&L'!P30>0,MIN(Drivers!$C$522*'GABX Mini P&L'!P30,MAX(0,(M59+'GABX Mini P&L'!P27))),0))),0) -> 0
C60: Total Equity | D60: =D58+D59 -> 3635.1 | E60: =E58+E59 -> 3721.2922 | F60: =F58+F59 -> 3745.9944 | G60: =G58+G59 -> 3795.6572 | H60: =H58+H59 -> 3864.2395 | I60: =I58+I59 -> 3928.5267 | J60: =J58+J59 -> 4006.9635 | K60: =K58+K59 -> 4093.1954 | ... N60: =N58+N59 -> 4403.9178
C61: Total Liabilities and Equity | D61: =D51+D60 -> 17999.5 | E61: =E51+E60 -> 18248.296 | F61: =F51+F60 -> 18801.037 | G61: =G51+G60 -> 19353.327 | H61: =H51+H60 -> 19904.062 | I61: =I51+I60 -> 20452.588 | J61: =J51+J60 -> 20790.097 | K61: =K51+K60 -> 21084.669 | ... N61: =N51+N60 -> 21986.071
A62: x | C62: BALANCE CHECK (must be 0) | D62: =D44-D61 -> 0 | E62: =E44-E61 -> 0 | F62: =F44-F61 -> 0 | G62: =G44-G61 -> 0 | H62: =H44-H61 -> 0 | I62: =I44-I61 -> 0 | J62: =J44-J61 -> 0 | K62: =K44-K61 -> 0 | ... N62: =N44-N61 -> 0
A64: x | C64: CASH FLOW STATEMENT ($M)
C65: Net income | D65: 333.3 | E65: =E29 -> 385.36922 | F65: =F29 -> 383.77697 | G65: =G29 -> 400.21937 | H65: =H29 -> 410.67198 | I65: =I29 -> 397.95967 | J65: =J29 -> 413.4194 | K65: =K29 -> 417.42769 | L65: =L29 -> 425.4398 | ... N65: =N29 -> 444.05234
C66: D&A (add back = -Depr on IS, matches PPE roll) | D66: 452.3 | E66: =-E19 -> 671.4 | F66: =-F19 -> 720 | G66: =-G19 -> 720 | H66: =-H19 -> 720 | I66: =-I19 -> 720 | J66: =-J19 -> 720 | K66: =-K19 -> 732.8353 | L66: =-L19 -> 743.92318 | ... N66: =-N19 -> 766.43269
C67: Net gains on sales of assets (subtract) | D67: -140 | E67: =-E23 -> -210.5 | F67: =-F23 -> -210.5 | G67: =-G23 -> -210.49926 | H67: =-H23 -> -210.49926 | I67: =-I23 -> -210.49926 | J67: =-J23 -> -217.86674 | K67: =-K23 -> -220.40246 | L67: =-L23 -> -223.02694 | ... N67: =-N23 -> -228.55467
C68: Deferred tax change (Δ DT BS) | D68: 53.2 | E68: =E49-D49 -> 11.957 | F68: =F49-E49 -> 12.07657 | G68: =G49-F49 -> 12.197336 | H68: =H49-G49 -> 12.319309 | I68: =I49-H49 -> 12.442502 | J68: =J49-I49 -> 12.566927 | K68: =K49-J49 -> 12.692596 | L68: =L49-K49 -> 12.819522 | ... N68: =N49-M49 -> 13.077195
C69: Δ Working capital (AP + OthL − Recv) | D69: -11.8 | E69: =(E46-D46)+(E50-D50)-(E38-D38) -> 101.29478 | F69: =(F46-E46)+(F50-E50)-(F38-E38) -> 13.508658 | G69: =(G46-F46)+(G50-F50)-(G38-F38) -> 12.913214 | H69: =(H46-G46)+(H50-G50)-(H38-G38) -> 10.861809 | I69: =(I46-H46)+(I50-H50)-(I38-H38) -> 7.9479246 | J69: =(J46-I46)+(J50-I50)-(J38-I38) -> 6.6072552 | K69: =(K46-J46)+(K50-J50)-(K38-J38) -> 7.4363714 | L69: =(L46-K46)+(L50-K50)-(L38-K38) -> 7.6480829 | ... N69: =(N46-M46)+(N50-M50)-(N38-M38) -> 8.0949874
C70: Share of affiliates net of dividends (CFO subtract) | D70: -67.3 | E70: =-(E41-D41) -> 0 | F70: =-(F41-E41) -> -20 | G70: =-(G41-F41) -> -20 | H70: =-(H41-G41) -> -20 | I70: =-(I41-H41) -> -20 | J70: =-(J41-I41) -> -20 | K70: =-(K41-J41) -> -20 | L70: =-(L41-K41) -> -20 | ... N70: =-(N41-M41) -> -20
C71: Share-based comp (add-back, matches Δ APIC) | D71: 25 | E71: =Drivers!$C$83 -> 28 | F71: =Drivers!$C$83 -> 28 | G71: =Drivers!$C$83 -> 28 | H71: =Drivers!$C$83 -> 28 | I71: =Drivers!$C$83 -> 28 | J71: =Drivers!$C$83 -> 28 | K71: =Drivers!$C$83 -> 28 | L71: =Drivers!$C$83 -> 28 | ... N71: =Drivers!$C$83 -> 28
C72: ROU + OL amortization (non-cash op lease) | D72: 0 | E72: =-(E40-D40)+(E48-D48) -> -0.6 | F72: =-(F40-E40)+(F48-E48) -> -1.3 | G72: =-(G40-F40)+(G48-F48) -> -0.5 | H72: =-(H40-G40)+(H48-G48) -> -0.5 | I72: =-(I40-H40)+(I48-H48) -> -0.5 | J72: =-(J40-I40)+(J48-I48) -> -0.5 | K72: =-(K40-J40)+(K48-J48) -> -0.5 | L72: =-(L40-K40)+(L48-K48) -> -0.5 | ... N72: =-(N40-M40)+(N48-M48) -> -0.5
C73: CFO | D73: =SUM(D65:D72) -> 644.7 | E73: =SUM(E65:E72) -> 986.92101 | F73: =SUM(F65:F72) -> 925.5622 | G73: =SUM(G65:G72) -> 942.33066 | H73: =SUM(H65:H72) -> 950.85383 | I73: =SUM(I65:I72) -> 935.35084 | J73: =SUM(J65:J72) -> 942.22685 | K73: =SUM(K65:K72) -> 957.4895 | ... N73: =SUM(N65:N72) -> 1010.6025
C75: Capex (organic) | D75: -1316.7 | E75: =-Drivers!$C$121 -> -1041 | F75: =-Drivers!$C$122 -> -1400 | G75: =-Drivers!$C$300 -> -1400 | H75: =-Drivers!$C$301 -> -1400 | I75: =-Drivers!$C$302 -> -1400 | J75: =-Drivers!$C$563 -> -1190 | K75: =-Drivers!$C$564 -> -1159.27 | L75: =-Drivers!$C$565 -> -1173.1223 | M75: =-Drivers!$C$566 -> -1187.113 | N75: =-Drivers!$C$567 -> -1201.2437
C76: Wells Fargo acquisition (2026 CFI outflow) | D76: 0 | E76: =-Drivers!$C$123 -> -4200 | F76: 0 | G76: 0 | H76: 0 | I76: 0 | J76: 0 | K76: 0 | L76: 0 | M76: 0 | N76: 0
C77: Portfolio proceeds (dispositions of assets) | D77: 311.8 | E77: =E23+Drivers!$C$86 -> 360.5 | F77: =F23+Drivers!$C$87 -> 360.5 | G77: =G23+Drivers!$C$288 -> 360.49926 | H77: =H23+Drivers!$C$289 -> 360.49926 | I77: =I23+Drivers!$C$290 -> 360.49926 | J77: =J23+Drivers!$C$553 -> 367.86674 | K77: =K23+Drivers!$C$554 -> 370.40246 | L77: =L23+Drivers!$C$555 -> 373.02694 | M77: =M23+Drivers!$C$556 -> 375.74327 | N77: =N23+Drivers!$C$557 -> 378.55467
C78: Other investing | D78: -11.9 | E78: 0 | F78: 0 | G78: 0 | H78: 0 | I78: 0 | J78: 0 | K78: 0 | L78: 0 | M78: 0 | N78: 0
C79: CFI | D79: =D75+D76+D77+D78 -> -1016.8 | E79: =E75+E76+E77+E78 -> -4880.5 | F79: =F75+F76+F77+F78 -> -1039.5 | G79: =G75+G76+G77+G78 -> -1039.5007 | H79: =H75+H76+H77+H78 -> -1039.5007 | I79: =I75+I76+I77+I78 -> -1039.5007 | J79: =J75+J76+J77+J78 -> -822.13326 | K79: =K75+K76+K77+K78 -> -788.86759 | ... N79: =N75+N76+N77+N78 -> -822.68902
C81: Debt refinancing (maturity + refi from Debt sheet) | D81: 4178.5 | E81: 0 | F81: 0 | G81: 0 | H81: 0 | I81: 0 | J81: 0 | K81: 0 | L81: 0 | M81: 0 | N81: 0
C82: Net new debt issuance (revolver plug) | D82: 0 | E82: =((E36+E37)-(D36+D37))-(E73+E79+E81+E83+E84+E85+E86+E87+E88) -> -16.944005 | F82: =((F36+F37)-(E36+E37))-(F73+F79+F81+F83+F84+F85+F86+F87+F88) -> 501.01258 | G82: =((G36+G37)-(F36+F37))-(G73+G79+G81+G83+G84+G85+G86+G87+G88) -> 475.72665 | H82: =((H36+H37)-(G36+G37))-(H73+H79+H81+H83+H84+H85+H86+H87+H88) -> 458.73662 | I82: =((I36+I37)-(H36+H37))-(I73+I79+I81+I83+I84+I85+I86+I87+I88) -> 465.82236 | J82: =((J36+J37)-(I36+I37))-(J73+J79+J81+J83+J84+J85+J86+J87+J88) -> 242.88898 | K82: =((K36+K37)-(J36+J37))-(K73+K79+K81+K83+K84+K85+K86+K87+K88) -> 190.57389 | L82: =((L36+L37)-(K36+K37))-(L73+L79+L81+L83+L84+L85+L86+L87+L88) -> 184.05498 | ... N82: =((N36+N37)-(M36+M37))-(N73+N79+N81+N83+N84+N85+N86+N87+N88) -> 172.30919
C83: GABX tranche cash to Brookfield (v9 Sec 2 — call-option strikes) | D83: 0 | E83: =-'GABX Mini P&L'!G31 -> -66.2 | F83: =-'GABX Mini P&L'!H31 -> -131.08911 | G83: =-'GABX Mini P&L'!I31 -> -131.08911 | H83: =-'GABX Mini P&L'!J31 -> -131.08911 | I83: =-'GABX Mini P&L'!K31 -> -131.08911 | J83: =-'GABX Mini P&L'!L31 -> -131.08911 | K83: =-'GABX Mini P&L'!M31 -> -131.08911 | L83: =-'GABX Mini P&L'!N31 -> -131.08911 | ... N83: =-'GABX Mini P&L'!P31 -> -131.08911
C84: Restricted cash release (=0; captured in Cash+Restricted reconciliation) | D84: 0 | E84: 0 | F84: 0 | G84: 0 | H84: 0 | I84: 0 | J84: 0 | K84: 0 | L84: 0 | M84: 0 | N84: 0
C85: Stock repurchases (buyback) | D85: -65 | E85: =-Drivers!$C$81 -> -100 | F85: =-Drivers!$C$82 -> -100 | G85: =-Drivers!$C$282 -> -100 | H85: =-Drivers!$C$283 -> -100 | I85: =-Drivers!$C$284 -> -100 | J85: =-Drivers!$C$580*J31 -> -104.32551 | K85: =-Drivers!$C$580*K31 -> -105.99804 | L85: =-Drivers!$C$580*L31 -> -109.15624 | M85: =-Drivers!$C$580*M31 -> -112.97325 | N85: =-Drivers!$C$580*N31 -> -117.46333
C86: Dividends paid | D86: -89.8 | E86: =-Drivers!$C$79*Drivers!$C$77 -> -94.512 | F86: =-Drivers!$C$80*Drivers!$C$78 -> -96.520665 | G86: =-Drivers!$C$279*Drivers!$C$276 -> -95.002467 | H86: =-Drivers!$C$280*Drivers!$C$277 -> -93.535609 | I86: =-Drivers!$C$281*Drivers!$C$278 -> -92.118354 | J86: =-Drivers!$C$579*J31 -> -96.102945 | K86: =-Drivers!$C$579*K31 -> -97.64365 | L86: =-Drivers!$C$579*L31 -> -100.55293 | M86: =-Drivers!$C$579*M31 -> -104.0691 | N86: =-Drivers!$C$579*N31 -> -108.20528
C87: GABX NCI equity contribution (2025 only) | D87: 899 | E87: 0 | F87: 0 | G87: 0 | H87: 0 | I87: 0 | J87: 0 | K87: 0 | L87: 0 | M87: 0 | N87: 0
C88: Distributions to NCI (Brookfield) | D88: 0 | E88: =-IF('GABX Mini P&L'!G30>0,MIN(Drivers!$C$84*'GABX Mini P&L'!G30,MAX(0,(D59+'GABX Mini P&L'!G27))),0) -> -66.465 | F88: =-IF('GABX Mini P&L'!H30>0,MIN(Drivers!$C$85*'GABX Mini P&L'!H30,MAX(0,(E59+'GABX Mini P&L'!H27))),0) -> -59.465 | G88: =-IF('GABX Mini P&L'!I30>0,MIN(Drivers!$C$285*'GABX Mini P&L'!I30,MAX(0,(F59+'GABX Mini P&L'!I27))),0) -> -52.465 | H88: =-IF('GABX Mini P&L'!J30>0,MIN(Drivers!$C$286*'GABX Mini P&L'!J30,MAX(0,(G59+'GABX Mini P&L'!J27))),0) -> -45.465 | I88: =-IF('GABX Mini P&L'!K30>0,MIN(Drivers!$C$287*'GABX Mini P&L'!K30,MAX(0,(H59+'GABX Mini P&L'!K27))),0) -> -38.465 | J88: =-IF('GABX Mini P&L'!L30>0,MIN(Drivers!$C$518*'GABX Mini P&L'!L30,MAX(0,(I59+'GABX Mini P&L'!L27))),0) -> -31.465 | K88: =-IF('GABX Mini P&L'!M30>0,MIN(Drivers!$C$519*'GABX Mini P&L'!M30,MAX(0,(J59+'GABX Mini P&L'!M27))),0) -> -24.465 | L88: =-IF('GABX Mini P&L'!N30>0,MIN(Drivers!$C$520*'GABX Mini P&L'!N30,MAX(0,(K59+'GABX Mini P&L'!N27))),0) -> -17.465 | M88: =-IF('GABX Mini P&L'!O30>0,MIN(Drivers!$C$521*'GABX Mini P&L'!O30,MAX(0,(L59+'GABX Mini P&L'!O27))),0) -> -10.465 | N88: =-IF('GABX Mini P&L'!P30>0,MIN(Drivers!$C$522*'GABX Mini P&L'!P30,MAX(0,(M59+'GABX Mini P&L'!P27))),0) -> -3.465
C89: CFF | D89: =D81+D82+D83+D84+D85+D86+D87+D88 -> 4922.7 | E89: =E81+E82+E83+E84+E85+E86+E87+E88 -> -344.12101 | F89: =F81+F82+F83+F84+F85+F86+F87+F88 -> 113.9378 | G89: =G81+G82+G83+G84+G85+G86+G87+G88 -> 97.170078 | H89: =H81+H82+H83+H84+H85+H86+H87+H88 -> 88.646903 | I89: =I81+I82+I83+I84+I85+I86+I87+I88 -> 104.1499 | J89: =J81+J82+J83+J84+J85+J86+J87+J88 -> -120.09359 | K89: =K81+K82+K83+K84+K85+K86+K87+K88 -> -168.62191 | ... N89: =N81+N82+N83+N84+N85+N86+N87+N88 -> -187.91353
C91: Net change in Cash + Restricted Cash | D91: =D73+D79+D89 -> 4550.6 | E91: =E73+E79+E89 -> -4237.7 | F91: =F73+F79+F89 -> 0 | G91: =G73+G79+G89 -> 0 | H91: =H73+H79+H89 -> 0 | I91: =I73+I79+I89 -> 0 | J91: =J73+J79+J89 -> 0 | K91: =K73+K79+K89 -> 0 | ... N91: =N73+N79+N89 -> 0
C92: Cash + Restricted BOP | D92: 401.8 | E92: =D36+D37 -> 4984.9 | F92: =E36+E37 -> 747.2 | G92: =F36+F37 -> 747.2 | H92: =G36+G37 -> 747.2 | I92: =H36+H37 -> 747.2 | J92: =I36+I37 -> 747.2 | K92: =J36+J37 -> 747.2 | L92: =K36+K37 -> 747.2 | ... N92: =M36+M37 -> 747.2
C93: Cash + Restricted EOP (CFS = BS) | D93: 4984.9 | E93: =E92+E91 -> 747.2 | F93: =F92+F91 -> 747.2 | G93: =G92+G91 -> 747.2 | H93: =H92+H91 -> 747.2 | I93: =I92+I91 -> 747.2 | J93: =J92+J91 -> 747.2 | K93: =K92+K91 -> 747.2 | L93: =L92+L91 -> 747.2 | ... N93: =N92+N91 -> 747.2
C94: BS Cash + Restricted total (verification) | D94: =D36+D37 -> 4984.9 | E94: =E36+E37 -> 747.2 | F94: =F36+F37 -> 747.2 | G94: =G36+G37 -> 747.2 | H94: =H36+H37 -> 747.2 | I94: =I36+I37 -> 747.2 | J94: =J36+J37 -> 747.2 | K94: =K36+K37 -> 747.2 | ... N94: =N36+N37 -> 747.2
C96: v17 ITEM 2 CHECKS (2026-09-26) — Terminal steady state 2031E-2035E
A97: x | C97: EPS CAGR 2030E→2035E (= (L21/G21)^(1/5) - 1) | D97: =(N33/I33)^(1/Drivers!$C$582)-1 -> 0.049225286
C98: Terminal g (Drivers!B397) | D98: =Drivers!$C$397 -> 0.035
C99: ROE 2030E (NI attrib G19 / avg equity (F46+G46)/2) | D99: =I31/((H58+I58)/2) -> 0.10757372
C100: Payout ratio 2030E (Div+Buyback)/NI = (-G74-G73)/G19 | D100: =(-I86-I85)/I31 -> 0.51297375
C101: Retention 2030E = 1 - Payout | D101: =1-D100 -> 0.48702625
C102: ROE × retention (max sustainable growth in constant capital structure) | D102: =D99*D101 -> 0.052391225
C103: CAGR sits in [g, ROE×retention]? (should be TRUE) | D103: =IF(AND(D97>=D98, D97<=D102), "TRUE", "FALSE") -> TRUE
C104: D/(D+E) ratio target = 2030E value | D104: =I47/(I47+I58) -> 0.80182507
C105: D/(D+E) actual 2031E-2035E (target held approximately if within ±2% of B92) | J105: =J47/(J47+J58) -> 0.79694688 | K105: =K47/(K47+K58) -> 0.79157585 | L105: =L47/(L47+L58) -> 0.78610047 | M105: =M47/(M47+M58) -> 0.78048263 | N105: =N47/(N47+N58) -> 0.77746705
C106: D/(D+E) delta from 2030E target (H-L) | J106: =J105-$D$104 -> -0.004878187 | K106: =K105-$D$104 -> -0.010249223 | L106: =L105-$D$104 -> -0.015724596 | M106: =M105-$D$104 -> -0.021342438 | N106: =N105-$D$104 -> -0.024358023
C108: v23 ITEM 1 GATES (2026-09-28) — Terminal state 2031E-2035E bottom-up
C109: Implied LPI 2031E-2035E (Legacy Cohort J46:N46) | J109: ='Legacy Cohort Model'!J46 -> -0.0098957236 | K109: ='Legacy Cohort Model'!K46 -> -0.0061228446 | L109: ='Legacy Cohort Model'!L46 -> -0.0061300157 | M109: ='Legacy Cohort Model'!M46 -> -0.0061300021 | N109: ='Legacy Cohort Model'!N46 -> -0.0061300021
C110: Terminal_LPI driver (Drivers!C704) | D110: =Drivers!$C$704 -> 0.02
C111: Total cars: Legacy cohorts + base + Acquired Pool | I111: =SUM('Legacy Cohort Model'!I21:I26)+'Acquired Pool'!I19 -> 199128 | J111: =SUM('Legacy Cohort Model'!J21:J26)+'Acquired Pool'!J19 -> 201119.28 | K111: =SUM('Legacy Cohort Model'!K21:K26)+'Acquired Pool'!K19 -> 203130.47 | L111: =SUM('Legacy Cohort Model'!L21:L26)+'Acquired Pool'!L19 -> 205161.78 | M111: =SUM('Legacy Cohort Model'!M21:M26)+'Acquired Pool'!M19 -> 207213.4 | N111: =SUM('Legacy Cohort Model'!N21:N26)+'Acquired Pool'!N19 -> 209285.53
C112: Car-count YoY growth | J112: =IFERROR(J111/I111-1, 0) -> 0.01 | K112: =IFERROR(K111/J111-1, 0) -> 0.01 | L112: =IFERROR(L111/K111-1, 0) -> 0.01 | M112: =IFERROR(M111/L111-1, 0) -> 0.01 | N112: =IFERROR(N111/M111-1, 0) -> 0.01
C113: Terminal_fleet_growth driver (Drivers!C705) | D113: =Drivers!$C$705 -> 0.01
...

Sheet Debt & Interest
C2: ="Financial Statement Model - "&Cover!$D$5 -> Financial Statement Model - GATX Corporation
C3: $ mm except per share
C5: Company name | D5: =Cover!$D$5 -> GATX Corporation
C6: Ticker | D6: =Cover!$D$6 -> GATX
C7: Circ break 1=off, 0=on | D7: =Cover!$D$7 -> 1
C8: Latest closing share price | D8: =Cover!$D$8 -> 162.78
C9: Share price date | D9: =Cover!$D$9 -> 46303
C10: Latest fiscal year end | D10: =Cover!$D$10 -> 46022
C11: Shares outstanding (millions) | D11: =Cover!$D$11 -> 35.8
C13: DEBT & INTEREST — Q2 10-Q p.42 ladder rolled forward
C15: Debt roll: BOP − maturities + refinancing at Drivers!New_issue_rate + net new issuance (from cash plug).
C16: Interest expense = (BOP + EOP)/2 × Fixed_cost_of_debt. FY2026 gate: within 3% of $588.0M (H1 $294.0M × 2).
A18: x | C18: MATURITY LADDER (10-Q p.42) | D18: 2026 rem | E18: 2027 | F18: 2028 | G18: 2029 | H18: 2030 | I18: Thereafter
C19: Recourse debt maturities | D19: =Drivers!$C$90 -> 633.8 | E19: =Drivers!$C$91 -> 848.1 | F19: =Drivers!$C$92 -> 819.4 | G19: =Drivers!$C$93 -> 850 | H19: =Drivers!$C$94 -> 2576.4 | I19: =Drivers!$C$95 -> 6615.2
C20: Interest scheduled (10-Q p.42) | D20: =Drivers!$C$96 -> 294.2 | E20: =Drivers!$C$97 -> 542.1 | F20: =Drivers!$C$98 -> 511.1
C22: DEBT ROLL ($M) — BOP − maturities + refi + net new (from cash plug) | D22: 2025A | E22: 2026E | F22: 2027E | G22: 2028E | H22: 2029E | I22: 2030E | J22: 2031E | K22: 2032E | L22: 2033E | M22: 2034E | N22: 2035E
C23: Total debt BOP | D23: =Drivers!$C$101 -> 12533.9 | E23: =Drivers!$C$101 -> 12533.9 | F23: =E27 -> 12516.956 | G23: =F27 -> 13017.969 | H23: =G27 -> 13493.695 | I23: =H27 -> 13952.432 | J23: =I27 -> 14418.254 | K23: =J27 -> 14661.143 | L23: =K27 -> 14851.717 | M23: =L27 -> 15035.772 | N23: =M27 -> 15213.731
C24: Less: maturities | D24: 0 | E24: =-Drivers!$C$90 -> -633.8 | F24: =-Drivers!$C$91 -> -848.1 | G24: =-Drivers!$C$92 -> -819.4 | H24: =-Drivers!$C$93 -> -850 | I24: =-Drivers!$C$94 -> -2576.4 | J24: 0 | K24: 0 | L24: 0 | M24: 0 | N24: 0
C25: Plus: refinancing at New_issue_rate | D25: 0 | E25: =Drivers!$C$90 -> 633.8 | F25: =Drivers!$C$91 -> 848.1 | G25: =Drivers!$C$92 -> 819.4 | H25: =Drivers!$C$93 -> 850 | I25: =Drivers!$C$94 -> 2576.4 | J25: 0 | K25: 0 | L25: 0 | M25: 0 | N25: 0
C26: Net new issuance (cash plug from CFS) | D26: 0 | E26: ='3 Statement Forecast'!E82 -> -16.944005 | F26: ='3 Statement Forecast'!F82 -> 501.01258 | G26: ='3 Statement Forecast'!G82 -> 475.72665 | H26: ='3 Statement Forecast'!H82 -> 458.73662 | I26: ='3 Statement Forecast'!I82 -> 465.82236 | J26: ='3 Statement Forecast'!J82 -> 242.88898 | K26: ='3 Statement Forecast'!K82 -> 190.57389 | L26: ='3 Statement Forecast'!L82 -> 184.05498 | ... N26: ='3 Statement Forecast'!N82 -> 172.30919
C27: Total debt EOP | D27: =D23+D24+D25+D26 -> 12533.9 | E27: =E23+E24+E25+E26 -> 12516.956 | F27: =F23+F24+F25+F26 -> 13017.969 | G27: =G23+G24+G25+G26 -> 13493.695 | H27: =H23+H24+H25+H26 -> 13952.432 | I27: =I23+I24+I25+I26 -> 14418.254 | J27: =J23+J24+J25+J26 -> 14661.143 | K27: =K23+K24+K25+K26 -> 14851.717 | ... N27: =N23+N24+N25+N26 -> 15386.04
C28: Average debt balance | D28: =D27 -> 12533.9 | E28: =(E23+E27)/2 -> 12525.428 | F28: =(F23+F27)/2 -> 12767.462 | G28: =(G23+G27)/2 -> 13255.832 | H28: =(H23+H27)/2 -> 13723.064 | I28: =(I23+I27)/2 -> 14185.343 | J28: =(J23+J27)/2 -> 14539.699 | K28: =(K23+K27)/2 -> 14756.43 | L28: =(L23+L27)/2 -> 14943.745 | ... N28: =(N23+N27)/2 -> 15299.886
C29: Non-GABX debt (fixed rate) | D29: =Drivers!$C$168 -> 9616.5 | E29: =Drivers!$C$168 -> 9616.5 | F29: =Drivers!$C$168+Drivers!$C$88 -> 10016.5 | G29: =F29+Drivers!$C$291 -> 10416.5 | H29: =G29+Drivers!$C$292 -> 10816.5 | I29: =H29+Drivers!$C$293 -> 11216.5 | J29: =J27-J30 -> 11800.943 | K29: =K27-K30 -> 11991.517 | L29: =L27-L30 -> 12175.572 | M29: =M27-M30 -> 12353.531 | N29: =N27-N30 -> 12525.84
C30: GABX debt (floating, mostly hedged) | D30: =Drivers!$C$106 -> 2942.9 | E30: =Drivers!$C$107 -> 2860.2 | F30: =Drivers!$C$107 -> 2860.2 | G30: =Drivers!$C$107 -> 2860.2 | H30: =Drivers!$C$107 -> 2860.2 | I30: =Drivers!$C$107 -> 2860.2 | J30: =I30 -> 2860.2 | K30: =J30 -> 2860.2 | L30: =K30 -> 2860.2 | M30: =L30 -> 2860.2 | N30: =M30 -> 2860.2
C31: Interest expense (Non-GABX×fixed + GABX×float; net float hedged flat) | D31: -391.5 | E31: =-(Drivers!$C$168*Drivers!$C$170+E30*Drivers!$C$108) -> -588.82599 | F31: =-((Drivers!$C$168-Drivers!$C$91)*Drivers!$C$170+Drivers!$C$91*Drivers!$C$102+Drivers!$C$88*Drivers!$C$102+F30*Drivers!$C$108) -> -615.70826 | G31: =-((Drivers!$C$168-Drivers!$C$91-Drivers!$C$92)*Drivers!$C$170+(Drivers!$C$91+Drivers!$C$92)*Drivers!$C$102+(Drivers!$C$88+Drivers!$C$291)*Drivers!$C$102+G30*Drivers!$C$108) -> -642.39824 | H31: =-((Drivers!$C$168-Drivers!$C$91-Drivers!$C$92-Drivers!$C$93)*Drivers!$C$170+(Drivers!$C$91+Drivers!$C$92+Drivers!$C$93)*Drivers!$C$102+(Drivers!$C$88+Drivers!$C$291+Drivers!$C$292)*Drivers!$C$102+H30*Drivers!$C$108) -> -669.29324 | I31: =-((Drivers!$C$168-Drivers!$C$91-Drivers!$C$92-Drivers!$C$93-Drivers!$C$94)*Drivers!$C$170+(Drivers!$C$91+Drivers!$C$92+Drivers!$C$93+Drivers!$C$94)*Drivers!$C$102+(Drivers!$C$88+Drivers!$C$291+Drivers!$C$292+Drivers!$C$293)*Drivers!$C$102+I30*Drivers!$C$102) -> -715.76368 | J31: =$I$31/$I$28*J23 -> -727.51591 | K31: =$I$31/$I$28*K23 -> -739.77159 | L31: =$I$31/$I$28*L23 -> -749.38756 | M31: =$I$31/$I$28*M23 -> -758.67461 | N31: =$I$31/$I$28*N23 -> -767.65406 | P31: GATE: 2026E within 3% of -$588.0M (H1 $294.0M × 2)
C32: Kill test delta 2027: 6.00% on 2027 refi + growth only | E32: =-E29*(Drivers!$C$105-Drivers!$C$104) -> -131.74605 | F32: =-(Drivers!$C$105-Drivers!$C$102)*(Drivers!$C$91+Drivers!$C$88) -> -8.7367 | G32: =-(Drivers!$C$105-Drivers!$C$102)*(Drivers!$C$91+Drivers!$C$92+Drivers!$C$88+Drivers!$C$291) -> -17.2725 | H32: =-(Drivers!$C$105-Drivers!$C$102)*(Drivers!$C$91+Drivers!$C$92+Drivers!$C$93+Drivers!$C$88+Drivers!$C$291+Drivers!$C$292) -> -26.0225 | I32: =-(Drivers!$C$105-Drivers!$C$102)*(Drivers!$C$91+Drivers!$C$92+Drivers!$C$93+Drivers!$C$94+Drivers!$C$88+Drivers!$C$291+Drivers!$C$292+Drivers!$C$293) -> -46.8573 | P32: Sensitivity: substitute Kill (6.00%) for New_issue_rate (5.30%) moves only the refi + growth tranche, not the full debt stack.
A34: x | C34: FIXED / FLOATING BREAKOUT (10-Q p.42) | D34: Q2 2026
C35: Fixed debt | D35: =Drivers!$C$168 -> 9616.5
C36: Floating debt (gross) | D36: =Drivers!$C$169 -> 2672.8
C37: Less: cash-flow hedges (SOFR fixed) | D37: =-Drivers!$C$173 -> -1754.4
C38: Net floating exposure | D38: =D36+D37 -> 918.4 | P38: [note] refers to Drivers!Net_floating_exposure (audit link)
C39: Fair-value hedges (float on fixed) | D39: =Drivers!$C$174 -> 50
C40: Weighted fixed coupon | D40: =Drivers!$C$170 -> 0.0463
C41: Floating all-in rate (SOFR + spread) | D41: =Drivers!$C$171 -> 0.0525
C42: Memo: net-float interest sensitivity (Δ100bp) | D42: =D38*0.01 -> 9.184 | P42: $M / 100bp move in SOFR on net_floating exposure (post-hedge).
A44: x | C44: 2030 REFI EFFECT BREAKOUT (v9 Section 3, 2026-09-25)
C45: FY2030 interest ex-2030-refi (i.e., pre-2030 refi state) | I45: =-((Drivers!$C$168-Drivers!$C$91-Drivers!$C$92-Drivers!$C$93)*Drivers!$C$170+(Drivers!$C$91+Drivers!$C$92+Drivers!$C$93)*Drivers!$C$102+(Drivers!$C$88+Drivers!$C$291+Drivers!$C$292+Drivers!$C$293)*Drivers!$C$102+I30*Drivers!$C$108) -> -690.49324
C46: 2030 refi effect — $2,576M maturity × (New_issue_rate − old coupon) | I46: =-Drivers!$C$94*(Drivers!$C$102-Drivers!$C$170) -> -17.26188
C47: 2030 refi effect — GABX term loan × (New_issue_rate − GABX_rate) | I47: =-I30*(Drivers!$C$102-Drivers!$C$108) -> -8.00856
C48: Total 2030 interest = ex-refi + $2,576M refi + GABX refi (check = row 19 col G) | I48: =I45+I46+I47 -> -715.76368
C49: Delta memo total vs Row 19 (must be 0) | I49: =I48-I31 -> 0
C50: v23 (2026-09-28): TERMINAL STATE 2031E-2035E — Total debt EOP (row 27 J:N) target-driven to hold D/(D+E) at Drivers!C709 (2030E ratio). Non-GABX debt (row 29) = row 27 - row 30 (GABX held flat). Net new issuance (row 26) = EOP - BOP. Interest (row 31) = 2030E blended rate × average debt. Revolver/plug from 3SF row 82 now equals target-driven issuance from Debt sheet; cash EOP (3SF row 36 J:N) becomes the natural balance-sheet plug, floating with CFO+CFI+CFF flows.
C52: Memo: v23 target-leverage debt (retired v25: unstable with residual payouts) | J52: =Drivers!$C$709/(1-Drivers!$C$709)*'3 Statement Forecast'!I58*(1+('3 Statement Forecast'!I58/'3 Statement Forecast'!H58-1)) -> 15114.101 | K52: =Drivers!$C$709/(1-Drivers!$C$709)*'3 Statement Forecast'!J58*(1+('3 Statement Forecast'!J58/'3 Statement Forecast'!I58-1)) -> 15843.291 | L52: =Drivers!$C$709/(1-Drivers!$C$709)*'3 Statement Forecast'!K58*(1+('3 Statement Forecast'!K58/'3 Statement Forecast'!J58-1)) -> 16563.311 | M52: =Drivers!$C$709/(1-Drivers!$C$709)*'3 Statement Forecast'!L58*(1+('3 Statement Forecast'!L58/'3 Statement Forecast'!K58-1)) -> 17318.638 | N52: =Drivers!$C$709/(1-Drivers!$C$709)*'3 Statement Forecast'!M58*(1+('3 Statement Forecast'!M58/'3 Statement Forecast'!L58-1)) -> 18107.404
C54: D/(D+E) by year (output only — no target) | D54: ='3 Statement Forecast'!D47/('3 Statement Forecast'!D47+'3 Statement Forecast'!D58) -> 0.82004527 | E54: ='3 Statement Forecast'!E47/('3 Statement Forecast'!E47+'3 Statement Forecast'!E58) -> 0.81037411 | F54: ='3 Statement Forecast'!F47/('3 Statement Forecast'!F47+'3 Statement Forecast'!F58) -> 0.80904583 | G54: ='3 Statement Forecast'!G47/('3 Statement Forecast'!G47+'3 Statement Forecast'!G58) -> 0.80687471 | H54: ='3 Statement Forecast'!H47/('3 Statement Forecast'!H47+'3 Statement Forecast'!H58) -> 0.80408628 | I54: ='3 Statement Forecast'!I47/('3 Statement Forecast'!I47+'3 Statement Forecast'!I58) -> 0.80182507 | J54: ='3 Statement Forecast'!J47/('3 Statement Forecast'!J47+'3 Statement Forecast'!J58) -> 0.79694688 | K54: ='3 Statement Forecast'!K47/('3 Statement Forecast'!K47+'3 Statement Forecast'!K58) -> 0.79157585 | ... N54: ='3 Statement Forecast'!N47/('3 Statement Forecast'!N47+'3 Statement Forecast'!N58) -> 0.77746705
C55: Net debt / EBITDA by year (output only — no target) | D55: =('3 Statement Forecast'!D47-'3 Statement Forecast'!D36)/('3 Statement Forecast'!D26-'3 Statement Forecast'!D24-'3 Statement Forecast'!D19) -> 10.695664 | E55: =('3 Statement Forecast'!E47-'3 Statement Forecast'!E36)/('3 Statement Forecast'!E26-'3 Statement Forecast'!E24-'3 Statement Forecast'!E19) -> 7.3877624 | F55: =('3 Statement Forecast'!F47-'3 Statement Forecast'!F36)/('3 Statement Forecast'!F26-'3 Statement Forecast'!F24-'3 Statement Forecast'!F19) -> 7.4671681 | G55: =('3 Statement Forecast'!G47-'3 Statement Forecast'!G36)/('3 Statement Forecast'!G26-'3 Statement Forecast'!G24-'3 Statement Forecast'!G19) -> 7.5350775 | H55: =('3 Statement Forecast'!H47-'3 Statement Forecast'!H36)/('3 Statement Forecast'!H26-'3 Statement Forecast'!H24-'3 Statement Forecast'!H19) -> 7.6230814 | I55: =('3 Statement Forecast'!I47-'3 Statement Forecast'!I36)/('3 Statement Forecast'!I26-'3 Statement Forecast'!I24-'3 Statement Forecast'!I19) -> 7.758768 | J55: =('3 Statement Forecast'!J47-'3 Statement Forecast'!J36)/('3 Statement Forecast'!J26-'3 Statement Forecast'!J24-'3 Statement Forecast'!J19) -> 7.7553565 | K55: =('3 Statement Forecast'!K47-'3 Statement Forecast'!K36)/('3 Statement Forecast'!K26-'3 Statement Forecast'!K24-'3 Statement Forecast'!K19) -> 7.730737 | ... N55: =('3 Statement Forecast'!N47-'3 Statement Forecast'!N36)/('3 Statement Forecast'!N26-'3 Statement Forecast'!N24-'3 Statement Forecast'!N19) -> 7.6204881

Sheet Legacy Cohort Model
C2: ="Financial Statement Model - "&Cover!$D$5 -> Financial Statement Model - GATX Corporation
C3: $ mm except per share
C5: Company name | D5: =Cover!$D$5 -> GATX Corporation
C6: Ticker | D6: =Cover!$D$6 -> GATX
C7: Circ break 1=off, 0=on | D7: =Cover!$D$7 -> 1
C8: Latest closing share price | D8: =Cover!$D$8 -> 162.78
C9: Share price date | D9: =Cover!$D$9 -> 46303
C10: Latest fiscal year end | D10: =Cover!$D$10 -> 46022
C11: Shares outstanding (millions) | D11: =Cover!$D$11 -> 35.8
C13: v36 LEGACY FLEET MODEL — disclosed-expiration-driven renewal engine (rows 55-68)
C15: v36: engine builds forward from 2025A anchor (Drivers!C45 = 954.2) using disclosed renewal counts × success × expiring-rate × LPI; renewals spread evenly → half year t, half year t+1.
C16: Target: 2025A cohort revenue = Rail NA lease $1,049.1M − boxcars $58.5M − locos $36.4M = $954.2M (10-K p.31 railcars line).
C17: v36 2026-10-07: v34/v35 lumpy single-term-per-year timing REVERTED. Rows 20-42 (5-vintage cohort build) retained as REFERENCE ONLY — do not feed D43 anymore.
C18: v36: rows 21-26 (cohort cars) still feed 3SF!I111:N111 fleet count; rows 29-33 (cohort rates) kept as display; rows 37-42 (cohort rev) now display-only, not summed into D43.
A20: x | C20: COHORT CARS (reference only v36; still feeds 3SF fleet count row 111) — 2025A → | D20: 2025A | E20: 2026E | F20: 2027E | G20: 2028E | H20: 2029E | I20: 2030E | J20: 2031E | K20: 2032E | L20: 2033E | M20: 2034E | N20: 2035E
C21: Cohort 2021 cars | D21: =Drivers!$C$11 -> 20000 | E21: =Drivers!$C$11 -> 20000 | F21: =Drivers!$C$11 -> 20000 | G21: =Drivers!$C$11 -> 20000 | H21: =Drivers!$C$11 -> 20000 | I21: =Drivers!$C$11 -> 20000 | J21: =I21*(1+Drivers!$C$705) -> 20200 | K21: =J21*(1+Drivers!$C$705) -> 20402 | L21: =K21*(1+Drivers!$C$705) -> 20606.02 | M21: =L21*(1+Drivers!$C$705) -> 20812.08 | N21: =M21*(1+Drivers!$C$705) -> 21020.201
C22: Cohort 2022 cars | D22: =Drivers!$C$12 -> 18500 | E22: =Drivers!$C$12 -> 18500 | F22: =Drivers!$C$12 -> 18500 | G22: =Drivers!$C$12 -> 18500 | H22: =Drivers!$C$12 -> 18500 | I22: =Drivers!$C$12 -> 18500 | J22: =I22*(1+Drivers!$C$705) -> 18685 | K22: =J22*(1+Drivers!$C$705) -> 18871.85 | L22: =K22*(1+Drivers!$C$705) -> 19060.569 | M22: =L22*(1+Drivers!$C$705) -> 19251.174 | N22: =M22*(1+Drivers!$C$705) -> 19443.686
C23: Cohort 2023 cars | D23: =Drivers!$C$13 -> 18700 | E23: =Drivers!$C$13 -> 18700 | F23: =Drivers!$C$13 -> 18700 | G23: =Drivers!$C$13 -> 18700 | H23: =Drivers!$C$13 -> 18700 | I23: =Drivers!$C$13 -> 18700 | J23: =I23*(1+Drivers!$C$705) -> 18887 | K23: =J23*(1+Drivers!$C$705) -> 19075.87 | L23: =K23*(1+Drivers!$C$705) -> 19266.629 | M23: =L23*(1+Drivers!$C$705) -> 19459.295 | N23: =M23*(1+Drivers!$C$705) -> 19653.888
C24: Cohort 2024 cars | D24: =Drivers!$C$14 -> 19400 | E24: =Drivers!$C$14 -> 19400 | F24: =Drivers!$C$14 -> 19400 | G24: =Drivers!$C$14 -> 19400 | H24: =Drivers!$C$14 -> 19400 | I24: =Drivers!$C$14 -> 19400 | J24: =I24*(1+Drivers!$C$705) -> 19594 | K24: =J24*(1+Drivers!$C$705) -> 19789.94 | L24: =K24*(1+Drivers!$C$705) -> 19987.839 | M24: =L24*(1+Drivers!$C$705) -> 20187.718 | N24: =M24*(1+Drivers!$C$705) -> 20389.595
C25: Cohort 2025 cars | D25: =Drivers!$C$15 -> 21500 | E25: =Drivers!$C$15 -> 21500 | F25: =Drivers!$C$15 -> 21500 | G25: =Drivers!$C$15 -> 21500 | H25: =Drivers!$C$15 -> 21500 | I25: =Drivers!$C$15 -> 21500 | J25: =I25*(1+Drivers!$C$705) -> 21715 | K25: =J25*(1+Drivers!$C$705) -> 21932.15 | L25: =K25*(1+Drivers!$C$705) -> 22151.471 | M25: =L25*(1+Drivers!$C$705) -> 22372.986 | N25: =M25*(1+Drivers!$C$705) -> 22596.716
C26: Legacy base fleet cars | D26: =Drivers!$C$16 -> 2493 | E26: =Drivers!$C$16 -> 2493 | F26: =Drivers!$C$16 -> 2493 | G26: =Drivers!$C$16 -> 2493 | H26: =Drivers!$C$16 -> 2493 | I26: =Drivers!$C$16 -> 2493 | J26: =I26*(1+Drivers!$C$705) -> 2517.93 | K26: =J26*(1+Drivers!$C$705) -> 2543.1093 | L26: =K26*(1+Drivers!$C$705) -> 2568.5404 | M26: =L26*(1+Drivers!$C$705) -> 2594.2258 | N26: =M26*(1+Drivers!$C$705) -> 2620.1681
C28: RATES ($/car/yr) — factor × pre-rate for the 5 cohorts; base held flat | D28: 2025A | E28: 2026E | F28: 2027E | G28: 2028E | H28: 2029E | I28: 2030E | J28: 2031E | K28: 2032E | L28: 2033E | M28: 2034E | N28: 2035E
C29: Cohort 2021 rate | D29: =(1-Drivers!$D$810)*(Drivers!$C$23*Drivers!$C$17) + (Drivers!$D$810-Drivers!$D$816)*(Drivers!$C$23*Drivers!$C$17)*(1+Drivers!$C$824) + Drivers!$D$816*(Drivers!$C$23*Drivers!$C$17)*(1+Drivers!$C$824)*(1+Drivers!$D$824) -> 9981.4446 | E29: =(1-Drivers!$E$810)*(Drivers!$C$23*Drivers!$C$17) + (Drivers!$E$810-Drivers!$E$816)*(Drivers!$C$23*Drivers!$C$17)*(1+Drivers!$C$824) + Drivers!$E$816*(Drivers!$C$23*Drivers!$C$17)*(1+Drivers!$C$824)*(1+Drivers!$D$824) -> 9981.4446 | F29: =(1-Drivers!$F$810)*(Drivers!$C$23*Drivers!$C$17) + (Drivers!$F$810-Drivers!$F$816)*(Drivers!$C$23*Drivers!$C$17)*(1+Drivers!$C$824) + Drivers!$F$816*(Drivers!$C$23*Drivers!$C$17)*(1+Drivers!$C$824)*(1+Drivers!$D$824) -> 9981.4446 | G29: =(1-Drivers!$G$810)*(Drivers!$C$23*Drivers!$C$17) + (Drivers!$G$810-Drivers!$G$816)*(Drivers!$C$23*Drivers!$C$17)*(1+Drivers!$C$824) + Drivers!$G$816*(Drivers!$C$23*Drivers!$C$17)*(1+Drivers!$C$824)*(1+Drivers!$D$824) -> 9981.4446 | H29: =(1-Drivers!$H$810)*(Drivers!$C$23*Drivers!$C$17) + (Drivers!$H$810-Drivers!$H$816)*(Drivers!$C$23*Drivers!$C$17)*(1+Drivers!$C$824) + Drivers!$H$816*(Drivers!$C$23*Drivers!$C$17)*(1+Drivers!$C$824)*(1+Drivers!$D$824) -> 10230.981 | I29: =(1-Drivers!$I$810)*(Drivers!$C$23*Drivers!$C$17) + (Drivers!$I$810-Drivers!$I$816)*(Drivers!$C$23*Drivers!$C$17)*(1+Drivers!$C$824) + Drivers!$I$816*(Drivers!$C$23*Drivers!$C$17)*(1+Drivers!$C$824)*(1+Drivers!$D$824) -> 10480.517 | J29: =(1-Drivers!$J$810)*(Drivers!$C$23*Drivers!$C$17) + (Drivers!$J$810-Drivers!$J$816)*(Drivers!$C$23*Drivers!$C$17)*(1+Drivers!$C$824) + Drivers!$J$816*(Drivers!$C$23*Drivers!$C$17)*(1+Drivers!$C$824)*(1+Drivers!$D$824) -> 10480.517 | K29: =(1-Drivers!$K$810)*(Drivers!$C$23*Drivers!$C$17) + (Drivers!$K$810-Drivers!$K$816)*(Drivers!$C$23*Drivers!$C$17)*(1+Drivers!$C$824) + Drivers!$K$816*(Drivers!$C$23*Drivers!$C$17)*(1+Drivers!$C$824)*(1+Drivers!$D$824) -> 10480.517 | L29: =(1-Drivers!$L$810)*(Drivers!$C$23*Drivers!$C$17) + (Drivers!$L$810-Drivers!$L$816)*(Drivers!$C$23*Drivers!$C$17)*(1+Drivers!$C$824) + Drivers!$L$816*(Drivers!$C$23*Drivers!$C$17)*(1+Drivers!$C$824)*(1+Drivers!$D$824) -> 10480.517 | M29: =(1-Drivers!$M$810)*(Drivers!$C$23*Drivers!$C$17) + (Drivers!$M$810-Drivers!$M$816)*(Drivers!$C$23*Drivers!$C$17)*(1+Drivers!$C$824) + Drivers!$M$816*(Drivers!$C$23*Drivers!$C$17)*(1+Drivers!$C$824)*(1+Drivers!$D$824) -> 10480.517 | N29: =(1-Drivers!$N$810)*(Drivers!$C$23*Drivers!$C$17) + (Drivers!$N$810-Drivers!$N$816)*(Drivers!$C$23*Drivers!$C$17)*(1+Drivers!$C$824) + Drivers!$N$816*(Drivers!$C$23*Drivers!$C$17)*(1+Drivers!$C$824)*(1+Drivers!$D$824) -> 10480.517
C30: Cohort 2022 rate | D30: =(1-Drivers!$D$811)*(Drivers!$C$23*Drivers!$C$18) + (Drivers!$D$811-Drivers!$D$817)*(Drivers!$C$23*Drivers!$C$18)*(1+Drivers!$C$825) + Drivers!$D$817*(Drivers!$C$23*Drivers!$C$18)*(1+Drivers!$C$825)*(1+Drivers!$D$825) -> 8918.64 | E30: =(1-Drivers!$E$811)*(Drivers!$C$23*Drivers!$C$18) + (Drivers!$E$811-Drivers!$E$817)*(Drivers!$C$23*Drivers!$C$18)*(1+Drivers!$C$825) + Drivers!$E$817*(Drivers!$C$23*Drivers!$C$18)*(1+Drivers!$C$825)*(1+Drivers!$D$825) -> 10018.606 | F30: =(1-Drivers!$F$811)*(Drivers!$C$23*Drivers!$C$18) + (Drivers!$F$811-Drivers!$F$817)*(Drivers!$C$23*Drivers!$C$18)*(1+Drivers!$C$825) + Drivers!$F$817*(Drivers!$C$23*Drivers!$C$18)*(1+Drivers!$C$825)*(1+Drivers!$D$825) -> 10568.588 | G30: =(1-Drivers!$G$811)*(Drivers!$C$23*Drivers!$C$18) + (Drivers!$G$811-Drivers!$G$817)*(Drivers!$C$23*Drivers!$C$18)*(1+Drivers!$C$825) + Drivers!$G$817*(Drivers!$C$23*Drivers!$C$18)*(1+Drivers!$C$825)*(1+Drivers!$D$825) -> 10568.588 | H30: =(1-Drivers!$H$811)*(Drivers!$C$23*Drivers!$C$18) + (Drivers!$H$811-Drivers!$H$817)*(Drivers!$C$23*Drivers!$C$18)*(1+Drivers!$C$825) + Drivers!$H$817*(Drivers!$C$23*Drivers!$C$18)*(1+Drivers!$C$825)*(1+Drivers!$D$825) -> 10568.588 | I30: =(1-Drivers!$I$811)*(Drivers!$C$23*Drivers!$C$18) + (Drivers!$I$811-Drivers!$I$817)*(Drivers!$C$23*Drivers!$C$18)*(1+Drivers!$C$825) + Drivers!$I$817*(Drivers!$C$23*Drivers!$C$18)*(1+Drivers!$C$825)*(1+Drivers!$D$825) -> 10568.588 | J30: =(1-Drivers!$J$811)*(Drivers!$C$23*Drivers!$C$18) + (Drivers!$J$811-Drivers!$J$817)*(Drivers!$C$23*Drivers!$C$18)*(1+Drivers!$C$825) + Drivers!$J$817*(Drivers!$C$23*Drivers!$C$18)*(1+Drivers!$C$825)*(1+Drivers!$D$825) -> 10674.274 | K30: =(1-Drivers!$K$811)*(Drivers!$C$23*Drivers!$C$18) + (Drivers!$K$811-Drivers!$K$817)*(Drivers!$C$23*Drivers!$C$18)*(1+Drivers!$C$825) + Drivers!$K$817*(Drivers!$C$23*Drivers!$C$18)*(1+Drivers!$C$825)*(1+Drivers!$D$825) -> 10779.96 | L30: =(1-Drivers!$L$811)*(Drivers!$C$23*Drivers!$C$18) + (Drivers!$L$811-Drivers!$L$817)*(Drivers!$C$23*Drivers!$C$18)*(1+Drivers!$C$825) + Drivers!$L$817*(Drivers!$C$23*Drivers!$C$18)*(1+Drivers!$C$825)*(1+Drivers!$D$825) -> 10779.96 | M30: =(1-Drivers!$M$811)*(Drivers!$C$23*Drivers!$C$18) + (Drivers!$M$811-Drivers!$M$817)*(Drivers!$C$23*Drivers!$C$18)*(1+Drivers!$C$825) + Drivers!$M$817*(Drivers!$C$23*Drivers!$C$18)*(1+Drivers!$C$825)*(1+Drivers!$D$825) -> 10779.96 | N30: =(1-Drivers!$N$811)*(Drivers!$C$23*Drivers!$C$18) + (Drivers!$N$811-Drivers!$N$817)*(Drivers!$C$23*Drivers!$C$18)*(1+Drivers!$C$825) + Drivers!$N$817*(Drivers!$C$23*Drivers!$C$18)*(1+Drivers!$C$825)*(1+Drivers!$D$825) -> 10779.96
C31: Cohort 2023 rate | D31: =(1-Drivers!$D$812)*(Drivers!$C$23*Drivers!$C$19) + (Drivers!$D$812-Drivers!$D$818)*(Drivers!$C$23*Drivers!$C$19)*(1+Drivers!$C$826) + Drivers!$D$818*(Drivers!$C$23*Drivers!$C$19)*(1+Drivers!$C$826)*(1+Drivers!$D$826) -> 9290.25 | E31: =(1-Drivers!$E$812)*(Drivers!$C$23*Drivers!$C$19) + (Drivers!$E$812-Drivers!$E$818)*(Drivers!$C$23*Drivers!$C$19)*(1+Drivers!$C$826) + Drivers!$E$818*(Drivers!$C$23*Drivers!$C$19)*(1+Drivers!$C$826)*(1+Drivers!$D$826) -> 9290.25 | F31: =(1-Drivers!$F$812)*(Drivers!$C$23*Drivers!$C$19) + (Drivers!$F$812-Drivers!$F$818)*(Drivers!$C$23*Drivers!$C$19)*(1+Drivers!$C$826) + Drivers!$F$818*(Drivers!$C$23*Drivers!$C$19)*(1+Drivers!$C$826)*(1+Drivers!$D$826) -> 9290.25 | G31: =(1-Drivers!$G$812)*(Drivers!$C$23*Drivers!$C$19) + (Drivers!$G$812-Drivers!$G$818)*(Drivers!$C$23*Drivers!$C$19)*(1+Drivers!$C$826) + Drivers!$G$818*(Drivers!$C$23*Drivers!$C$19)*(1+Drivers!$C$826)*(1+Drivers!$D$826) -> 9832.1812 | H31: =(1-Drivers!$H$812)*(Drivers!$C$23*Drivers!$C$19) + (Drivers!$H$812-Drivers!$H$818)*(Drivers!$C$23*Drivers!$C$19)*(1+Drivers!$C$826) + Drivers!$H$818*(Drivers!$C$23*Drivers!$C$19)*(1+Drivers!$C$826)*(1+Drivers!$D$826) -> 10219.275 | I31: =(1-Drivers!$I$812)*(Drivers!$C$23*Drivers!$C$19) + (Drivers!$I$812-Drivers!$I$818)*(Drivers!$C$23*Drivers!$C$19)*(1+Drivers!$C$826) + Drivers!$I$818*(Drivers!$C$23*Drivers!$C$19)*(1+Drivers!$C$826)*(1+Drivers!$D$826) -> 10219.275 | J31: =(1-Drivers!$J$812)*(Drivers!$C$23*Drivers!$C$19) + (Drivers!$J$812-Drivers!$J$818)*(Drivers!$C$23*Drivers!$C$19)*(1+Drivers!$C$826) + Drivers!$J$818*(Drivers!$C$23*Drivers!$C$19)*(1+Drivers!$C$826)*(1+Drivers!$D$826) -> 10219.275 | K31: =(1-Drivers!$K$812)*(Drivers!$C$23*Drivers!$C$19) + (Drivers!$K$812-Drivers!$K$818)*(Drivers!$C$23*Drivers!$C$19)*(1+Drivers!$C$826) + Drivers!$K$818*(Drivers!$C$23*Drivers!$C$19)*(1+Drivers!$C$826)*(1+Drivers!$D$826) -> 10219.275 | L31: =(1-Drivers!$L$812)*(Drivers!$C$23*Drivers!$C$19) + (Drivers!$L$812-Drivers!$L$818)*(Drivers!$C$23*Drivers!$C$19)*(1+Drivers!$C$826) + Drivers!$L$818*(Drivers!$C$23*Drivers!$C$19)*(1+Drivers!$C$826)*(1+Drivers!$D$826) -> 10321.468 | M31: =(1-Drivers!$M$812)*(Drivers!$C$23*Drivers!$C$19) + (Drivers!$M$812-Drivers!$M$818)*(Drivers!$C$23*Drivers!$C$19)*(1+Drivers!$C$826) + Drivers!$M$818*(Drivers!$C$23*Drivers!$C$19)*(1+Drivers!$C$826)*(1+Drivers!$D$826) -> 10423.66 | N31: =(1-Drivers!$N$812)*(Drivers!$C$23*Drivers!$C$19) + (Drivers!$N$812-Drivers!$N$818)*(Drivers!$C$23*Drivers!$C$19)*(1+Drivers!$C$826) + Drivers!$N$818*(Drivers!$C$23*Drivers!$C$19)*(1+Drivers!$C$826)*(1+Drivers!$D$826) -> 10423.66
C32: Cohort 2024 rate | D32: =(1-Drivers!$D$813)*(Drivers!$C$23*Drivers!$C$20) + (Drivers!$D$813-Drivers!$D$819)*(Drivers!$C$23*Drivers!$C$20)*(1+Drivers!$C$827) + Drivers!$D$819*(Drivers!$C$23*Drivers!$C$20)*(1+Drivers!$C$827)*(1+Drivers!$D$827) -> 9785.73 | E32: =(1-Drivers!$E$813)*(Drivers!$C$23*Drivers!$C$20) + (Drivers!$E$813-Drivers!$E$819)*(Drivers!$C$23*Drivers!$C$20)*(1+Drivers!$C$827) + Drivers!$E$819*(Drivers!$C$23*Drivers!$C$20)*(1+Drivers!$C$827)*(1+Drivers!$D$827) -> 9785.73 | F32: =(1-Drivers!$F$813)*(Drivers!$C$23*Drivers!$C$20) + (Drivers!$F$813-Drivers!$F$819)*(Drivers!$C$23*Drivers!$C$20)*(1+Drivers!$C$827) + Drivers!$F$819*(Drivers!$C$23*Drivers!$C$20)*(1+Drivers!$C$827)*(1+Drivers!$D$827) -> 9785.73 | G32: =(1-Drivers!$G$813)*(Drivers!$C$23*Drivers!$C$20) + (Drivers!$G$813-Drivers!$G$819)*(Drivers!$C$23*Drivers!$C$20)*(1+Drivers!$C$827) + Drivers!$G$819*(Drivers!$C$23*Drivers!$C$20)*(1+Drivers!$C$827)*(1+Drivers!$D$827) -> 9785.73 | H32: =(1-Drivers!$H$813)*(Drivers!$C$23*Drivers!$C$20) + (Drivers!$H$813-Drivers!$H$819)*(Drivers!$C$23*Drivers!$C$20)*(1+Drivers!$C$827) + Drivers!$H$819*(Drivers!$C$23*Drivers!$C$20)*(1+Drivers!$C$827)*(1+Drivers!$D$827) -> 10275.016 | I32: =(1-Drivers!$I$813)*(Drivers!$C$23*Drivers!$C$20) + (Drivers!$I$813-Drivers!$I$819)*(Drivers!$C$23*Drivers!$C$20)*(1+Drivers!$C$827) + Drivers!$I$819*(Drivers!$C$23*Drivers!$C$20)*(1+Drivers!$C$827)*(1+Drivers!$D$827) -> 10275.016 | J32: =(1-Drivers!$J$813)*(Drivers!$C$23*Drivers!$C$20) + (Drivers!$J$813-Drivers!$J$819)*(Drivers!$C$23*Drivers!$C$20)*(1+Drivers!$C$827) + Drivers!$J$819*(Drivers!$C$23*Drivers!$C$20)*(1+Drivers!$C$827)*(1+Drivers!$D$827) -> 10275.016 | K32: =(1-Drivers!$K$813)*(Drivers!$C$23*Drivers!$C$20) + (Drivers!$K$813-Drivers!$K$819)*(Drivers!$C$23*Drivers!$C$20)*(1+Drivers!$C$827) + Drivers!$K$819*(Drivers!$C$23*Drivers!$C$20)*(1+Drivers!$C$827)*(1+Drivers!$D$827) -> 10275.016 | L32: =(1-Drivers!$L$813)*(Drivers!$C$23*Drivers!$C$20) + (Drivers!$L$813-Drivers!$L$819)*(Drivers!$C$23*Drivers!$C$20)*(1+Drivers!$C$827) + Drivers!$L$819*(Drivers!$C$23*Drivers!$C$20)*(1+Drivers!$C$827)*(1+Drivers!$D$827) -> 10275.016 | M32: =(1-Drivers!$M$813)*(Drivers!$C$23*Drivers!$C$20) + (Drivers!$M$813-Drivers!$M$819)*(Drivers!$C$23*Drivers!$C$20)*(1+Drivers!$C$827) + Drivers!$M$819*(Drivers!$C$23*Drivers!$C$20)*(1+Drivers!$C$827)*(1+Drivers!$D$827) -> 10377.767 | N32: =(1-Drivers!$N$813)*(Drivers!$C$23*Drivers!$C$20) + (Drivers!$N$813-Drivers!$N$819)*(Drivers!$C$23*Drivers!$C$20)*(1+Drivers!$C$827) + Drivers!$N$819*(Drivers!$C$23*Drivers!$C$20)*(1+Drivers!$C$827)*(1+Drivers!$D$827) -> 10480.517
C33: Cohort 2025 rate | D33: =(1-Drivers!$D$814)*(Drivers!$C$23*Drivers!$C$21) + (Drivers!$D$814-Drivers!$D$820)*(Drivers!$C$23*Drivers!$C$21)*(1+Drivers!$C$828) + Drivers!$D$820*(Drivers!$C$23*Drivers!$C$21)*(1+Drivers!$C$828)*(1+Drivers!$D$828) -> 10033.47 | E33: =(1-Drivers!$E$814)*(Drivers!$C$23*Drivers!$C$21) + (Drivers!$E$814-Drivers!$E$820)*(Drivers!$C$23*Drivers!$C$21)*(1+Drivers!$C$828) + Drivers!$E$820*(Drivers!$C$23*Drivers!$C$21)*(1+Drivers!$C$828)*(1+Drivers!$D$828) -> 10033.47 | F33: =(1-Drivers!$F$814)*(Drivers!$C$23*Drivers!$C$21) + (Drivers!$F$814-Drivers!$F$820)*(Drivers!$C$23*Drivers!$C$21)*(1+Drivers!$C$828) + Drivers!$F$820*(Drivers!$C$23*Drivers!$C$21)*(1+Drivers!$C$828)*(1+Drivers!$D$828) -> 10033.47 | G33: =(1-Drivers!$G$814)*(Drivers!$C$23*Drivers!$C$21) + (Drivers!$G$814-Drivers!$G$820)*(Drivers!$C$23*Drivers!$C$21)*(1+Drivers!$C$828) + Drivers!$G$820*(Drivers!$C$23*Drivers!$C$21)*(1+Drivers!$C$828)*(1+Drivers!$D$828) -> 10033.47 | H33: =(1-Drivers!$H$814)*(Drivers!$C$23*Drivers!$C$21) + (Drivers!$H$814-Drivers!$H$820)*(Drivers!$C$23*Drivers!$C$21)*(1+Drivers!$C$828) + Drivers!$H$820*(Drivers!$C$23*Drivers!$C$21)*(1+Drivers!$C$828)*(1+Drivers!$D$828) -> 10117.082 | I33: =(1-Drivers!$I$814)*(Drivers!$C$23*Drivers!$C$21) + (Drivers!$I$814-Drivers!$I$820)*(Drivers!$C$23*Drivers!$C$21)*(1+Drivers!$C$828) + Drivers!$I$820*(Drivers!$C$23*Drivers!$C$21)*(1+Drivers!$C$828)*(1+Drivers!$D$828) -> 10535.144 | J33: =(1-Drivers!$J$814)*(Drivers!$C$23*Drivers!$C$21) + (Drivers!$J$814-Drivers!$J$820)*(Drivers!$C$23*Drivers!$C$21)*(1+Drivers!$C$828) + Drivers!$J$820*(Drivers!$C$23*Drivers!$C$21)*(1+Drivers!$C$828)*(1+Drivers!$D$828) -> 10535.144 | K33: =(1-Drivers!$K$814)*(Drivers!$C$23*Drivers!$C$21) + (Drivers!$K$814-Drivers!$K$820)*(Drivers!$C$23*Drivers!$C$21)*(1+Drivers!$C$828) + Drivers!$K$820*(Drivers!$C$23*Drivers!$C$21)*(1+Drivers!$C$828)*(1+Drivers!$D$828) -> 10535.144 | L33: =(1-Drivers!$L$814)*(Drivers!$C$23*Drivers!$C$21) + (Drivers!$L$814-Drivers!$L$820)*(Drivers!$C$23*Drivers!$C$21)*(1+Drivers!$C$828) + Drivers!$L$820*(Drivers!$C$23*Drivers!$C$21)*(1+Drivers!$C$828)*(1+Drivers!$D$828) -> 10535.144 | M33: =(1-Drivers!$M$814)*(Drivers!$C$23*Drivers!$C$21) + (Drivers!$M$814-Drivers!$M$820)*(Drivers!$C$23*Drivers!$C$21)*(1+Drivers!$C$828) + Drivers!$M$820*(Drivers!$C$23*Drivers!$C$21)*(1+Drivers!$C$828)*(1+Drivers!$D$828) -> 10640.495 | N33: =(1-Drivers!$N$814)*(Drivers!$C$23*Drivers!$C$21) + (Drivers!$N$814-Drivers!$N$820)*(Drivers!$C$23*Drivers!$C$21)*(1+Drivers!$C$828) + Drivers!$N$820*(Drivers!$C$23*Drivers!$C$21)*(1+Drivers!$C$828)*(1+Drivers!$D$828) -> 10745.846
C34: Legacy base rate | D34: =Drivers!$C$22 -> 8300 | E34: =Drivers!$C$22 -> 8300 | F34: =Drivers!$C$22 -> 8300 | G34: =Drivers!$C$22 -> 8300 | H34: =Drivers!$C$22 -> 8300 | I34: =Drivers!$C$22 -> 8300 | J34: =Drivers!$C$22 -> 8300 | K34: =Drivers!$C$22 -> 8300 | ... N34: =Drivers!$C$22 -> 8300
C36: REVENUE BY COHORT (reference only v36; D43 NO LONGER sums these — see new engine rows 55-68) | D36: 2025A | E36: 2026E | F36: 2027E | G36: 2028E | H36: 2029E | I36: 2030E | J36: 2031E | K36: 2032E | L36: 2033E | M36: 2034E | N36: 2035E
C37: Cohort 2021 rev | D37: =D21*D29/1000000 -> 199.62889 | E37: =E21*E29/1000000 -> 199.62889 | F37: =F21*F29/1000000 -> 199.62889 | G37: =G21*G29/1000000 -> 199.62889 | H37: =H21*H29/1000000 -> 204.61961 | I37: =I21*I29/1000000 -> 209.61034 | J37: =J21*J29/1000000 -> 211.70644 | K37: =K21*K29/1000000 -> 213.8235 | ... N37: =N21*N29/1000000 -> 220.30257
C38: Cohort 2022 rev | D38: =D22*D30/1000000 -> 164.99484 | E38: =E22*E30/1000000 -> 185.3442 | F38: =F22*F30/1000000 -> 195.51889 | G38: =G22*G30/1000000 -> 195.51889 | H38: =H22*H30/1000000 -> 195.51889 | I38: =I22*I30/1000000 -> 195.51889 | J38: =J22*J30/1000000 -> 199.44881 | K38: =K22*K30/1000000 -> 203.43779 | ... N38: =N22*N30/1000000 -> 209.60216
C39: Cohort 2023 rev | D39: =D23*D31/1000000 -> 173.72768 | E39: =E23*E31/1000000 -> 173.72768 | F39: =F23*F31/1000000 -> 173.72768 | G39: =G23*G31/1000000 -> 183.86179 | H39: =H23*H31/1000000 -> 191.10044 | I39: =I23*I31/1000000 -> 191.10044 | J39: =J23*J31/1000000 -> 193.01145 | K39: =K23*K31/1000000 -> 194.94156 | ... N39: =N23*N31/1000000 -> 204.86546
C40: Cohort 2024 rev | D40: =D24*D32/1000000 -> 189.84316 | E40: =E24*E32/1000000 -> 189.84316 | F40: =F24*F32/1000000 -> 189.84316 | G40: =G24*G32/1000000 -> 189.84316 | H40: =H24*H32/1000000 -> 199.33532 | I40: =I24*I32/1000000 -> 199.33532 | J40: =J24*J32/1000000 -> 201.32867 | K40: =K24*K32/1000000 -> 203.34196 | ... N40: =N24*N32/1000000 -> 213.69349
C41: Cohort 2025 rev | D41: =D25*D33/1000000 -> 215.71961 | E41: =E25*E33/1000000 -> 215.71961 | F41: =F25*F33/1000000 -> 215.71961 | G41: =G25*G33/1000000 -> 215.71961 | H41: =H25*H33/1000000 -> 217.51727 | I41: =I25*I33/1000000 -> 226.50559 | J41: =J25*J33/1000000 -> 228.77064 | K41: =K25*K33/1000000 -> 231.05835 | ... N41: =N25*N33/1000000 -> 242.82084
C42: Base fleet rev | D42: =D26*D34/1000000 -> 20.6919 | E42: =E26*E34/1000000 -> 20.6919 | F42: =F26*F34/1000000 -> 20.6919 | G42: =G26*G34/1000000 -> 20.6919 | H42: =H26*H34/1000000 -> 20.6919 | I42: =I26*I34/1000000 -> 20.6919 | J42: =J26*J34/1000000 -> 20.898819 | K42: =K26*K34/1000000 -> 21.107807 | ... N42: =N26*N34/1000000 -> 21.747395
A43: x | C43: LEGACY COHORT REVENUE TOTAL | D43: =D65 -> 954.2 | E43: =E65 -> 980.16565 | F43: =F65 -> 1004.0025 | G43: =G65 -> 1027.6065 | H43: =H65 -> 1042.0861 | I43: =I65 -> 1044.9995 | J43: =J65 -> 1045.005 | K43: =K65 -> 1048.9927 | ... N43: =N65 -> 1061.0243
A44: x | C44: CALIBRATION CHECK: 2025A vs target | D44: =D43 -> 954.2 | E44: =Drivers!$C$45 -> 954.2 | F44: =D44-E44 -> 0 | P44: v36: delta MUST be ~0 (D65 anchored to Drivers!C45; no calibration factor needed).
C46: IMPLIED LPI (OUTPUT ROW, v23): year-over-year revenue-per-car growth. Should = Terminal_LPI (2%) in every terminal year since car counts grow separately at Terminal_fleet_growth. | D46: n/a | E46: n/a | F46: n/a | G46: n/a | H46: n/a | I46: n/a | J46: =IFERROR((J43/SUM(J21:J26))/(I43/SUM(I21:I26))-1, 0) -> -0.0098957236 | K46: =IFERROR((K43/SUM(K21:K26))/(J43/SUM(J21:J26))-1, 0) -> -0.0061228446 | L46: =IFERROR((L43/SUM(L21:L26))/(K43/SUM(K21:K26))-1, 0) -> -0.0061300157 | M46: =IFERROR((M43/SUM(M21:M26))/(L43/SUM(L21:L26))-1, 0) -> -0.0061300021 | N46: =IFERROR((N43/SUM(N21:N26))/(M43/SUM(M21:M26))-1, 0) -> -0.0061300021
C48: v23 (2026-09-28): terminal years 2031E-2035E — cohort rates (rows 29-33) compound at Terminal_LPI; cars (rows 21-26) compound at Terminal_fleet_growth. Legacy base rate row 34 held flat at Drivers!C22 (existing mechanic). Implied LPI output row 46 now measures revenue-per-car YoY growth to isolate LPI from fleet-count growth.
B50: 2024A=0 (no modeled cohort R1 lands in 2024) | C50: Cars renewing per year (v34, derived) | D50: =Drivers!$C11*Drivers!$D$810+Drivers!$C12*Drivers!$D$811+Drivers!$C13*Drivers!$D$812+Drivers!$C14*Drivers!$D$813+Drivers!$C15*Drivers!$D$814+Drivers!$C11*Drivers!$D$816+Drivers!$C12*Drivers!$D$817+Drivers!$C13*Drivers!$D$818+Drivers!$C14*Drivers!$D$819+Drivers!$C15*Drivers!$D$820 -> 20000 | E50: =Drivers!$C11*(Drivers!$E$810-Drivers!$D$810)+Drivers!$C12*(Drivers!$E$811-Drivers!$D$811)+Drivers!$C13*(Drivers!$E$812-Drivers!$D$812)+Drivers!$C14*(Drivers!$E$813-Drivers!$D$813)+Drivers!$C15*(Drivers!$E$814-Drivers!$D$814)+Drivers!$C11*(Drivers!$E$816-Drivers!$D$816)+Drivers!$C12*(Drivers!$E$817-Drivers!$D$817)+Drivers!$C13*(Drivers!$E$818-Drivers!$D$818)+Drivers!$C14*(Drivers!$E$819-Drivers!$D$819)+Drivers!$C15*(Drivers!$E$820-Drivers!$D$820) -> 12333.333 | F50: =Drivers!$C11*(Drivers!$F$810-Drivers!$E$810)+Drivers!$C12*(Drivers!$F$811-Drivers!$E$811)+Drivers!$C13*(Drivers!$F$812-Drivers!$E$812)+Drivers!$C14*(Drivers!$F$813-Drivers!$E$813)+Drivers!$C15*(Drivers!$F$814-Drivers!$E$814)+Drivers!$C11*(Drivers!$F$816-Drivers!$E$816)+Drivers!$C12*(Drivers!$F$817-Drivers!$E$817)+Drivers!$C13*(Drivers!$F$818-Drivers!$E$818)+Drivers!$C14*(Drivers!$F$819-Drivers!$E$819)+Drivers!$C15*(Drivers!$F$820-Drivers!$E$820) -> 6166.6667 | G50: =Drivers!$C11*(Drivers!$G$810-Drivers!$F$810)+Drivers!$C12*(Drivers!$G$811-Drivers!$F$811)+Drivers!$C13*(Drivers!$G$812-Drivers!$F$812)+Drivers!$C14*(Drivers!$G$813-Drivers!$F$813)+Drivers!$C15*(Drivers!$G$814-Drivers!$F$814)+Drivers!$C11*(Drivers!$G$816-Drivers!$F$816)+Drivers!$C12*(Drivers!$G$817-Drivers!$F$817)+Drivers!$C13*(Drivers!$G$818-Drivers!$F$818)+Drivers!$C14*(Drivers!$G$819-Drivers!$F$819)+Drivers!$C15*(Drivers!$G$820-Drivers!$F$820) -> 10908.333 | H50: =Drivers!$C11*(Drivers!$H$810-Drivers!$G$810)+Drivers!$C12*(Drivers!$H$811-Drivers!$G$811)+Drivers!$C13*(Drivers!$H$812-Drivers!$G$812)+Drivers!$C14*(Drivers!$H$813-Drivers!$G$813)+Drivers!$C15*(Drivers!$H$814-Drivers!$G$814)+Drivers!$C11*(Drivers!$H$816-Drivers!$G$816)+Drivers!$C12*(Drivers!$H$817-Drivers!$G$817)+Drivers!$C13*(Drivers!$H$818-Drivers!$G$818)+Drivers!$C14*(Drivers!$H$819-Drivers!$G$819)+Drivers!$C15*(Drivers!$H$820-Drivers!$G$820) -> 40775 | I50: =Drivers!$C11*(Drivers!$I$810-Drivers!$H$810)+Drivers!$C12*(Drivers!$I$811-Drivers!$H$811)+Drivers!$C13*(Drivers!$I$812-Drivers!$H$812)+Drivers!$C14*(Drivers!$I$813-Drivers!$H$813)+Drivers!$C15*(Drivers!$I$814-Drivers!$H$814)+Drivers!$C11*(Drivers!$I$816-Drivers!$H$816)+Drivers!$C12*(Drivers!$I$817-Drivers!$H$817)+Drivers!$C13*(Drivers!$I$818-Drivers!$H$818)+Drivers!$C14*(Drivers!$I$819-Drivers!$H$819)+Drivers!$C15*(Drivers!$I$820-Drivers!$H$820) -> 27916.667 | P50: v34: derived from Drivers term-by-year block (rows 788-820). Formula: sum over 5 cohorts of (cars × delta_R1_frac + cars × delta_R2_frac). 2024A reported as 0 since no modeled cohort R1 lands in 2024 (Cohort 2021 R1 = 2025 under term-driven).
C51: 2025A disclosed = 21,500; delta vs modeled (< 15% target) | D51: =D50/21500-1 -> -0.069767442
C55: --- v36 LEGACY RENEWAL ENGINE: disclosed-expiration-driven; LPI uplift definition ---
C56: v36 2026-10-07: cars renewing per year sourced from 10-K disclosures (2024A/2025A/2026E) or legacy_fleet × 12 / forward_term (2027E+). Uplift $M = renewed_cars × expiring_rate × LPI; renewals spread evenly through year so half the uplift lands in year t and half in t+1 (carryover). Replaces v34/v35 lumpy single-term-per-year timing (deck slide 5 — superseded).
C57: Metric | D57: 2025A | E57: 2026E | F57: 2027E | G57: 2028E | H57: 2029E | I57: 2030E | J57: 2031E | K57: 2032E | L57: 2033E | M57: 2034E | N57: 2035E | P57: 2024A (ref)
C58: Renewal count (cars) | D58: 21500 | E58: 13700 | F58: =Drivers!$C$5*12/Drivers!$C$785 -> 22354 | G58: =Drivers!$C$5*12/Drivers!$C$785 -> 22354 | H58: =Drivers!$C$5*12/Drivers!$C$785 -> 22354 | I58: =Drivers!$C$5*12/Drivers!$C$785 -> 22354 | J58: =Drivers!$C$5*12/Drivers!$C$785 -> 22354 | K58: =Drivers!$C$5*12/Drivers!$C$785 -> 22354 | L58: =Drivers!$C$5*12/Drivers!$C$785 -> 22354 | M58: =Drivers!$C$5*12/Drivers!$C$785 -> 22354 | N58: =Drivers!$C$5*12/Drivers!$C$785 -> 22354 | O58: Source | P58: 19400
D59: 10-K FY2024 p.XX: "approximately 21,500 tank and freight cars scheduled to expire in 2025" | E59: 10-K FY2025 p.33 (research/coverage/rail/gatx-10ks/GATX-10K-FY2025.pdf): "approximately 13,700 tank and freight cars... scheduled to expire in 2026" (legacy fleet, before Wells pool) | P59: 10-K FY2023 p.XX: "leases for approximately 19,400 tank and freight cars... scheduled to expire in 2024"
C60: Renewal success rate | D60: =Drivers!$C$8 -> 0.873 | E60: =Drivers!$C$37 -> 0.808 | F60: =Drivers!$C$38 -> 0.85 | G60: =Drivers!$C$38 -> 0.85 | H60: =Drivers!$C$38 -> 0.85 | I60: =Drivers!$C$38 -> 0.85 | J60: =Drivers!$C$38 -> 0.85 | K60: =Drivers!$C$38 -> 0.85 | L60: =Drivers!$C$38 -> 0.85 | M60: =Drivers!$C$38 -> 0.85 | N60: =Drivers!$C$38 -> 0.85 | P60: =Drivers!$C$8 -> 0.873
C61: Renewed cars = renewal count × success rate | D61: =D58*D60 -> 18769.5 | E61: =E58*E60 -> 11069.6 | F61: =F58*F60 -> 19000.9 | G61: =G58*G60 -> 19000.9 | H61: =H58*H60 -> 19000.9 | I61: =I58*I60 -> 19000.9 | J61: =J58*J60 -> 19000.9 | K61: =K58*K60 -> 19000.9 | ... N61: =N58*N60 -> 19000.9 | P61: =P58*P60 -> 16936.2
C62: Legacy cars on lease (ex-boxcar × utilization) | D62: =Drivers!$C$5*Drivers!$C$7 -> 99587.07 | E62: =Drivers!$C$5*Drivers!$C$7 -> 99587.07 | F62: =Drivers!$C$5*Drivers!$C$7 -> 99587.07 | G62: =Drivers!$C$5*Drivers!$C$7 -> 99587.07 | H62: =Drivers!$C$5*Drivers!$C$7 -> 99587.07 | I62: =Drivers!$C$5*Drivers!$C$7 -> 99587.07 | J62: =Drivers!$C$5*Drivers!$C$7 -> 99587.07 | K62: =Drivers!$C$5*Drivers!$C$7 -> 99587.07 | ... N62: =Drivers!$C$5*Drivers!$C$7 -> 99587.07 | P62: =Drivers!$C$5*Drivers!$C$7 -> 99587.07
C63: LPI (year) | D63: =Drivers!$C$9 -> 0.219 | E63: =Drivers!$C$32 -> 0.185 | F63: =Drivers!$C$33 -> 0.15 | G63: =Drivers!$C$34 -> 0.1 | H63: =Drivers!$C$35 -> 0.05 | I63: =Drivers!$C$36 -> -0.02 | J63: =Drivers!$C$704 -> 0.02 | K63: =Drivers!$C$704 -> 0.02 | L63: =Drivers!$C$704 -> 0.02 | M63: =Drivers!$C$704 -> 0.02 | N63: =Drivers!$C$704 -> 0.02 | P63: =Drivers!$C$9 -> 0.219
C64: Expiring rate per car ($/car/yr) = prior-year legacy rev / cars on lease | D64: =P65*1000000/D62 -> 7860.1847 | E64: =D65*1000000/E62 -> 9581.5652 | F64: =E65*1000000/F62 -> 9842.2983 | G64: =F65*1000000/G62 -> 10081.655 | H64: =G65*1000000/H62 -> 10318.674 | I64: =H65*1000000/I62 -> 10464.07 | J64: =I65*1000000/J62 -> 10493.325 | K64: =J65*1000000/K62 -> 10493.38 | L64: =K65*1000000/L62 -> 10533.422 | ... N64: =M65*1000000/N62 -> 10613.812 | P64: =P65*1000000/P62 -> 7860.1847
C65: Legacy lease revenue ($M) — ENGINE OUTPUT | D65: =Drivers!$C$45 -> 954.2 | E65: =D65 + 0.5*E66 + 0.5*D66 -> 980.16565 | F65: =E65 + 0.5*F66 + 0.5*E66 -> 1004.0025 | G65: =F65 + 0.5*G66 + 0.5*F66 -> 1027.6065 | H65: =G65 + 0.5*H66 + 0.5*G66 -> 1042.0861 | I65: =H65 + 0.5*I66 + 0.5*H66 -> 1044.9995 | J65: =I65 + 0.5*J66 + 0.5*I66 -> 1045.005 | K65: =J65 + 0.5*K66 + 0.5*J66 -> 1048.9927 | L65: =K65 + 0.5*L66 + 0.5*K66 -> 1052.988 | ... N65: =M65 + 0.5*N66 + 0.5*M66 -> 1061.0243 | P65: =D65/(1+Drivers!$C$9) -> 782.77276
C66: Annual rate uplift ($M) = renewed × expiring_rate × LPI / 1e6 | D66: =D61*D64*D63/1000000 -> 32.30945 | E66: =E61*E64*E63/1000000 -> 19.621857 | F66: =F61*F64*F63/1000000 -> 28.051879 | G66: =G61*G64*G63/1000000 -> 19.156053 | H66: =H61*H64*H63/1000000 -> 9.8032044 | I66: =I61*I64*I63/1000000 -> -3.9765351 | J66: =J61*J64*J63/1000000 -> 3.9876522 | K66: =K61*K64*K63/1000000 -> 3.9876734 | ... N66: =N61*N64*N63/1000000 -> 4.0334397 | P66: =P61*P64*P63/1000000 -> 29.153644
C68: DIAGNOSTIC — cars renewing per year (= row 58) | D68: =D58 -> 21500 | E68: =E58 -> 13700 | F68: =F58 -> 22354 | G68: =G58 -> 22354 | H68: =H58 -> 22354 | I68: =I58 -> 22354 | J68: =J58 -> 22354 | K68: =K58 -> 22354 | ... N68: =N58 -> 22354 | P68: =P58 -> 19400

Sheet Acquired Pool
C2: ="Financial Statement Model - "&Cover!$D$5 -> Financial Statement Model - GATX Corporation
C3: $ mm except per share
C5: Company name | D5: =Cover!$D$5 -> GATX Corporation
C6: Ticker | D6: =Cover!$D$6 -> GATX
C7: Circ break 1=off, 0=on | D7: =Cover!$D$7 -> 1
C8: Latest closing share price | D8: =Cover!$D$8 -> 162.78
C9: Share price date | D9: =Cover!$D$9 -> 46303
C10: Latest fiscal year end | D10: =Cover!$D$10 -> 46022
C11: Shares outstanding (millions) | D11: =Cover!$D$11 -> 35.8
C13: ACQUIRED POOL (Wells Fargo) — carry blended rate forward, reprice expiring fraction
C15: Base: GABX H1 2026 revenue $271.5M half-year (10-Q Note 7 p.11). Full-year 2026E = 271.5 + Q2 run rate × 2.
C16: Blended rate rises with LPI on expiring fraction only. Cars held flat pending disclosure.
D18: 2025A | E18: 2026E | F18: 2027E | G18: 2028E | H18: 2029E | I18: 2030E | J18: 2031E | K18: 2032E | L18: 2033E | M18: 2034E | N18: 2035E
C19: Acquired pool cars | D19: 0 | E19: =Drivers!$C$25 -> 98535 | F19: =Drivers!$C$25 -> 98535 | G19: =Drivers!$C$25 -> 98535 | H19: =Drivers!$C$25 -> 98535 | I19: =Drivers!$C$25 -> 98535 | J19: =I19*(1+Drivers!$C$705) -> 99520.35 | K19: =J19*(1+Drivers!$C$705) -> 100515.55 | L19: =K19*(1+Drivers!$C$705) -> 101520.71 | M19: =L19*(1+Drivers!$C$705) -> 102535.92 | N19: =M19*(1+Drivers!$C$705) -> 103561.28
C20: Implied rate at close ($/car/yr) = H1 rev × 2 / cars | D20: 0 | E20: =Drivers!$C$26*2*1000000/Drivers!$C$25 -> 5510.7322 | F20: =E20 -> 5510.7322 | G20: =E20 -> 5510.7322 | H20: =E20 -> 5510.7322 | I20: =E20 -> 5510.7322 | J20: =I20 -> 5510.7322 | K20: =J20 -> 5510.7322 | L20: =K20 -> 5510.7322 | M20: =L20 -> 5510.7322 | N20: =M20 -> 5510.7322
C21: Fraction expiring this year | D21: 0 | E21: =Drivers!$C$176 -> 0.25 | F21: =Drivers!$C$176 -> 0.25 | G21: =Drivers!$C$176 -> 0.25 | H21: =Drivers!$C$176 -> 0.25 | I21: =Drivers!$C$176 -> 0.25 | J21: =Drivers!$C$176 -> 0.25 | K21: =Drivers!$C$176 -> 0.25 | L21: =Drivers!$C$176 -> 0.25 | ... N21: =Drivers!$C$176 -> 0.25
C22: Blended rate ($/car/yr) | D22: 0 | E22: =E20 -> 5510.7322 | F22: =E22*(1+Drivers!$C$33*F21) -> 5717.3847 | G22: =F22*(1+Drivers!$C$34*G21) -> 5860.3193 | H22: =G22*(1+Drivers!$C$35*H21) -> 5933.5733 | I22: =H22*(1+Drivers!$C$36*I21) -> 5903.9054 | J22: =I22*(1+Drivers!$C$704*J21) -> 5933.425 | K22: =J22*(1+Drivers!$C$704*K21) -> 5963.0921 | L22: =K22*(1+Drivers!$C$704*L21) -> 5992.9075 | M22: =L22*(1+Drivers!$C$704*M21) -> 6022.8721 | N22: =M22*(1+Drivers!$C$704*N21) -> 6052.9864
A23: x | C23: ACQUIRED POOL REVENUE ($M) | D23: =D19*D22/1000000 -> 0 | E23: =E19*E22/1000000 -> 543 | F23: =F19*F22/1000000 -> 563.3625 | G23: =G19*G22/1000000 -> 577.44656 | H23: =H19*H22/1000000 -> 584.66464 | I23: =I19*I22/1000000 -> 581.74132 | J23: =J19*J22/1000000 -> 590.49653 | K23: =K19*K22/1000000 -> 599.3835 | ... N23: =N19*N22/1000000 -> 626.85499 | P23: FY2026E gate: should be ~$543M (H1 $271.5 × 2 = $543M; Q2 was $136.6M × 2 = $273M for H2)
C25: v17 Item 2 (2026-09-26): 2031E-2035E revenue overrides pool mechanics and grows at Terminal_g (Drivers!B397). Rationale: pool LPI cycle completes by ~2029E; terminal state grows at g by construction.
C27: v23 (2026-09-28): terminal years 2031E-2035E — cars row 19 compounds at Terminal_fleet_growth; blended rate row 22 compounds at Terminal_LPI × fraction_expiring (same mechanic as 2026-2030 but with terminal LPI). Revenue row 23 is cars × rate / 1e6 (pool mechanics restored, v17 override retired).
A29: x | C29: SENSITIVITY: 2027E acquired-pool revenue and 2027E EPS at C176 = 20% / 25% / 30% (v26 1c)
C30: Fraction expiring | D30: 0.2 | E30: 0.25 | F30: 0.3
C31: 2027E blended rate ($/car/yr) | D31: =$E$20*(1+Drivers!$C$33*D30) -> 5676.0542 | E31: =$E$20*(1+Drivers!$C$33*E30) -> 5717.3847 | F31: =$E$20*(1+Drivers!$C$33*F30) -> 5758.7152
C32: 2027E acquired-pool revenue ($M) | D32: =$F$19*D31/1000000 -> 559.29 | E32: =$F$19*E31/1000000 -> 563.3625 | F32: =$F$19*F31/1000000 -> 567.435
C33: 2027E EPS ($/sh, model base + delta rev × (1-tax) / shares) | D33: ='3 Statement Forecast'!$F$33+(D32-$E$32)*(1-Drivers!$C$274)/Drivers!$C$277 -> 10.085393 | E33: ='3 Statement Forecast'!$F$33+(E32-$E$32)*(1-Drivers!$C$274)/Drivers!$C$277 -> 10.17606 | F33: ='3 Statement Forecast'!$F$33+(F32-$E$32)*(1-Drivers!$C$274)/Drivers!$C$277 -> 10.266727
C34: Note: base column (E) uses C176=0.25 same as model driver; F and D show effect of ±5pp.
A35: x | C35: IDLE-FILL MECHANISM (v38 Phase B, switch=Drivers!C763). Default OFF. Util rises 97%->99% over 2026E-2030E when switch=1.
C36: Idle_fill_incremental_cars | E36: ='Acquired Pool'!E19*(Drivers!$C$764-Drivers!$C$769)*Drivers!$C$763 -> 0 | F36: ='Acquired Pool'!F19*(Drivers!$C$765-Drivers!$C$769)*Drivers!$C$763 -> 0 | G36: ='Acquired Pool'!G19*(Drivers!$C$766-Drivers!$C$769)*Drivers!$C$763 -> 0 | H36: ='Acquired Pool'!H19*(Drivers!$C$767-Drivers!$C$769)*Drivers!$C$763 -> 0 | I36: ='Acquired Pool'!I19*(Drivers!$C$768-Drivers!$C$769)*Drivers!$C$763 -> 0
C37: Idle_fill_incremental_rev_$M | E37: ='Acquired Pool'!E36*'Acquired Pool'!E22/1000000 -> 0 | F37: ='Acquired Pool'!F36*'Acquired Pool'!F22/1000000 -> 0 | G37: ='Acquired Pool'!G36*'Acquired Pool'!G22/1000000 -> 0 | H37: ='Acquired Pool'!H36*'Acquired Pool'!H22/1000000 -> 0 | I37: ='Acquired Pool'!I36*'Acquired Pool'!I22/1000000 -> 0
C38: Idle_fill_incremental_maint_$M | E38: ='Acquired Pool'!E37*Drivers!$C$128 -> 0 | F38: ='Acquired Pool'!F37*Drivers!$C$128 -> 0 | G38: ='Acquired Pool'!G37*Drivers!$C$128 -> 0 | H38: ='Acquired Pool'!H37*Drivers!$C$128 -> 0 | I38: ='Acquired Pool'!I37*Drivers!$C$128 -> 0
C39: Idle_fill_incremental_pretax_$M (consolidated) | E39: ='Acquired Pool'!E37-'Acquired Pool'!E38 -> 0 | F39: ='Acquired Pool'!F37-'Acquired Pool'!F38 -> 0 | G39: ='Acquired Pool'!G37-'Acquired Pool'!G38 -> 0 | H39: ='Acquired Pool'!H37-'Acquired Pool'!H38 -> 0 | I39: ='Acquired Pool'!I37-'Acquired Pool'!I38 -> 0
C40: Idle_fill_GATX_attributable_$M (check figure; NOT fed into Segment P&L) | E40: ='Acquired Pool'!E39*Drivers!$C$251 -> 0 | F40: ='Acquired Pool'!F39*Drivers!$C$251 -> 0 | G40: ='Acquired Pool'!G39*Drivers!$C$251 -> 0 | H40: ='Acquired Pool'!H39*Drivers!$C$251 -> 0 | I40: ='Acquired Pool'!I39*Drivers!$C$251 -> 0

Sheet GABX Mini P&L
C2: ="Financial Statement Model - "&Cover!$D$5 -> Financial Statement Model - GATX Corporation
C3: $ mm except per share
C5: Company name | D5: =Cover!$D$5 -> GATX Corporation
C6: Ticker | D6: =Cover!$D$6 -> GATX
C7: Circ break 1=off, 0=on | D7: =Cover!$D$7 -> 1
C8: Latest closing share price | D8: =Cover!$D$8 -> 162.78
C9: Share price date | D9: =Cover!$D$9 -> 46303
C10: Latest fiscal year end | D10: =Cover!$D$10 -> 46022
C11: Shares outstanding (millions) | D11: =Cover!$D$11 -> 35.8
C13: GABX MINI P&L — 10-Q Note 7 p.11 direct. FY 2026E = Q1 + Q2 + Q2 × 2 (H2 at Q2 run-rate)
C14: v9 Section 1 fix (2026-09-25): GABX dispositions on row 10 flow into 3SF row 11 in addition to legacy Disposition Engine. E10=$70M (JV guide, Drivers!B57), F10=$70M (Drivers!B59), G10-I10 built from cars × gain/car anchor (Drivers rows 236-238). See NCI mechanic row 15 removes Brookfield's 70% via GABX_JV_share_GATX (Drivers!B73).
C15: Q2 net income = $10.8M (Note 7). H1 net income = $1.7M. Q1 = H1 − Q2 = −$9.1M (integration one-time).
A16: x | C16: FY 2026E = Q1 + Q2 + (Q2 × 2 for H2) = 2 × Q2 + Q1 = 2 × 10.8 + (−9.1) = $12.5M — NOT H1 × 2.
C17: FY 2027E = Q2 × 4 for underlying P&L, BUT dispositions use JV $70M guidance (transcript, not Q2×4).
D19: Q2 2026 (Note 7) | E19: H1 2026 (Note 7) | F19: Q1 2026 (derived) | G19: FY 2026E | H19: FY 2027E | I19: FY 2028E | J19: FY 2029E | K19: FY 2030E | L19: FY 2031E | M19: FY 2032E | N19: FY 2033E | O19: FY 2034E | P19: FY 2035E
C20: Total revenue | D20: =Drivers!$C$61 -> 136.6 | E20: =Drivers!$C$67 -> 271.5 | F20: =E20-D20 -> 134.9 | G20: =F20+D20*3 -> 544.7 | H20: ='Acquired Pool'!F23 -> 563.3625 | I20: ='Acquired Pool'!G23 -> 577.44656 | J20: ='Acquired Pool'!H23 -> 584.66464 | K20: ='Acquired Pool'!I23 -> 581.74132 | L20: ='Acquired Pool'!J23 -> 590.49653 | M20: ='Acquired Pool'!K23 -> 599.3835 | N20: ='Acquired Pool'!L23 -> 608.40422 | O20: ='Acquired Pool'!M23 -> 617.56071 | P20: ='Acquired Pool'!N23 -> 626.85499
C21: Total expenses (incl. mgmt fee to GATX) | D21: =Drivers!$C$62 -> -108.6 | E21: =Drivers!$C$68 -> -208.8 | F21: =E21-D21 -> -100.2 | G21: =F21+D21*3 -> -426 | H21: =D21*4 -> -434.4 | I21: =H21 -> -434.4 | J21: =H21 -> -434.4 | K21: =H21 -> -434.4 | L21: =K21 -> -434.4 | M21: =L21 -> -434.4 | N21: =M21 -> -434.4 | O21: =N21 -> -434.4 | P21: =O21 -> -434.4
C22: Net gain on dispositions | D22: =Drivers!$C$63 -> 21.9 | E22: =Drivers!$C$69 -> 23.9 | F22: =E22-D22 -> 2 | G22: =Drivers!$C$57 -> 70 | H22: =Drivers!$C$59 -> 70 | I22: =Drivers!$C$243 -> 69.999264 | J22: =Drivers!$C$244 -> 69.999264 | K22: =Drivers!$C$245 -> 69.999264 | L22: =K22*(1+Drivers!$C$397) -> 72.449238 | M22: =L22*(1+Drivers!$C$397) -> 74.984962 | N22: =M22*(1+Drivers!$C$397) -> 77.609435 | O22: =N22*(1+Drivers!$C$397) -> 80.325765 | P22: =O22*(1+Drivers!$C$397) -> 83.137167
C23: Interest expense | D23: =Drivers!$C$64 -> -36.6 | E23: =Drivers!$C$70 -> -80.5 | F23: =E23-D23 -> -43.9 | G23: =F23+D23*3 -> -153.7 | H23: =D23*4 -> -146.4 | I23: =H23 -> -146.4 | J23: =H23 -> -146.4 | K23: =H23 -> -146.4 | L23: =K23 -> -146.4 | M23: =L23 -> -146.4 | N23: =M23 -> -146.4 | O23: =N23 -> -146.4 | P23: =O23 -> -146.4
C24: Income before taxes | D24: =D20+D21+D22+D23 -> 13.3 | E24: =E20+E21+E22+E23 -> 6.1 | F24: =F20+F21+F22+F23 -> -7.2 | G24: =G20+G21+G22+G23 -> 35 | H24: =H20+H21+H22+H23 -> 52.5625 | I24: =I20+I21+I22+I23 -> 66.645826 | J24: =J20+J21+J22+J23 -> 73.863909 | K24: =K20+K21+K22+K23 -> 70.940585 | ... P24: =P20+P21+P22+P23 -> 129.19216
C25: Income taxes | D25: =Drivers!$C$65 -> -2.5 | E25: =Drivers!$C$71 -> -4.4 | F25: =E25-D25 -> -1.9 | G25: =F25+D25*3 -> -9.4 | H25: =D25*4 -> -10 | I25: =H25 -> -10 | J25: =H25 -> -10 | K25: =H25 -> -10 | L25: =K25 -> -10 | M25: =L25 -> -10 | N25: =M25 -> -10 | O25: =N25 -> -10 | P25: =O25 -> -10
C26: GABX Net Income | D26: =D24+D25 -> 10.8 | E26: =E24+E25 -> 1.7 | F26: =F24+F25 -> -9.1 | G26: =G24+G25 -> 25.6 | H26: =H24+H25 -> 42.5625 | I26: =I24+I25 -> 56.645826 | J26: =J24+J25 -> 63.863909 | K26: =K24+K25 -> 60.940585 | ... P26: =P24+P25 -> 119.19216
C27: NCI (per-year NCI%, row 18) — v9 Sec 2 rewire | D27: =D26*D30 -> 7.56 | E27: =E26*E30 -> 1.19 | F27: =F26*F30 -> -6.37 | G27: =G26*G30 -> 17.01504 | H27: =H26*H30 -> 25.309791 | I27: =I26*I30 -> 29.719233 | J27: =J26*J30 -> 29.035726 | K27: =K26*K30 -> 23.440796 | ... P27: =P26*P30 -> 4.1300084
C29: GATX ownership % (v9 Sec 2) | D29: =Drivers!$C$248 -> 0.3 | E29: =Drivers!$C$248 -> 0.3 | F29: =Drivers!$C$248 -> 0.3 | G29: =Drivers!$C$251 -> 0.33535 | H29: =Drivers!$C$252 -> 0.40535 | I29: =Drivers!$C$253 -> 0.47535 | J29: =Drivers!$C$254 -> 0.54535 | K29: =Drivers!$C$255 -> 0.61535 | L29: =Drivers!$C$488 -> 0.68535 | M29: =Drivers!$C$489 -> 0.75535 | N29: =Drivers!$C$490 -> 0.82535 | O29: =Drivers!$C$491 -> 0.89535 | P29: =Drivers!$C$492 -> 0.96535
C30: NCI % (= 1 − ownership) | D30: =1-D29 -> 0.7 | E30: =1-E29 -> 0.7 | F30: =1-F29 -> 0.7 | G30: =1-G29 -> 0.66465 | H30: =1-H29 -> 0.59465 | I30: =1-I29 -> 0.52465 | J30: =1-J29 -> 0.45465 | K30: =1-K29 -> 0.38465 | ... P30: =1-P29 -> 0.03465
C31: Tranche cash paid to Brookfield ($M) | G31: =IF(G30>0,Drivers!$C$258,0) -> 66.2 | H31: =IF(H30>0,Drivers!$C$259,0) -> 131.08911 | I31: =IF(I30>0,Drivers!$C$259,0) -> 131.08911 | J31: =IF(J30>0,Drivers!$C$259,0) -> 131.08911 | K31: =IF(K30>0,Drivers!$C$259,0) -> 131.08911 | L31: =IF(L30>0,Drivers!$C$493,0) -> 131.08911 | M31: =IF(M30>0,Drivers!$C$494,0) -> 131.08911 | N31: =IF(N30>0,Drivers!$C$495,0) -> 131.08911 | O31: =IF(O30>0,Drivers!$C$496,0) -> 131.08911 | P31: =IF(P30>0,Drivers!$C$497,0) -> 131.08911
C32: Memo: NCI mechanic now uses per-year NCI% (row 18) — row 15 formulas rewired

Sheet Segment P&L
C2: ="Financial Statement Model - "&Cover!$D$5 -> Financial Statement Model - GATX Corporation
C3: $ mm except per share
C5: Company name | D5: =Cover!$D$5 -> GATX Corporation
C6: Ticker | D6: =Cover!$D$6 -> GATX
C7: Circ break 1=off, 0=on | D7: =Cover!$D$7 -> 1
C8: Latest closing share price | D8: =Cover!$D$8 -> 162.78
C9: Share price date | D9: =Cover!$D$9 -> 46303
C10: Latest fiscal year end | D10: =Cover!$D$10 -> 46022
C11: Shares outstanding (millions) | D11: =Cover!$D$11 -> 35.8
C13: SEGMENT P&L — 2025A from 10-K; forward driven by Legacy Cohort + Acquired Pool
D15: 2025A | E15: 2026E | F15: 2027E | G15: 2028E | H15: 2029E | I15: 2030E | J15: 2031E | K15: 2032E | L15: 2033E | M15: 2034E | N15: 2035E
A16: x | C16: RAIL NORTH AMERICA
C17: Legacy cohort lease revenue | D17: ='Legacy Cohort Model'!D43+Drivers!$C$43+Drivers!$C$44 -> 1049.1 | E17: ='Legacy Cohort Model'!E43+Drivers!$C$43+Drivers!$C$44 -> 1075.0657 | F17: ='Legacy Cohort Model'!F43+Drivers!$C$43+Drivers!$C$44 -> 1098.9025 | G17: ='Legacy Cohort Model'!G43+Drivers!$C$43+Drivers!$C$44 -> 1122.5065 | H17: ='Legacy Cohort Model'!H43+Drivers!$C$43+Drivers!$C$44 -> 1136.9861 | I17: ='Legacy Cohort Model'!I43+Drivers!$C$43+Drivers!$C$44 -> 1139.8995 | J17: ='Legacy Cohort Model'!J43+Drivers!$C$43+Drivers!$C$44 -> 1139.905 | K17: ='Legacy Cohort Model'!K43+Drivers!$C$43+Drivers!$C$44 -> 1143.8927 | ... N17: ='Legacy Cohort Model'!N43+Drivers!$C$43+Drivers!$C$44 -> 1155.9243
C18: Acquired (Wells Fargo) lease revenue | D18: 0 | E18: ='Acquired Pool'!E23 -> 543 | F18: ='Acquired Pool'!F23 -> 563.3625 | G18: ='Acquired Pool'!G23 -> 577.44656 | H18: ='Acquired Pool'!H23 -> 584.66464 | I18: ='Acquired Pool'!I23 -> 581.74132 | J18: ='Acquired Pool'!J23 -> 590.49653 | K18: ='Acquired Pool'!K23 -> 599.3835 | L18: ='Acquired Pool'!L23 -> 608.40422 | ... N18: ='Acquired Pool'!N23 -> 626.85499
C19: Total Rail NA lease revenue | D19: =D17+D18 -> 1049.1 | E19: =E17+E18 -> 1618.0657 | F19: =F17+F18 -> 1662.265 | G19: =G17+G18 -> 1699.9531 | H19: =H17+H18 -> 1721.6508 | I19: =I17+I18 -> 1721.6408 | J19: =J17+J18 -> 1730.4015 | K19: =K17+K18 -> 1743.2762 | ... N19: =N17+N18 -> 1782.7792
C20: Rail NA other revenue | D20: =Drivers!$C$46 -> 137.3 | E20: =Drivers!$C$320 -> 160 | F20: =Drivers!$C$320*(1+Drivers!$C$321) -> 164.8 | G20: =Drivers!$C$320*(1+Drivers!$C$321)^2 -> 169.744 | H20: =Drivers!$C$320*(1+Drivers!$C$321)^3 -> 174.83632 | I20: =Drivers!$C$320*(1+Drivers!$C$321)^4 -> 180.08141 | J20: =I20*(1+Drivers!$C$397) -> 186.38426 | K20: =J20*(1+Drivers!$C$397) -> 192.90771 | L20: =K20*(1+Drivers!$C$397) -> 199.65948 | M20: =L20*(1+Drivers!$C$397) -> 206.64756 | N20: =M20*(1+Drivers!$C$397) -> 213.88022
C21: Total Rail NA revenue | D21: =D19+D20 -> 1186.4 | E21: =E19+E20 -> 1778.0657 | F21: =F19+F20 -> 1827.065 | G21: =G19+G20 -> 1869.6971 | H21: =H19+H20 -> 1896.4871 | I21: =I19+I20 -> 1901.7222 | J21: =J19+J20 -> 1916.7858 | K21: =K19+K20 -> 1936.1839 | ... N21: =N19+N20 -> 1996.6595
A23: x | C23: RAIL INTERNATIONAL
C24: Lease revenue | D24: =Drivers!$C$47 -> 366.1 | E24: =D24*(1+Drivers!$C$137) -> 391.727 | F24: =E24*(1+Drivers!$C$138) -> 411.31335 | G24: =F24*(1+Drivers!$C$306) -> 431.87902 | H24: =G24*(1+Drivers!$C$307) -> 453.47297 | I24: =H24*(1+Drivers!$C$308) -> 476.14662 | J24: =I24*(1+Drivers!$C$538) -> 492.81175 | K24: =J24*(1+Drivers!$C$539) -> 510.06016 | L24: =K24*(1+Drivers!$C$540) -> 527.91227 | M24: =L24*(1+Drivers!$C$541) -> 546.38919 | N24: =M24*(1+Drivers!$C$542) -> 565.51282
C25: Other revenue | D25: =Drivers!$C$48 -> 22.3 | E25: =D25*(1+Drivers!$C$137) -> 23.861 | F25: =E25*(1+Drivers!$C$138) -> 25.05405 | G25: =F25*(1+Drivers!$C$306) -> 26.306753 | H25: =G25*(1+Drivers!$C$307) -> 27.62209 | I25: =H25*(1+Drivers!$C$308) -> 29.003195 | J25: =I25*(1+Drivers!$C$538) -> 30.018306 | K25: =J25*(1+Drivers!$C$539) -> 31.068947 | L25: =K25*(1+Drivers!$C$540) -> 32.15636 | M25: =L25*(1+Drivers!$C$541) -> 33.281833 | N25: =M25*(1+Drivers!$C$542) -> 34.446697
C26: Total Rail Intl revenue | D26: =D24+D25 -> 388.4 | E26: =E24+E25 -> 415.588 | F26: =F24+F25 -> 436.3674 | G26: =G24+G25 -> 458.18577 | H26: =H24+H25 -> 481.09506 | I26: =I24+I25 -> 505.14981 | J26: =J24+J25 -> 522.83005 | K26: =K24+K25 -> 541.12911 | ... N26: =N24+N25 -> 599.95951
A28: x | C28: ENGINE LEASING
C29: Lease revenue (GEL) | D29: =Drivers!$C$49 -> 38.2 | E29: =D29*(1+Drivers!$C$139) -> 45.84 | F29: =E29*(1+Drivers!$C$140) -> 50.424 | G29: =F29*(1+Drivers!$C$309) -> 55.4664 | H29: =G29*(1+Drivers!$C$310) -> 61.01304 | I29: =H29*(1+Drivers!$C$311) -> 67.114344 | J29: =I29*(1+Drivers!$C$543) -> 69.463346 | K29: =J29*(1+Drivers!$C$544) -> 71.894563 | L29: =K29*(1+Drivers!$C$545) -> 74.410873 | M29: =L29*(1+Drivers!$C$546) -> 77.015253 | N29: =M29*(1+Drivers!$C$547) -> 79.710787
C30: Non-dedicated engine revenue | D30: =Drivers!$C$50 -> 86.7 | E30: =D30*(1+Drivers!$C$139) -> 104.04 | F30: =E30*(1+Drivers!$C$140) -> 114.444 | G30: =F30*(1+Drivers!$C$309) -> 125.8884 | H30: =G30*(1+Drivers!$C$310) -> 138.47724 | I30: =H30*(1+Drivers!$C$311) -> 152.32496 | J30: =I30*(1+Drivers!$C$543) -> 157.65634 | K30: =J30*(1+Drivers!$C$544) -> 163.17431 | L30: =K30*(1+Drivers!$C$545) -> 168.88541 | M30: =L30*(1+Drivers!$C$546) -> 174.7964 | N30: =M30*(1+Drivers!$C$547) -> 180.91427
C31: Total Engine Leasing revenue | D31: =D29+D30 -> 124.9 | E31: =E29+E30 -> 149.88 | F31: =F29+F30 -> 164.868 | G31: =G29+G30 -> 181.3548 | H31: =H29+H30 -> 199.49028 | I31: =I29+I30 -> 219.43931 | J31: =J29+J30 -> 227.11968 | K31: =K29+K30 -> 235.06887 | ... N31: =N29+N30 -> 260.62506
C33: OTHER
C34: Total revenue | D34: =Drivers!$C$51 -> 40.7 | E34: =D34*(1+Drivers!$C$141) -> 41.921 | F34: =E34*(1+Drivers!$C$141) -> 43.17863 | G34: =F34*(1+Drivers!$C$141) -> 44.473989 | H34: =G34*(1+Drivers!$C$141) -> 45.808209 | I34: =H34*(1+Drivers!$C$141) -> 47.182455 | J34: =I34*(1+Drivers!$C$397) -> 48.833841 | K34: =J34*(1+Drivers!$C$397) -> 50.543025 | L34: =K34*(1+Drivers!$C$397) -> 52.312031 | M34: =L34*(1+Drivers!$C$397) -> 54.142952 | N34: =M34*(1+Drivers!$C$397) -> 56.037955
A36: x | C36: CONSOLIDATED TOTAL REVENUE | D36: =D21+D26+D31+D34 -> 1740.4 | E36: =E21+E26+E31+E34 -> 2385.4547 | F36: =F21+F26+F31+F34 -> 2471.4791 | G36: =G21+G26+G31+G34 -> 2553.7116 | H36: =H21+H26+H31+H34 -> 2622.8806 | I36: =I21+I26+I31+I34 -> 2673.4938 | J36: =J21+J26+J31+J34 -> 2715.5694 | K36: =K21+K26+K31+K34 -> 2762.9249 | ... N36: =N21+N26+N31+N34 -> 2913.282
C38: Memo: Mgmt fee — JV (already in row 8 Rail NA other rev) | D38: 0 | E38: =Drivers!$C$260 -> 44 | F38: =Drivers!$C$260 -> 44 | G38: =Drivers!$C$260 -> 44 | H38: =Drivers!$C$260 -> 44 | I38: =Drivers!$C$260 -> 44 | J38: =Drivers!$C$260 -> 44 | K38: =Drivers!$C$260 -> 44 | L38: =Drivers!$C$260 -> 44 | ... N38: =Drivers!$C$260 -> 44
C39: Memo: Mgmt fee — Brookfield-book (already in row 8 Rail NA other rev) | D39: 0 | E39: =Drivers!$C$261 -> 11 | F39: =Drivers!$C$261 -> 11 | G39: =Drivers!$C$261 -> 11 | H39: =Drivers!$C$261 -> 11 | I39: =Drivers!$C$261 -> 11 | J39: =Drivers!$C$261 -> 11 | K39: =Drivers!$C$261 -> 11 | L39: =Drivers!$C$261 -> 11 | ... N39: =Drivers!$C$261 -> 11
C40: v10 Fix 1 (2026-09-25): Rail NA other rev 2026E anchored to $160M (H1 $80.0M × 2, release line 157). Mgmt fees are memo only — the $80M H1 actual already includes them. Prior v9 formula double-counted by adding fees on top of anchor.
C42: Idle fill upside (switch controlled) — consolidated pretax $M | E42: ='Acquired Pool'!E39*Drivers!$C$763 -> 0 | F42: ='Acquired Pool'!F39*Drivers!$C$763 -> 0 | G42: ='Acquired Pool'!G39*Drivers!$C$763 -> 0 | H42: ='Acquired Pool'!H39*Drivers!$C$763 -> 0 | I42: ='Acquired Pool'!I39*Drivers!$C$763 -> 0 | J42: 0 | K42: 0 | L42: 0 | M42: 0 | N42: 0
C43: v38 note: row 42 is a switch-controlled memo. With switch (Drivers!C763)=0 the row is identically zero and v37 outputs are preserved to the cent. Phase B 2026-10-08.

Sheet Disposition Engine
C2: ="Financial Statement Model - "&Cover!$D$5 -> Financial Statement Model - GATX Corporation
C3: $ mm except per share
C5: Company name | D5: =Cover!$D$5 -> GATX Corporation
C6: Ticker | D6: =Cover!$D$6 -> GATX
C7: Circ break 1=off, 0=on | D7: =Cover!$D$7 -> 1
C8: Latest closing share price | D8: =Cover!$D$8 -> 162.78
C9: Share price date | D9: =Cover!$D$9 -> 46303
C10: Latest fiscal year end | D10: =Cover!$D$10 -> 46022
C11: Shares outstanding (millions) | D11: =Cover!$D$11 -> 35.8
C13: GATX DISPOSITION ENGINE (v9, added 2026-09-24)
C14: Rail NA ex boxcars. Formulas only. Inputs → Drivers rows 201-233.
A16: x | C16: SECTION A — HISTORICAL CARS & GAINS
D17: 2020 | E17: 2021 | F17: 2022 | G17: 2023 | H17: 2024 | I17: 2025
C18: Cars sold (Rail NA ex boxcars) | G18: =Drivers!C201 -> 3154 | H18: =Drivers!C202 -> 2127 | I18: =Drivers!C203 -> 3413
C19: Cars scrapped | G19: =Drivers!C204 -> 1286 | H19: =Drivers!C205 -> 1433 | I19: =Drivers!C206 -> 2305
C20: Consolidated net gain on dispositions ($M, all segments) | D20: =Historicals!D28 -> 41.7 | E20: =Historicals!E28 -> 105.9 | F20: =Historicals!F28 -> 77.9 | G20: =Historicals!G28 -> 130.3 | H20: =Historicals!H28 -> 138.3 | I20: =Historicals!I28 -> 136.9
C21: Rail NA remarketing gains ($M) — dispo of owned + residual sharing | G21: =Drivers!C207 -> 112.1 | H21: =Drivers!C208 -> 119.9 | I21: =Drivers!C209 -> 117
C22: Rail NA non-remarketing gains ($M) — scrapping | G22: =Drivers!C210 -> 8.4 | H22: =Drivers!C211 -> 12.9 | I22: =Drivers!C212 -> 16.6
C23: Rail NA asset impairments ($M) | G23: =Drivers!C213 -> 0 | H23: =Drivers!C214 -> 0 | I23: =Drivers!C215 -> -3.6
C24: Gain per car sold ($/car) = remarketing gains / cars sold | G24: =G21*1000000/G18 -> 35542.169 | H24: =H21*1000000/H18 -> 56370.475 | I24: =I21*1000000/I18 -> 34280.691
C25: Scrap gain per car ($/car) = non-remarketing / cars scrapped | G25: =G22*1000000/G19 -> 6531.8818 | H25: =H22*1000000/H19 -> 9002.0935 | I25: =I22*1000000/I19 -> 7201.7354
C26: 2023-2025 average gain per car sold ($/car) | J26: =AVERAGE(G24:I24) -> 42064.445
C27: 2023-2025 average scrap gain per car ($/car) | J27: =AVERAGE(G25:I25) -> 7578.5702
A29: x | C29: SECTION B — SCRAP VALUE FLOOR
C30: Scrap steel price ($/ton) | D30: =Drivers!C216 -> 420
C31: Avg car weight (tons) | D31: =Drivers!C217 -> 32
C32: Scrap value per car ($/car) = price × weight | D32: =D30*D31 -> 13440
A34: x | C34: SECTION C — FORECAST 2026E-2030E
D35: 2026 | E35: 2027 | F35: 2028 | G35: 2029 | H35: 2030 | I35: 2031 | J35: 2032 | K35: 2033 | L35: 2034 | M35: 2035
C36: Cars sold (Drivers, base = 2025) | D36: =Drivers!C218 -> 3413 | E36: =Drivers!C219 -> 3413 | F36: =Drivers!C220 -> 3413 | G36: =Drivers!C221 -> 3413 | H36: =Drivers!C222 -> 3413 | I36: =Drivers!C463 -> 3413 | J36: =$I$36 -> 3413 | K36: =$I$36 -> 3413 | L36: =$I$36 -> 3413 | M36: =$I$36 -> 3413 | N36: =$I$36 -> 3413
C37: Cars scrapped (Drivers, base = 2025) | D37: =Drivers!C223 -> 2305 | E37: =Drivers!C224 -> 2305 | F37: =Drivers!C225 -> 2305 | G37: =Drivers!C226 -> 2305 | H37: =Drivers!C227 -> 2305 | I37: =Drivers!C468 -> 2305 | J37: =$I$37 -> 2305 | K37: =$I$37 -> 2305 | L37: =$I$37 -> 2305 | M37: =$I$37 -> 2305 | N37: =$I$37 -> 2305
C38: Gain per car sold ($/car) = toggle×avg + (1−toggle)×2025_level | D38: =Drivers!$C$228*$J$26+(1-Drivers!$C$228)*$I$24 -> 34280.691 | E38: =Drivers!$C$228*$J$26+(1-Drivers!$C$228)*$I$24 -> 34280.691 | F38: =Drivers!$C$228*$J$26+(1-Drivers!$C$228)*$I$24 -> 34280.691 | G38: =Drivers!$C$228*$J$26+(1-Drivers!$C$228)*$I$24 -> 34280.691 | H38: =Drivers!$C$228*$J$26+(1-Drivers!$C$228)*$I$24 -> 34280.691 | I38: =Drivers!$C$228*$J$26+(1-Drivers!$C$228)*$I$24 -> 34280.691 | J38: =Drivers!$C$228*$J$26+(1-Drivers!$C$228)*$I$24 -> 34280.691 | K38: =Drivers!$C$228*$J$26+(1-Drivers!$C$228)*$I$24 -> 34280.691 | ... M38: =Drivers!$C$228*$J$26+(1-Drivers!$C$228)*$I$24 -> 34280.691
C39: Scrap gain per car ($/car) = MAX(toggle×avg+(1−toggle)×2025, scrap floor) | D39: =Drivers!$C$228*$J$27+(1-Drivers!$C$228)*$I$25 -> 7201.7354 | E39: =Drivers!$C$228*$J$27+(1-Drivers!$C$228)*$I$25 -> 7201.7354 | F39: =Drivers!$C$228*$J$27+(1-Drivers!$C$228)*$I$25 -> 7201.7354 | G39: =Drivers!$C$228*$J$27+(1-Drivers!$C$228)*$I$25 -> 7201.7354 | H39: =Drivers!$C$228*$J$27+(1-Drivers!$C$228)*$I$25 -> 7201.7354 | I39: =Drivers!$C$228*$J$27+(1-Drivers!$C$228)*$I$25 -> 7201.7354 | J39: =Drivers!$C$228*$J$27+(1-Drivers!$C$228)*$I$25 -> 7201.7354 | K39: =Drivers!$C$228*$J$27+(1-Drivers!$C$228)*$I$25 -> 7201.7354 | ... M39: =Drivers!$C$228*$J$27+(1-Drivers!$C$228)*$I$25 -> 7201.7354
C40: Rail NA remarketing gains ($M) = cars sold × gain per car / 1e6 | D40: =D36*D38/1000000 -> 117 | E40: =E36*E38/1000000 -> 117 | F40: =F36*F38/1000000 -> 117 | G40: =G36*G38/1000000 -> 117 | H40: =H36*H38/1000000 -> 117 | I40: =I36*I38/1000000 -> 117 | J40: =J36*J38/1000000 -> 117 | K40: =K36*K38/1000000 -> 117 | ... M40: =M36*M38/1000000 -> 117
C41: Rail NA non-remarketing gains ($M) = cars scrapped × scrap gain per car / 1e6 | D41: =D37*D39/1000000 -> 16.6 | E41: =E37*E39/1000000 -> 16.6 | F41: =F37*F39/1000000 -> 16.6 | G41: =G37*G39/1000000 -> 16.6 | H41: =H37*H39/1000000 -> 16.6 | I41: =I37*I39/1000000 -> 16.6 | J41: =J37*J39/1000000 -> 16.6 | K41: =K37*K39/1000000 -> 16.6 | ... M41: =M37*M39/1000000 -> 16.6
C42: Rail NA total dispositions ($M) = remarketing + non-remarketing | D42: =D40+D41 -> 133.6 | E42: =E40+E41 -> 133.6 | F42: =F40+F41 -> 133.6 | G42: =G40+G41 -> 133.6 | H42: =H40+H41 -> 133.6 | I42: =I40+I41 -> 133.6 | J42: =J40+J41 -> 133.6 | K42: =K40+K41 -> 133.6 | ... M42: =M40+M41 -> 133.6
C43: Non-RailNA dispositions ($M) — Rail Intl + EL + Other (flat assumption) | D43: =Drivers!C229 -> 6.9 | E43: =Drivers!C230 -> 6.9 | F43: =Drivers!C231 -> 6.9 | G43: =Drivers!C232 -> 6.9 | H43: =Drivers!C233 -> 6.9 | I43: =Drivers!C473 -> 6.9 | J43: =Drivers!C474 -> 6.9 | K43: =Drivers!C475 -> 6.9 | L43: =Drivers!C476 -> 6.9 | M43: =Drivers!C477 -> 6.9
C44: Legacy net gain on dispositions ($M) — GABX added in 3SF row 11 | D44: =D42+D43 -> 140.5 | E44: =E42+E43 -> 140.5 | F44: =F42+F43 -> 140.5 | G44: =G42+G43 -> 140.5 | H44: =H42+H43 -> 140.5 | I44: =H44*(1+Drivers!$C$397) -> 145.4175 | J44: =$I$44 -> 145.4175 | K44: =$I$44 -> 145.4175 | L44: =$I$44 -> 145.4175 | M44: =$I$44 -> 145.4175 | N44: =$I$44 -> 145.4175
A46: x | C46: SECTION D — RECONCILIATION TO 2026 GUIDANCE (v10 Fix 3 rewrite)
C47: Guidance 2026 legacy ($M) | D47: =Drivers!C56 -> 130
C48: Model 2026 LEGACY ($M) — Rail NA + non-RailNA (excludes GABX) | D48: =D44 -> 140.5
C49: Delta legacy: model − guidance ($M) | D49: =D48-D47 -> 10.5
C50: Legacy note: H1 2026 legacy net gain on disposition = ~$94M (Bob Lyons, Q2 call pg 3). Mgmt language: "running ahead of where we thought we would be on the legacy portfolio through the first six months, and we'll probably exceed [$130M] a little bit." Model $154.9M is running ahead consistent with mgmt. | D50: =D44 -> 140.5
C51: Guidance 2026 consolidated ($M) = legacy + JV | D51: =Drivers!C56+Drivers!C57 -> 200
C52: Model 2026 CONSOLIDATED ($M) = legacy engine + GABX row 10 | D52: =D44+'GABX Mini P&L'!G22 -> 210.5
C53: Delta consolidated: model − guidance ($M) | D53: =D52-D51 -> 10.5
C54: MEMO — 2026 dispositions AT 2023-2025 average gain per car (toggle = 1)
C55: Rail NA remarketing @ avg ($M) = 2026 cars sold × avg gain / 1e6 | D55: =D36*J26/1000000 -> 143.56595
C56: Rail NA non-remarketing @ avg ($M) = 2026 cars scrapped × MAX(avg,floor) / 1e6 | D56: =D37*MAX(J27,D32)/1000000 -> 30.9792
C57: Non-RailNA @ 2025 flat ($M) | D57: =Drivers!C229 -> 6.9
C58: Consolidated @ 2023-2025 avg ($M) | D58: =D55+D56+D57 -> 181.44515
C59: Delta (avg-based − guidance) ($M) | D59: =D58-D49 -> 170.94515
C61: v17 Item 2 (2026-09-26): Disposition Engine row 32 columns G:K (2031E-2035E) overridden to grow at Terminal_g (Drivers!B397). Rationale: fleet grows at g → dispositions scale with fleet in real terms. Sub-component rows 28-31 in those columns still compute per cohort mechanic but no longer sum to row 32. Base (2030E, col F) retains cohort-driven value; growth applies from 2030E.

Sheet Thesis Test
C2: ="Financial Statement Model - "&Cover!$D$5 -> Financial Statement Model - GATX Corporation
C3: $ mm except per share
C5: Company name | D5: =Cover!$D$5 -> GATX Corporation
C6: Ticker | D6: =Cover!$D$6 -> GATX
C7: Circ break 1=off, 0=on | D7: =Cover!$D$7 -> 1
C8: Latest closing share price | D8: =Cover!$D$8 -> 162.78
C9: Share price date | D9: =Cover!$D$9 -> 46303
C10: Latest fiscal year end | D10: =Cover!$D$10 -> 46022
C11: Shares outstanding (millions) | D11: =Cover!$D$11 -> 35.8
C13: GATX FSM v6 — THESIS TEST
C14: Formulas only; every input links to Drivers or a prior model sheet. No literals.
A16: x | C16: SECTION A — EARNINGS SOURCES vs USES ($M)
D17: 2026E | E17: 2027E | F17: 2028E | G17: 2029E | H17: 2030E | I17: 2031E | J17: 2032E | K17: 2033E | L17: 2034E | M17: 2035E
C18: 1. Repricing uplift (ΔLegacy + AP blended rate delta × cars) | D18: =('Legacy Cohort Model'!E43-'Legacy Cohort Model'!D43) -> 25.965654 | E18: =('Legacy Cohort Model'!F43-'Legacy Cohort Model'!E43)+('Acquired Pool'!F22-'Acquired Pool'!E22)*'Acquired Pool'!F19/1000000 -> 44.199368 | F18: =('Legacy Cohort Model'!G43-'Legacy Cohort Model'!F43)+('Acquired Pool'!G22-'Acquired Pool'!F22)*'Acquired Pool'!G19/1000000 -> 37.688028 | G18: =('Legacy Cohort Model'!H43-'Legacy Cohort Model'!G43)+('Acquired Pool'!H22-'Acquired Pool'!G22)*'Acquired Pool'!H19/1000000 -> 21.697711 | H18: =('Legacy Cohort Model'!I43-'Legacy Cohort Model'!H43)+('Acquired Pool'!I22-'Acquired Pool'!H22)*'Acquired Pool'!I19/1000000 -> -0.0099885701 | I18: =('Legacy Cohort Model'!I43-'Legacy Cohort Model'!H43)+('Acquired Pool'!I22-'Acquired Pool'!H22)*'Acquired Pool'!I19*'Acquired Pool'!I21/1000000 -> 2.1825038 | J18: =('Legacy Cohort Model'!J43-'Legacy Cohort Model'!I43)+('Acquired Pool'!J22-'Acquired Pool'!I22)*'Acquired Pool'!J19*'Acquired Pool'!J21/1000000 -> 0.74000697 | K18: =('Legacy Cohort Model'!K43-'Legacy Cohort Model'!J43)+('Acquired Pool'!K22-'Acquired Pool'!J22)*'Acquired Pool'!K19*'Acquired Pool'!K21/1000000 -> 4.7331647 | L18: =('Legacy Cohort Model'!L43-'Legacy Cohort Model'!K43)+('Acquired Pool'!L22-'Acquired Pool'!K22)*'Acquired Pool'!L19*'Acquired Pool'!L21/1000000 -> 4.7520034 | M18: =('Legacy Cohort Model'!M43-'Legacy Cohort Model'!L43)+('Acquired Pool'!M22-'Acquired Pool'!L22)*'Acquired Pool'!M19*'Acquired Pool'!M21/1000000 -> 4.7786233
C19: 1a. Acquired base (WFR acquisition step-in, 2026E only) | D19: ='Acquired Pool'!E23-'Acquired Pool'!D23 -> 543 | E19: 0 | F19: 0 | G19: 0 | H19: 0 | I19: 0 | J19: 0 | K19: 0 | L19: 0 | M19: 0
C20: 2. Legacy dispositions + GATX's 33.5% share of GABX JV gains (attributable to GATX) | D20: ='3 Statement Forecast'!E23-Drivers!$C$175*'GABX Mini P&L'!G22 -> 163.9745 | E20: ='3 Statement Forecast'!F23-Drivers!$C$175*'GABX Mini P&L'!H22 -> 163.9745 | F20: ='3 Statement Forecast'!G23-Drivers!$C$175*'GABX Mini P&L'!I22 -> 163.97425 | G20: ='3 Statement Forecast'!H23-Drivers!$C$175*'GABX Mini P&L'!J22 -> 163.97425 | H20: ='3 Statement Forecast'!I23-Drivers!$C$175*'GABX Mini P&L'!K22 -> 163.97425 | I20: ='3 Statement Forecast'!J23-Drivers!$C$175*'GABX Mini P&L'!L22 -> 169.71335 | J20: ='3 Statement Forecast'!K23-Drivers!$C$175*'GABX Mini P&L'!M22 -> 170.56371 | K20: ='3 Statement Forecast'!L23-Drivers!$C$175*'GABX Mini P&L'!N22 -> 171.44382 | ... M20: ='3 Statement Forecast'!N23-Drivers!$C$175*'GABX Mini P&L'!P22 -> 173.29755
C21: 3. RRPF dividends received | D21: =Drivers!$C$115 -> 140 | E21: =Drivers!$C$116 -> 130 | F21: =Drivers!$C$297 -> 130 | G21: =Drivers!$C$298 -> 130 | H21: =Drivers!$C$299 -> 130 | I21: =Drivers!$C$533 -> 130 | J21: =Drivers!$C$534 -> 130 | K21: =Drivers!$C$535 -> 130 | L21: =Drivers!$C$536 -> 130 | M21: =Drivers!$C$537 -> 130
C22: 4. Interest expense vs 2025A base (use) | D22: =-('Debt & Interest'!E31-Drivers!$C$151) -> 197.32599 | E22: =-('Debt & Interest'!F31-Drivers!$C$151) -> 224.20826 | F22: =-('Debt & Interest'!G31-Drivers!$C$151) -> 250.89824 | G22: =-('Debt & Interest'!H31-Drivers!$C$151) -> 277.79324 | H22: =-('Debt & Interest'!I31-Drivers!$C$151) -> 324.26368 | I22: =-('Debt & Interest'!J31-Drivers!$C$151) -> 336.01591 | J22: =-('Debt & Interest'!K31-Drivers!$C$151) -> 348.27159 | K22: =-('Debt & Interest'!L31-Drivers!$C$151) -> 357.88756 | ... M22: =-('Debt & Interest'!N31-Drivers!$C$151) -> 376.15406
C23: 5. Refinancing cost (maturities × Δrate) | D23: =Drivers!$C$90*(Drivers!$C$102-Drivers!$C$170) -> 4.24646 | E23: =Drivers!$C$91*(Drivers!$C$102-Drivers!$C$170) -> 5.68227 | F23: =Drivers!$C$92*(Drivers!$C$102-Drivers!$C$170) -> 5.48998 | G23: =Drivers!$C$93*(Drivers!$C$102-Drivers!$C$170) -> 5.695 | H23: =Drivers!$C$94*(Drivers!$C$102-Drivers!$C$170) -> 17.26188 | I23: 0 | J23: 0 | K23: 0 | L23: 0 | M23: 0
C24: 6. Net (sources − uses) [row6+row7+row8+row9−row10−row11] | D24: =D18+D19+D20+D21-D22-D23 -> 671.3677 | E24: =E18+E19+E20+E21-E22-E23 -> 108.28334 | F24: =F18+F19+F20+F21-F22-F23 -> 75.274061 | G24: =G18+G19+G20+G21-G22-G23 -> 32.183724 | H24: =H18+H19+H20+H21-H22-H23 -> -47.561295 | I24: =I18+I19+I20+I21-I22-I23 -> -34.120051 | J24: =J18+J19+J20+J21-J22-J23 -> -46.967879 | K24: =K18+K19+K20+K21-K22-K23 -> -51.710576 | ... M24: =M18+M19+M20+M21-M22-M23 -> -68.077892
C25: 7. Cumulative net | D25: =D24 -> 671.3677 | E25: =D25+E24 -> 779.65104 | F25: =E25+F24 -> 854.9251 | G25: =F25+G24 -> 887.10883 | H25: =G25+H24 -> 839.54753 | I25: =H25+I24 -> 805.42748 | J25: =I25+J24 -> 758.4596 | K25: =J25+K24 -> 706.74903 | L25: =K25+L24 -> 646.68117 | M25: =L25+M24 -> 578.60328
C26: Notes v7: Row 6 = repricing ONLY (delta legacy + delta AP rate × cars). Row 7 = one-time WFR acquisition step-in for 2026E. Row 8 uses Drivers!GABX_NCI_share (0.7) for GABX NCI share. Row 11 uses Drivers!Weighted_fixed_coupon as the 'old' rate for Δrate.
A29: x | C29: SECTION B — 2027E EPS SENSITIVITY (7×7 grid)
C30: Linear approximation around the base case (LPI = base 15%, rate = 5.30% new issue).
C32: LPI 2027 delta ↓ / New-issue rate → | D32: =Drivers!$C$160 -> 0.048 | E32: =Drivers!$C$161 -> 0.053 | F32: =Drivers!$C$162 -> 0.058 | G32: =Drivers!$C$163 -> 0.06 | H32: =Drivers!$C$164 -> 0.065 | I32: =Drivers!$C$165 -> 0.07 | J32: =Drivers!$C$166 -> 0.075
C33: =Drivers!$C$153 -> -0.1 | D33: ='3 Statement Forecast'!$F$33+(Drivers!$C$153*Drivers!$C$12*(Drivers!$C$18*Drivers!$C$23)*Drivers!$C$39*(1-Drivers!$C$76)/Drivers!$C$78/1000000)-((Drivers!$C$160-Drivers!$C$102)*(Drivers!$C$90+Drivers!$C$91+Drivers!$C$152)*(1-Drivers!$C$76)/Drivers!$C$78) -> 10.135261 | E33: ='3 Statement Forecast'!$F$33+(Drivers!$C$153*Drivers!$C$12*(Drivers!$C$18*Drivers!$C$23)*Drivers!$C$39*(1-Drivers!$C$76)/Drivers!$C$78/1000000)-((Drivers!$C$161-Drivers!$C$102)*(Drivers!$C$90+Drivers!$C$91+Drivers!$C$152)*(1-Drivers!$C$76)/Drivers!$C$78) -> 9.8763327 | F33: ='3 Statement Forecast'!$F$33+(Drivers!$C$153*Drivers!$C$12*(Drivers!$C$18*Drivers!$C$23)*Drivers!$C$39*(1-Drivers!$C$76)/Drivers!$C$78/1000000)-((Drivers!$C$162-Drivers!$C$102)*(Drivers!$C$90+Drivers!$C$91+Drivers!$C$152)*(1-Drivers!$C$76)/Drivers!$C$78) -> 9.6174044 | G33: ='3 Statement Forecast'!$F$33+(Drivers!$C$153*Drivers!$C$12*(Drivers!$C$18*Drivers!$C$23)*Drivers!$C$39*(1-Drivers!$C$76)/Drivers!$C$78/1000000)-((Drivers!$C$163-Drivers!$C$102)*(Drivers!$C$90+Drivers!$C$91+Drivers!$C$152)*(1-Drivers!$C$76)/Drivers!$C$78) -> 9.5138332 | H33: ='3 Statement Forecast'!$F$33+(Drivers!$C$153*Drivers!$C$12*(Drivers!$C$18*Drivers!$C$23)*Drivers!$C$39*(1-Drivers!$C$76)/Drivers!$C$78/1000000)-((Drivers!$C$164-Drivers!$C$102)*(Drivers!$C$90+Drivers!$C$91+Drivers!$C$152)*(1-Drivers!$C$76)/Drivers!$C$78) -> 9.2549049 | I33: ='3 Statement Forecast'!$F$33+(Drivers!$C$153*Drivers!$C$12*(Drivers!$C$18*Drivers!$C$23)*Drivers!$C$39*(1-Drivers!$C$76)/Drivers!$C$78/1000000)-((Drivers!$C$165-Drivers!$C$102)*(Drivers!$C$90+Drivers!$C$91+Drivers!$C$152)*(1-Drivers!$C$76)/Drivers!$C$78) -> 8.9959767 | J33: ='3 Statement Forecast'!$F$33+(Drivers!$C$153*Drivers!$C$12*(Drivers!$C$18*Drivers!$C$23)*Drivers!$C$39*(1-Drivers!$C$76)/Drivers!$C$78/1000000)-((Drivers!$C$166-Drivers!$C$102)*(Drivers!$C$90+Drivers!$C$91+Drivers!$C$152)*(1-Drivers!$C$76)/Drivers!$C$78) -> 8.7370485
C34: =Drivers!$C$154 -> -0.05 | D34: ='3 Statement Forecast'!$F$33+(Drivers!$C$154*Drivers!$C$12*(Drivers!$C$18*Drivers!$C$23)*Drivers!$C$39*(1-Drivers!$C$76)/Drivers!$C$78/1000000)-((Drivers!$C$160-Drivers!$C$102)*(Drivers!$C$90+Drivers!$C$91+Drivers!$C$152)*(1-Drivers!$C$76)/Drivers!$C$78) -> 10.285125 | E34: ='3 Statement Forecast'!$F$33+(Drivers!$C$154*Drivers!$C$12*(Drivers!$C$18*Drivers!$C$23)*Drivers!$C$39*(1-Drivers!$C$76)/Drivers!$C$78/1000000)-((Drivers!$C$161-Drivers!$C$102)*(Drivers!$C$90+Drivers!$C$91+Drivers!$C$152)*(1-Drivers!$C$76)/Drivers!$C$78) -> 10.026196 | F34: ='3 Statement Forecast'!$F$33+(Drivers!$C$154*Drivers!$C$12*(Drivers!$C$18*Drivers!$C$23)*Drivers!$C$39*(1-Drivers!$C$76)/Drivers!$C$78/1000000)-((Drivers!$C$162-Drivers!$C$102)*(Drivers!$C$90+Drivers!$C$91+Drivers!$C$152)*(1-Drivers!$C$76)/Drivers!$C$78) -> 9.7672681 | G34: ='3 Statement Forecast'!$F$33+(Drivers!$C$154*Drivers!$C$12*(Drivers!$C$18*Drivers!$C$23)*Drivers!$C$39*(1-Drivers!$C$76)/Drivers!$C$78/1000000)-((Drivers!$C$163-Drivers!$C$102)*(Drivers!$C$90+Drivers!$C$91+Drivers!$C$152)*(1-Drivers!$C$76)/Drivers!$C$78) -> 9.6636968 | H34: ='3 Statement Forecast'!$F$33+(Drivers!$C$154*Drivers!$C$12*(Drivers!$C$18*Drivers!$C$23)*Drivers!$C$39*(1-Drivers!$C$76)/Drivers!$C$78/1000000)-((Drivers!$C$164-Drivers!$C$102)*(Drivers!$C$90+Drivers!$C$91+Drivers!$C$152)*(1-Drivers!$C$76)/Drivers!$C$78) -> 9.4047686 | I34: ='3 Statement Forecast'!$F$33+(Drivers!$C$154*Drivers!$C$12*(Drivers!$C$18*Drivers!$C$23)*Drivers!$C$39*(1-Drivers!$C$76)/Drivers!$C$78/1000000)-((Drivers!$C$165-Drivers!$C$102)*(Drivers!$C$90+Drivers!$C$91+Drivers!$C$152)*(1-Drivers!$C$76)/Drivers!$C$78) -> 9.1458404 | J34: ='3 Statement Forecast'!$F$33+(Drivers!$C$154*Drivers!$C$12*(Drivers!$C$18*Drivers!$C$23)*Drivers!$C$39*(1-Drivers!$C$76)/Drivers!$C$78/1000000)-((Drivers!$C$166-Drivers!$C$102)*(Drivers!$C$90+Drivers!$C$91+Drivers!$C$152)*(1-Drivers!$C$76)/Drivers!$C$78) -> 8.8869122
C35: =Drivers!$C$155 -> 0 | D35: ='3 Statement Forecast'!$F$33+(Drivers!$C$155*Drivers!$C$12*(Drivers!$C$18*Drivers!$C$23)*Drivers!$C$39*(1-Drivers!$C$76)/Drivers!$C$78/1000000)-((Drivers!$C$160-Drivers!$C$102)*(Drivers!$C$90+Drivers!$C$91+Drivers!$C$152)*(1-Drivers!$C$76)/Drivers!$C$78) -> 10.434988 | E35: ='3 Statement Forecast'!$F$33+(Drivers!$C$155*Drivers!$C$12*(Drivers!$C$18*Drivers!$C$23)*Drivers!$C$39*(1-Drivers!$C$76)/Drivers!$C$78/1000000)-((Drivers!$C$161-Drivers!$C$102)*(Drivers!$C$90+Drivers!$C$91+Drivers!$C$152)*(1-Drivers!$C$76)/Drivers!$C$78) -> 10.17606 | F35: ='3 Statement Forecast'!$F$33+(Drivers!$C$155*Drivers!$C$12*(Drivers!$C$18*Drivers!$C$23)*Drivers!$C$39*(1-Drivers!$C$76)/Drivers!$C$78/1000000)-((Drivers!$C$162-Drivers!$C$102)*(Drivers!$C$90+Drivers!$C$91+Drivers!$C$152)*(1-Drivers!$C$76)/Drivers!$C$78) -> 9.9171317 | G35: ='3 Statement Forecast'!$F$33+(Drivers!$C$155*Drivers!$C$12*(Drivers!$C$18*Drivers!$C$23)*Drivers!$C$39*(1-Drivers!$C$76)/Drivers!$C$78/1000000)-((Drivers!$C$163-Drivers!$C$102)*(Drivers!$C$90+Drivers!$C$91+Drivers!$C$152)*(1-Drivers!$C$76)/Drivers!$C$78) -> 9.8135605 | H35: ='3 Statement Forecast'!$F$33+(Drivers!$C$155*Drivers!$C$12*(Drivers!$C$18*Drivers!$C$23)*Drivers!$C$39*(1-Drivers!$C$76)/Drivers!$C$78/1000000)-((Drivers!$C$164-Drivers!$C$102)*(Drivers!$C$90+Drivers!$C$91+Drivers!$C$152)*(1-Drivers!$C$76)/Drivers!$C$78) -> 9.5546322 | I35: ='3 Statement Forecast'!$F$33+(Drivers!$C$155*Drivers!$C$12*(Drivers!$C$18*Drivers!$C$23)*Drivers!$C$39*(1-Drivers!$C$76)/Drivers!$C$78/1000000)-((Drivers!$C$165-Drivers!$C$102)*(Drivers!$C$90+Drivers!$C$91+Drivers!$C$152)*(1-Drivers!$C$76)/Drivers!$C$78) -> 9.295704 | J35: ='3 Statement Forecast'!$F$33+(Drivers!$C$155*Drivers!$C$12*(Drivers!$C$18*Drivers!$C$23)*Drivers!$C$39*(1-Drivers!$C$76)/Drivers!$C$78/1000000)-((Drivers!$C$166-Drivers!$C$102)*(Drivers!$C$90+Drivers!$C$91+Drivers!$C$152)*(1-Drivers!$C$76)/Drivers!$C$78) -> 9.0367758
C36: =Drivers!$C$156 -> 0.05 | D36: ='3 Statement Forecast'!$F$33+(Drivers!$C$156*Drivers!$C$12*(Drivers!$C$18*Drivers!$C$23)*Drivers!$C$39*(1-Drivers!$C$76)/Drivers!$C$78/1000000)-((Drivers!$C$160-Drivers!$C$102)*(Drivers!$C$90+Drivers!$C$91+Drivers!$C$152)*(1-Drivers!$C$76)/Drivers!$C$78) -> 10.584852 | E36: ='3 Statement Forecast'!$F$33+(Drivers!$C$156*Drivers!$C$12*(Drivers!$C$18*Drivers!$C$23)*Drivers!$C$39*(1-Drivers!$C$76)/Drivers!$C$78/1000000)-((Drivers!$C$161-Drivers!$C$102)*(Drivers!$C$90+Drivers!$C$91+Drivers!$C$152)*(1-Drivers!$C$76)/Drivers!$C$78) -> 10.325924 | F36: ='3 Statement Forecast'!$F$33+(Drivers!$C$156*Drivers!$C$12*(Drivers!$C$18*Drivers!$C$23)*Drivers!$C$39*(1-Drivers!$C$76)/Drivers!$C$78/1000000)-((Drivers!$C$162-Drivers!$C$102)*(Drivers!$C$90+Drivers!$C$91+Drivers!$C$152)*(1-Drivers!$C$76)/Drivers!$C$78) -> 10.066995 | G36: ='3 Statement Forecast'!$F$33+(Drivers!$C$156*Drivers!$C$12*(Drivers!$C$18*Drivers!$C$23)*Drivers!$C$39*(1-Drivers!$C$76)/Drivers!$C$78/1000000)-((Drivers!$C$163-Drivers!$C$102)*(Drivers!$C$90+Drivers!$C$91+Drivers!$C$152)*(1-Drivers!$C$76)/Drivers!$C$78) -> 9.9634241 | H36: ='3 Statement Forecast'!$F$33+(Drivers!$C$156*Drivers!$C$12*(Drivers!$C$18*Drivers!$C$23)*Drivers!$C$39*(1-Drivers!$C$76)/Drivers!$C$78/1000000)-((Drivers!$C$164-Drivers!$C$102)*(Drivers!$C$90+Drivers!$C$91+Drivers!$C$152)*(1-Drivers!$C$76)/Drivers!$C$78) -> 9.7044959 | I36: ='3 Statement Forecast'!$F$33+(Drivers!$C$156*Drivers!$C$12*(Drivers!$C$18*Drivers!$C$23)*Drivers!$C$39*(1-Drivers!$C$76)/Drivers!$C$78/1000000)-((Drivers!$C$165-Drivers!$C$102)*(Drivers!$C$90+Drivers!$C$91+Drivers!$C$152)*(1-Drivers!$C$76)/Drivers!$C$78) -> 9.4455677 | J36: ='3 Statement Forecast'!$F$33+(Drivers!$C$156*Drivers!$C$12*(Drivers!$C$18*Drivers!$C$23)*Drivers!$C$39*(1-Drivers!$C$76)/Drivers!$C$78/1000000)-((Drivers!$C$166-Drivers!$C$102)*(Drivers!$C$90+Drivers!$C$91+Drivers!$C$152)*(1-Drivers!$C$76)/Drivers!$C$78) -> 9.1866395
C37: =Drivers!$C$157 -> 0.1 | D37: ='3 Statement Forecast'!$F$33+(Drivers!$C$157*Drivers!$C$12*(Drivers!$C$18*Drivers!$C$23)*Drivers!$C$39*(1-Drivers!$C$76)/Drivers!$C$78/1000000)-((Drivers!$C$160-Drivers!$C$102)*(Drivers!$C$90+Drivers!$C$91+Drivers!$C$152)*(1-Drivers!$C$76)/Drivers!$C$78) -> 10.734715 | E37: ='3 Statement Forecast'!$F$33+(Drivers!$C$157*Drivers!$C$12*(Drivers!$C$18*Drivers!$C$23)*Drivers!$C$39*(1-Drivers!$C$76)/Drivers!$C$78/1000000)-((Drivers!$C$161-Drivers!$C$102)*(Drivers!$C$90+Drivers!$C$91+Drivers!$C$152)*(1-Drivers!$C$76)/Drivers!$C$78) -> 10.475787 | F37: ='3 Statement Forecast'!$F$33+(Drivers!$C$157*Drivers!$C$12*(Drivers!$C$18*Drivers!$C$23)*Drivers!$C$39*(1-Drivers!$C$76)/Drivers!$C$78/1000000)-((Drivers!$C$162-Drivers!$C$102)*(Drivers!$C$90+Drivers!$C$91+Drivers!$C$152)*(1-Drivers!$C$76)/Drivers!$C$78) -> 10.216859 | G37: ='3 Statement Forecast'!$F$33+(Drivers!$C$157*Drivers!$C$12*(Drivers!$C$18*Drivers!$C$23)*Drivers!$C$39*(1-Drivers!$C$76)/Drivers!$C$78/1000000)-((Drivers!$C$163-Drivers!$C$102)*(Drivers!$C$90+Drivers!$C$91+Drivers!$C$152)*(1-Drivers!$C$76)/Drivers!$C$78) -> 10.113288 | H37: ='3 Statement Forecast'!$F$33+(Drivers!$C$157*Drivers!$C$12*(Drivers!$C$18*Drivers!$C$23)*Drivers!$C$39*(1-Drivers!$C$76)/Drivers!$C$78/1000000)-((Drivers!$C$164-Drivers!$C$102)*(Drivers!$C$90+Drivers!$C$91+Drivers!$C$152)*(1-Drivers!$C$76)/Drivers!$C$78) -> 9.8543595 | I37: ='3 Statement Forecast'!$F$33+(Drivers!$C$157*Drivers!$C$12*(Drivers!$C$18*Drivers!$C$23)*Drivers!$C$39*(1-Drivers!$C$76)/Drivers!$C$78/1000000)-((Drivers!$C$165-Drivers!$C$102)*(Drivers!$C$90+Drivers!$C$91+Drivers!$C$152)*(1-Drivers!$C$76)/Drivers!$C$78) -> 9.5954313 | J37: ='3 Statement Forecast'!$F$33+(Drivers!$C$157*Drivers!$C$12*(Drivers!$C$18*Drivers!$C$23)*Drivers!$C$39*(1-Drivers!$C$76)/Drivers!$C$78/1000000)-((Drivers!$C$166-Drivers!$C$102)*(Drivers!$C$90+Drivers!$C$91+Drivers!$C$152)*(1-Drivers!$C$76)/Drivers!$C$78) -> 9.3365031
C38: =Drivers!$C$158 -> 0.15 | D38: ='3 Statement Forecast'!$F$33+(Drivers!$C$158*Drivers!$C$12*(Drivers!$C$18*Drivers!$C$23)*Drivers!$C$39*(1-Drivers!$C$76)/Drivers!$C$78/1000000)-((Drivers!$C$160-Drivers!$C$102)*(Drivers!$C$90+Drivers!$C$91+Drivers!$C$152)*(1-Drivers!$C$76)/Drivers!$C$78) -> 10.884579 | E38: ='3 Statement Forecast'!$F$33+(Drivers!$C$158*Drivers!$C$12*(Drivers!$C$18*Drivers!$C$23)*Drivers!$C$39*(1-Drivers!$C$76)/Drivers!$C$78/1000000)-((Drivers!$C$161-Drivers!$C$102)*(Drivers!$C$90+Drivers!$C$91+Drivers!$C$152)*(1-Drivers!$C$76)/Drivers!$C$78) -> 10.625651 | F38: ='3 Statement Forecast'!$F$33+(Drivers!$C$158*Drivers!$C$12*(Drivers!$C$18*Drivers!$C$23)*Drivers!$C$39*(1-Drivers!$C$76)/Drivers!$C$78/1000000)-((Drivers!$C$162-Drivers!$C$102)*(Drivers!$C$90+Drivers!$C$91+Drivers!$C$152)*(1-Drivers!$C$76)/Drivers!$C$78) -> 10.366723 | G38: ='3 Statement Forecast'!$F$33+(Drivers!$C$158*Drivers!$C$12*(Drivers!$C$18*Drivers!$C$23)*Drivers!$C$39*(1-Drivers!$C$76)/Drivers!$C$78/1000000)-((Drivers!$C$163-Drivers!$C$102)*(Drivers!$C$90+Drivers!$C$91+Drivers!$C$152)*(1-Drivers!$C$76)/Drivers!$C$78) -> 10.263151 | H38: ='3 Statement Forecast'!$F$33+(Drivers!$C$158*Drivers!$C$12*(Drivers!$C$18*Drivers!$C$23)*Drivers!$C$39*(1-Drivers!$C$76)/Drivers!$C$78/1000000)-((Drivers!$C$164-Drivers!$C$102)*(Drivers!$C$90+Drivers!$C$91+Drivers!$C$152)*(1-Drivers!$C$76)/Drivers!$C$78) -> 10.004223 | I38: ='3 Statement Forecast'!$F$33+(Drivers!$C$158*Drivers!$C$12*(Drivers!$C$18*Drivers!$C$23)*Drivers!$C$39*(1-Drivers!$C$76)/Drivers!$C$78/1000000)-((Drivers!$C$165-Drivers!$C$102)*(Drivers!$C$90+Drivers!$C$91+Drivers!$C$152)*(1-Drivers!$C$76)/Drivers!$C$78) -> 9.745295 | J38: ='3 Statement Forecast'!$F$33+(Drivers!$C$158*Drivers!$C$12*(Drivers!$C$18*Drivers!$C$23)*Drivers!$C$39*(1-Drivers!$C$76)/Drivers!$C$78/1000000)-((Drivers!$C$166-Drivers!$C$102)*(Drivers!$C$90+Drivers!$C$91+Drivers!$C$152)*(1-Drivers!$C$76)/Drivers!$C$78) -> 9.4863668
C39: =Drivers!$C$159 -> 0.2 | D39: ='3 Statement Forecast'!$F$33+(Drivers!$C$159*Drivers!$C$12*(Drivers!$C$18*Drivers!$C$23)*Drivers!$C$39*(1-Drivers!$C$76)/Drivers!$C$78/1000000)-((Drivers!$C$160-Drivers!$C$102)*(Drivers!$C$90+Drivers!$C$91+Drivers!$C$152)*(1-Drivers!$C$76)/Drivers!$C$78) -> 11.034443 | E39: ='3 Statement Forecast'!$F$33+(Drivers!$C$159*Drivers!$C$12*(Drivers!$C$18*Drivers!$C$23)*Drivers!$C$39*(1-Drivers!$C$76)/Drivers!$C$78/1000000)-((Drivers!$C$161-Drivers!$C$102)*(Drivers!$C$90+Drivers!$C$91+Drivers!$C$152)*(1-Drivers!$C$76)/Drivers!$C$78) -> 10.775515 | F39: ='3 Statement Forecast'!$F$33+(Drivers!$C$159*Drivers!$C$12*(Drivers!$C$18*Drivers!$C$23)*Drivers!$C$39*(1-Drivers!$C$76)/Drivers!$C$78/1000000)-((Drivers!$C$162-Drivers!$C$102)*(Drivers!$C$90+Drivers!$C$91+Drivers!$C$152)*(1-Drivers!$C$76)/Drivers!$C$78) -> 10.516586 | G39: ='3 Statement Forecast'!$F$33+(Drivers!$C$159*Drivers!$C$12*(Drivers!$C$18*Drivers!$C$23)*Drivers!$C$39*(1-Drivers!$C$76)/Drivers!$C$78/1000000)-((Drivers!$C$163-Drivers!$C$102)*(Drivers!$C$90+Drivers!$C$91+Drivers!$C$152)*(1-Drivers!$C$76)/Drivers!$C$78) -> 10.413015 | H39: ='3 Statement Forecast'!$F$33+(Drivers!$C$159*Drivers!$C$12*(Drivers!$C$18*Drivers!$C$23)*Drivers!$C$39*(1-Drivers!$C$76)/Drivers!$C$78/1000000)-((Drivers!$C$164-Drivers!$C$102)*(Drivers!$C$90+Drivers!$C$91+Drivers!$C$152)*(1-Drivers!$C$76)/Drivers!$C$78) -> 10.154087 | I39: ='3 Statement Forecast'!$F$33+(Drivers!$C$159*Drivers!$C$12*(Drivers!$C$18*Drivers!$C$23)*Drivers!$C$39*(1-Drivers!$C$76)/Drivers!$C$78/1000000)-((Drivers!$C$165-Drivers!$C$102)*(Drivers!$C$90+Drivers!$C$91+Drivers!$C$152)*(1-Drivers!$C$76)/Drivers!$C$78) -> 9.8951586 | J39: ='3 Statement Forecast'!$F$33+(Drivers!$C$159*Drivers!$C$12*(Drivers!$C$18*Drivers!$C$23)*Drivers!$C$39*(1-Drivers!$C$76)/Drivers!$C$78/1000000)-((Drivers!$C$166-Drivers!$C$102)*(Drivers!$C$90+Drivers!$C$91+Drivers!$C$152)*(1-Drivers!$C$76)/Drivers!$C$78) -> 9.6362304
C40: Shaded: 5.30% new-issue column (base) and 6.00% column (kill test); 0% LPI row is base. Center cell = model base-case 2027E EPS.
A43: x | C43: SECTION C — BREAK-EVEN & KILL TEST
C45: Break-even LPI 2027 (solve Row 6 + 7 + 8 + 9 = 10 + 11) | D45: =(E22+E23-E19-E20-E21-0)/((Drivers!$C$12*(Drivers!$C$18*Drivers!$C$23)*Drivers!$C$39/1000000)+('Acquired Pool'!F19*'Acquired Pool'!E22*Drivers!$C$176/1000000)) -> -0.23330779 | E45: Algebra: LPI = (Row10 + Row11 - Row7 - Row8 - Row9 - Row6_ex_LPI) / (cars_renewing × expiring_rate × phasing) — every term links to Drivers or the Acquired Pool / Legacy Cohort sheets.
C46: 2027E EPS at 6.00% new-issue rate (Kill test) | D46: ='3 Statement Forecast'!$F$33-((Drivers!$C$105-Drivers!$C$102)*(Drivers!$C$91+Drivers!$C$88)*(1-Drivers!$C$76)/Drivers!$C$78) -> 9.9875687
C47: Break-even is solved algebraically from Section A rows 6-11 (2027E col C). Kill test moves 6.00% only through the refi + net-new issuance component (not the entire debt stack).

Sheet Valuation
C2: ="Financial Statement Model - "&Cover!$D$5 -> Financial Statement Model - GATX Corporation
C3: $ mm except per share
C5: Company name | D5: =Cover!$D$5 -> GATX Corporation
C6: Ticker | D6: =Cover!$D$6 -> GATX
C7: Circ break 1=off, 0=on | D7: =Cover!$D$7 -> 1
C8: Latest closing share price | D8: =Cover!$D$8 -> 162.78
C9: Share price date | D9: =Cover!$D$9 -> 46303
C10: Latest fiscal year end | D10: =Cover!$D$10 -> 46022
C11: Shares outstanding (millions) | D11: =Cover!$D$11 -> 35.8
C13: GATX FSM v8 — VALUATION
C14: Formulas only. Every input is a Drivers cell with citation. P/E and P/B triangulation, 3-scenario probability-weighted target, and M38 implied-metric decomposition (see Section D).
C16: Reference stats (computed with formulas over source series)
C17: GATX NTM P/E — 10y daily distribution
C18: Series source | D18: GATX-NTM-PE-10y-2026-09-21.xlsx!Worksheet!D2:D2607 (2606 daily obs, 2016-09-26 to 2026-09-21)
C19: NTM P/E 25th pct | D19: =PERCENTILE(N212:N2817,0.25) -> 14.78
C20: NTM P/E median | D20: =MEDIAN(N212:N2817) -> 16.34
C21: NTM P/E 75th pct | D21: =PERCENTILE(N212:N2817,0.75) -> 17.6875
C22: NTM P/E current (2026-09-21) | D22: =INDEX(N212:N2817,COUNTA(N212:N2817)) -> 16.45
A24: x | C24: Peer NTM P/E median (AER, WLFC, TRN, GBX) | D24: =MEDIAN(Drivers!C183,Drivers!C184,Drivers!C185,Drivers!C186) -> 10.679857
A25: x | C25: Peer P/B median (AER, WLFC, TRN, GBX) | D25: =MEDIAN(Drivers!C188,Drivers!C189,Drivers!C190,Drivers!C191) -> 1.478895
C26: GATX 25y P/B — low | D26: =MIN(O212:O236) -> 1.202086
C27: GATX 25y P/B — median | D27: =MEDIAN(O212:O236) -> 1.632152
C28: GATX 25y P/B — high | D28: =MAX(O212:O236) -> 2.260367
C29: Current price | D29: =Drivers!C179 -> 162.78
C30: BVPS 2026E ($ per sh) | D30: =('3 Statement Forecast'!E58)/Drivers!C77 -> 81.814027
C31: BVPS 2027E ($ per sh) | D31: =('3 Statement Forecast'!F58)/Drivers!C78 -> 87.222697
A34: x | C34: SECTION A — P/E VALUATION GRID
C36: EPS ($) \ Multiple (x) | D36: 25th pct | E36: Median | F36: 75th pct | G36: Current | H36: Peer median
C37: Multiple value (link) | D37: =D19 -> 14.78 | E37: =D20 -> 16.34 | F37: =D21 -> 17.6875 | G37: =D22 -> 16.45 | H37: =D24 -> 10.679857
C39: Model 2027E EPS | D39: ='3 Statement Forecast'!$F$33*D$37 -> 150.40217 | E39: ='3 Statement Forecast'!$F$33*E$37 -> 166.27682 | F39: ='3 Statement Forecast'!$F$33*F$37 -> 179.98906 | G39: ='3 Statement Forecast'!$F$33*G$37 -> 167.39619 | H39: ='3 Statement Forecast'!$F$33*H$37 -> 108.67887 | I39: ='3 Statement Forecast'!F33 -> 10.17606
C40: Consensus 2027E EPS | D40: =Drivers!$C$194*D$37 -> 166.57947 | E40: =Drivers!$C$194*E$37 -> 184.1616 | F40: =Drivers!$C$194*F$37 -> 199.34874 | G40: =Drivers!$C$194*G$37 -> 185.40137 | H40: =Drivers!$C$194*H$37 -> 120.3684 | I40: =Drivers!C194 -> 11.2706
C41: DCF (Gordon TV): bear = DCF!D121 (WACC +100bps), base = DCF!B106, bull = DCF!D113 (WACC -100bps) — equity/sh after bridge | D41: =DCF!F133 -> 214.81319 | E41: =DCF!D118 -> 458.93013 | F41: =DCF!F125 -> 1041.8152
C42: % upside vs current price
C43: Model 2027E EPS → % upside | D43: =(D39-$D$29)/$D$29 -> -0.076040261 | E43: =(E39-$D$29)/$D$29 -> 0.021481876 | F43: =(F39-$D$29)/$D$29 -> 0.10571975 | G43: =(G39-$D$29)/$D$29 -> 0.028358437 | H43: =(H39-$D$29)/$D$29 -> -0.33235738
C44: Consensus 2027E EPS → % upside | D44: =(D40-$D$29)/$D$29 -> 0.023341123 | E44: =(E40-$D$29)/$D$29 -> 0.13135277 | F44: =(F40-$D$29)/$D$29 -> 0.22465129 | G44: =(G40-$D$29)/$D$29 -> 0.13896898 | H44: =(H40-$D$29)/$D$29 -> -0.26054554
C45: DCF → % upside vs current | D45: =(D41-$D$29)/$D$29 -> 0.31965345 | E45: =(E41-$D$29)/$D$29 -> 1.8193275 | F45: =(F41-$D$29)/$D$29 -> 5.4001424
C46: FCFE base (Gordon perpetuity, PRIMARY per-share) | D46: =FCFE!D74 -> 73.610215
A47: x | C47: SECTION B — P/B CROSS-CHECK
C48: FCFE base → % upside vs current | D48: =(D46-$D$29)/$D$29 -> -0.54779325
A49: x | C49: BVPS ($) \ P/B (x) | D49: GATX 25y low | E49: GATX 25y median | F49: GATX 25y high | G49: Peer median
C50: Multiple value (link) | D50: =D26 -> 1.202086 | E50: =D27 -> 1.632152 | F50: =D28 -> 2.260367 | G50: =D25 -> 1.478895
A52: x | C52: BVPS 2026E | D52: =$D$30*D$50 -> 98.347497 | E52: =$D$30*E$50 -> 133.53293 | F52: =$D$30*F$50 -> 184.92973 | G52: =$D$30*G$50 -> 120.99436 | I52: =D30 -> 81.814027
A53: x | C53: BVPS 2027E | D53: =$D$31*D$50 -> 104.84918 | E53: =$D$31*E$50 -> 142.3607 | F53: =$D$31*F$50 -> 197.1553 | G53: =$D$31*G$50 -> 128.99321 | I53: =D31 -> 87.222697
C55: Target comparison — P/E (2027E model @ NTM median) vs P/B (2027E BVPS @ GATX 25y median):
C56: P/E method target | D56: =E39 -> 166.27682
C57: P/B method target | D57: =E53 -> 142.3607
C58: Difference (P/E − P/B, $) | D58: =D56-D57 -> 23.916121
C59: Note | D59: If P/E and P/B disagree by more than ~10%, the models are pricing different things: P/E capitalizes earnings visibility; P/B capitalizes book equity growth. The wider gap = more sensitivity to whichever multiple you weight.
A62: x | C62: SECTION C — 3-SCENARIO PROBABILITY-WEIGHTED TARGET
C63: SECTION C v27 rewire: Bear/Bull EPS now link to Section C1 snapshot block; Thesis Test linear grid superseded by scenario snapshots for the target.
C64: Case | D64: EPS source cell | E64: EPS ($) | F64: Multiple (x) | G64: Price ($) | H64: Probability | I64: Weighted price
C65: Bear | D65: 'Thesis Test'!E21 × 25th pct NTM P/E | E65: =D152 -> 10.119224 | F65: =D19 -> 14.78 | G65: =E65*F65 -> 149.56213 | H65: =Drivers!C196 -> 0.25 | I65: =G65*H65 -> 37.390534
C66: Base | D66: '3 Statement Forecast'!D21 × NTM median | E66: ='3 Statement Forecast'!F33 -> 10.17606 | F66: =D20 -> 16.34 | G66: =E66*F66 -> 166.27682 | H66: =Drivers!C197 -> 0.5 | I66: =G66*H66 -> 83.13841
C67: Bull | D67: 'Thesis Test'!B27 × 75th pct NTM P/E | E67: =F152 -> 10.658934 | F67: =D21 -> 17.6875 | G67: =E67*F67 -> 188.5299 | H67: =Drivers!C198 -> 0.25 | I67: =G67*H67 -> 47.132475
C68: DCF | D68: DCF!B_price (Gordon TV, PRIMARY per-share) | E68: =DCF!D118 -> 458.93013 | F68: 1 | G68: =E68*F68 -> 458.93013 | H68: =Drivers!$C$408 -> 0 | I68: =G68*H68 -> 0
C69: Probability-weighted target | I69: =SUM(I65:I67) -> 167.66142
C70: Current price | I70: =D29 -> 162.78
C71: Upside vs current price | I71: =(I69-I70)/I70 -> 0.029987825
C72: Weighted target INCLUDING DCF and FCFE (if either Prob_weight > 0) | I72: =SUM(I65:I68)+I102 -> 167.66142
C73: Weighted target EXCLUDING DCF (P/E only, preserves existing) | I73: =SUM(I65:I67) -> 167.66142
A74: x | C74: SECTION D — WHAT THE PRICE IMPLIES (M38)
C76: M38 rule (shortened):
C77: (1) Invert at the CURRENT market price, not the analyst's target. (2) Use reference multiples the analyst did NOT choose (subject's own historical distribution, sector or matched-comp medians). (3) On a matched basis (NTM to NTM, forward-year to forward-year). (4) Decompose total return into multiple contribution, earnings contribution, and dividend yield.
C79: GATX 10y median NTM P/E (reference the analyst did NOT choose as target multiple) | D79: =D20 -> 16.34
C80: Implied 2027 EPS at median = Current price / GATX 10y median NTM P/E | D80: =$D$29/$D$20 -> 9.9620563
C81: Model 2027E EPS | D81: ='3 Statement Forecast'!F33 -> 10.17606
C82: Gap $ = Model EPS − Implied EPS at median | D82: =D81-D80 -> 0.21400366
C83: 1pp LPI sensitivity on 2027 EPS ($/sh per +1pp LPI, from Thesis Test grid @ 5.30% base rate) | D83: =('Thesis Test'!E36-'Thesis Test'!E35)/Drivers!C322 -> 0.02997273
C84: Gap in LPI points = Gap $ / 1pp LPI sensitivity | D84: =D82/D83 -> 7.1399454
C86: Decomposition — total return from current price to analyst target
C87: Analyst target multiple (uses P/E method target from Section A: model 2027E EPS × NTM median) | D87: =E37 -> 16.34
C88: Current implied 2027 multiple = Current price / Consensus 2027 EPS | D88: =$D$29/Drivers!C194 -> 14.442887
C89: Multiple contribution to target return = (Target multiple − Current implied multiple) / Current implied multiple | D89: =(D87-D88)/D88 -> 0.13135277
C90: Earnings contribution = (Model 2027 EPS − Consensus 2027 EPS) / Consensus 2027 EPS | D90: =('3 Statement Forecast'!F33-Drivers!C194)/Drivers!C194 -> -0.09711462
C91: Dividend yield (NTM 2027E) | D91: =Drivers!C181 -> 0.01517
C92: Total return decomposition (multiple + earnings + dividend) | D92: =D89+D90+D91 -> 0.04940815
C94: M38 re-read — DCF-implied vs P/E-implied 2027 EPS
C95: DCF-implied per-share value (Gordon, base) | D95: =DCF!D118 -> 458.93013
C96: P/E-implied per-share value (median × Model 2027 EPS) | D96: =D20*'3 Statement Forecast'!F33 -> 166.27682
C97: Gap DCF vs P/E-implied ($/sh) | D97: =DCF!D118-D20*'3 Statement Forecast'!F33 -> 292.65331
C102: FCFE base (Gordon perpetuity per FCFE!B62) | D102: FCFE!B62 direct link | E102: =FCFE!D74 -> 73.610215 | F102: 1 | G102: =E102*F102 -> 73.610215 | H102: =Drivers!$C$441 -> 0 | I102: =G102*H102 -> 0
C103: Weighted target INCLUDING FCFE (P/E + FCFE, excludes DCF) | I103: =SUM(I65:I67)+I102 -> 167.66142
C104: NAV/sh (after DT, v21 vintage-based) | D104: NAV!D168 (v21 vintage-based, after deferred tax) | E104: =NAV!D168 -> 169.73895 | F104: 1 | G104: =E104*F104 -> 169.73895 | H104: =Drivers!$C$660 -> 0 | I104: =G104*H104 -> 0
C105: RI/sh (v21 corrected formula: NI − Ke × opening book) | D105: 'Residual Income'!D45 (RI value per share) | E105: ='Residual Income'!D45 -> 93.460526 | F105: 1 | G105: =E105*F105 -> 93.460526 | H105: =Drivers!$C$661 -> 0 | I105: =G105*H105 -> 0
C106: Peer-fitted price (P/B = a + b × ROE, PURE-LESSOR set ex-builders, v21) | D106: 'Peer P-B vs ROE'!D41 (fitted P/B × BVPS 2027E) | E106: ='Peer P-B vs ROE'!D80 -> 162.17705 | F106: 1 | G106: =E106*F106 -> 162.17705 | H106: =Drivers!$C$662 -> 0 | I106: =G106*H106 -> 0
A107: x | C107: v17 ITEM 3 (2026-09-26) — RRPF AT VALUE: DECISION
C108: Method selected (Drivers!B572) | D108: =Drivers!$C$572 -> A
C109: Selected value ($M) (Drivers!B577) | D109: =Drivers!$C$577 -> 1994.302
C110: RRPF book value ($M) (Drivers!B404) | D110: =Drivers!$C$404 -> 732.3
C111: RRPF above book per share ($) = (selected − book) / diluted shares | D111: =(Drivers!$C$577-Drivers!$C$404)/DCF!$D$116 -> 35.251452
C112: Decision: DO NOT add RRPF above-book uplift to P/E scenarios.
C113: Reason: P/E multiples applied to model 2027E EPS already include RRPF affiliate income (3SF row 16 'Share of affiliates, net of tax' flows into net income; $150M/yr, ~$4.20/sh). Adding the RRPF at-value uplift on top of a P/E scenario would double-count. This mirrors dcf-judgment-calls.md §7: 'Do not add the affiliate back AND include its dividends in UFCF. One or the other.' The DCF bridge already handles RRPF at value correctly (RRPF income is excluded from UFCF via B58 add-back; then B101 adds RRPF at value in the bridge).
C114: 'RRPF at value: with' vs 'without' — since P/E scenarios are unchanged, Valuation!G57 (existing weighted target) is BOTH the 'with' and 'without' cell. Rating!B6 reads =Valuation!G57.
C115: Weighted target WITHOUT RRPF P/E uplift (link G57, unchanged) | D115: =I69 -> 167.66142
C116: Weighted target WITH hypothetical RRPF uplift on P/E (= G57 + B99, memo only — NOT used in Rating!B6) | D116: =I69+D111 -> 202.91287
C117: Rating!B6 reads: Valuation!G57 (WITHOUT uplift). Confirmed unchanged (Rating unchanged; rating stays HOLD).
A120: x | C120: SECTION E — EARNINGS QUALITY (v20, 2026-09-27)
D121: 2023A | E121: 2024A | F121: 2025A | G121: 2026E | H121: 2027E
C122: Pretax income ($M) — 3SF row 26 + row 28 (incl. affiliates) | D122: =Historicals!G31+Historicals!G33 -> 317.9 | E122: =Historicals!H31+Historicals!H33 -> 344.2 | F122: ='3 Statement Forecast'!D26+'3 Statement Forecast'!D28 -> 396.4 | G122: ='3 Statement Forecast'!E26+'3 Statement Forecast'!E28 -> 472.92975 | H122: ='3 Statement Forecast'!F26+'3 Statement Forecast'!F28 -> 457.60128
C123: Net gain on asset dispositions ($M) — 3SF row 23 | D123: =Historicals!G28 -> 130.3 | E123: =Historicals!H28 -> 138.3 | F123: ='3 Statement Forecast'!D23 -> 136.9 | G123: ='3 Statement Forecast'!E23 -> 210.5 | H123: ='3 Statement Forecast'!F23 -> 210.5
...

Sheet Quarterly 2026
C2: ="Financial Statement Model - "&Cover!$D$5 -> Financial Statement Model - GATX Corporation
C3: $ mm except per share
C5: Company name | D5: =Cover!$D$5 -> GATX Corporation
C6: Ticker | D6: =Cover!$D$6 -> GATX
C7: Circ break 1=off, 0=on | D7: =Cover!$D$7 -> 1
C8: Latest closing share price | D8: =Cover!$D$8 -> 162.78
C9: Share price date | D9: =Cover!$D$9 -> 46303
C10: Latest fiscal year end | D10: =Cover!$D$10 -> 46022
C11: Shares outstanding (millions) | D11: =Cover!$D$11 -> 35.8
C13: GATX QUARTERLY 2026 — Q1A + Q2A (from Q2 release) + Q3E + Q4E (H2 split) + FY2026E link
C14: Q1A = H1 - Q2 (release provides both). FY2026E from 3 Statement Forecast. Q3+Q4 split H2 = FY - H1 using Drivers seasonality assumptions. Identity: Q1 + Q2 + Q3 + Q4 = FY for every row (constrained by construction).
C16: Line ($M except EPS) | D16: Q1A | E16: Q2A | F16: Q3E | G16: Q4E | H16: FY2026E (model) | I16: Sum Q1+Q2+Q3+Q4 | J16: Identity check (col G − col F)
C17: Revenue | D17: =Drivers!C328 -> 583.7 | E17: =Drivers!C326 -> 580.1 | F17: =(H17-D17-E17)*Drivers!C360 -> 610.82733 | G17: =(H17-D17-E17)-F17 -> 610.82733 | H17: ='3 Statement Forecast'!E17 -> 2385.4547 | I17: =D17+E17+F17+G17 -> 2385.4547 | J17: =I17-H17 -> 0
C18: Maintenance | D18: =Drivers!C331 -> -140.7 | E18: =Drivers!C329 -> -151.8 | F18: =(H18-D18-E18)*Drivers!C360 -> -153.52036 | G18: =(H18-D18-E18)-F18 -> -153.52036 | H18: ='3 Statement Forecast'!E18 -> -599.54072 | I18: =D18+E18+F18+G18 -> -599.54072 | J18: =I18-H18 -> 0
C19: Depreciation | D19: =Drivers!C334 -> -169.2 | E19: =Drivers!C332 -> -166.5 | F19: =(H19-D19-E19)*Drivers!C360 -> -167.85 | G19: =(H19-D19-E19)-F19 -> -167.85 | H19: ='3 Statement Forecast'!E19 -> -671.4 | I19: =D19+E19+F19+G19 -> -671.4 | J19: =I19-H19 -> 0
C20: SG&A | D20: =Drivers!C337 -> -71.3 | E20: =Drivers!C335 -> -69.2 | F20: =(H20-D20-E20)*Drivers!C360 -> -74.070007 | G20: =(H20-D20-E20)-F20 -> -74.070007 | H20: ='3 Statement Forecast'!E22 -> -288.64001 | I20: =D20+E20+F20+G20 -> -288.64001 | J20: =I20-H20 -> 0
C21: Dispositions | D21: =Drivers!C340 -> 51 | E21: =Drivers!C338 -> 69.7 | F21: =(H21-D21-E21)*Drivers!C361 -> 49.39 | G21: =(H21-D21-E21)-F21 -> 40.41 | H21: ='3 Statement Forecast'!E23 -> 210.5 | I21: =D21+E21+F21+G21 -> 210.5 | J21: =I21-H21 -> 0
C22: Interest | D22: =Drivers!C343 -> -151 | E22: =Drivers!C341 -> -143 | F22: =(H22-D22-E22)*Drivers!C360 -> -147.41299 | G22: =(H22-D22-E22)-F22 -> -147.41299 | H22: ='3 Statement Forecast'!E24 -> -588.82599 | I22: =D22+E22+F22+G22 -> -588.82599 | J22: =I22-H22 -> 0
C23: Other income | D23: =Drivers!C346 -> 6.2 | E23: =Drivers!C344 -> 12.7 | F23: =(H23-D23-E23)*Drivers!C362 -> -4.25 | G23: =(H23-D23-E23)-F23 -> -4.25 | H23: ='3 Statement Forecast'!E25 -> 10.4 | I23: =D23+E23+F23+G23 -> 10.4 | J23: =I23-H23 -> 0
C24: Tax | D24: =Drivers!C349 -> -21.2 | E24: =Drivers!C347 -> -26 | F24: =(H24-D24-E24)*Drivers!C360 -> -20.180262 | G24: =(H24-D24-E24)-F24 -> -20.180262 | H24: ='3 Statement Forecast'!E27 -> -87.560524 | I24: =D24+E24+F24+G24 -> -87.560524 | J24: =I24-H24 -> 0
C25: RRPF | D25: =Drivers!C352 -> 20.8 | E25: =Drivers!C350 -> 37.2 | F25: =(H25-D25-E25)*Drivers!C360 -> 41 | G25: =(H25-D25-E25)-F25 -> 41 | H25: ='3 Statement Forecast'!E28 -> 140 | I25: =D25+E25+F25+G25 -> 140 | J25: =I25-H25 -> 0
C26: NCI | D26: =Drivers!C355 -> 6.4 | E26: =Drivers!C353 -> -7.6 | F26: =(H26-D26-E26)*Drivers!C360 -> -7.90752 | G26: =(H26-D26-E26)-F26 -> -7.90752 | H26: ='3 Statement Forecast'!E30 -> -17.01504 | I26: =D26+E26+F26+G26 -> -17.01504 | J26: =I26-H26 -> 0
C27: Diluted EPS | D27: =Drivers!C358 -> 2.35 | E27: =Drivers!C356 -> 2.84 | F27: =(H27-D27-E27)*Drivers!C360 -> 2.5496115 | G27: =(H27-D27-E27)-F27 -> 2.5496115 | H27: ='3 Statement Forecast'!E33 -> 10.289223 | I27: =D27+E27+F27+G27 -> 10.289223 | J27: =I27-H27 -> 0
C28: Memo: Rail NA revenue ($M; even quarterly split of annual Segment P&L!E21) | D28: ='Segment P&L'!$E$21/4 -> 444.51641 | E28: ='Segment P&L'!$E$21/4 -> 444.51641 | F28: ='Segment P&L'!$E$21/4 -> 444.51641 | G28: ='Segment P&L'!$E$21/4 -> 444.51641 | H28: ='Segment P&L'!$E$21 -> 1778.0657 | J28: v36 memo: no quarterly Rail NA breakout in release; using 25% of FY2026E as proxy for Q3 preview.
C29: OUTPUT — Q3E EPS vs consensus
C30: Model Q3E diluted EPS (link) | D30: =F27 -> 2.5496115
C31: Consensus Q3 2026 EPS — low ($2.458, FactSet) | D31: =Drivers!C364 -> 2.458
C32: Consensus Q3 2026 EPS — high ($2.458, FactSet) | D32: =Drivers!C365 -> 2.458
C33: Consensus Q3 2026 EPS — midpoint ($2.458) | D33: =Drivers!C366 -> 2.458
C34: Delta: Model Q3 − consensus mid ($) | D34: =D30-D33 -> 0.09161151
C35: Delta: Model Q3 − consensus mid (%) | D35: =D34/D33 -> 0.037270752
C37: Named drivers of delta (model vs consensus $2.48):
C38: (1) Dispositions Q3E — model runs above consensus because Drivers!Q3_pct_of_H2_dispo=0.55 reflects Q2 call 'legacy tracking ahead of plan' + strong secondary market; Street typically assumes flatter split. See Q3E dispo row 9 vs $50M implied share of $200M FY.
C39: (2) Interest expense Q3E — model refi at 5.30% (Drivers!B102) already flowing through; if Street uses lower refi assumption, Q3 interest gap narrows. See row 10.
C40: (3) Other income Q3E — Q2 call flagged 'lumpy' maintenance-reserve releases; consensus may not model persistence. See row 11 with Q3_pct_of_H2_otherincome = 0.50.
C41: (4) Fee income (JV + Brookfield-book) is baked into RailNA other rev at $160M FY26 (Drivers!B320) — even split into Q3 (steady). Cadence relative to Street unknown.
C43: GATE — Q1+Q2+Q3+Q4 EPS sum vs FY2026E ($10.53 pre-registered)
A44: x | C44: Sum Q1+Q2+Q3+Q4 EPS | D44: =I27 -> 10.289223
C45: FY2026E EPS from model | D45: =H27 -> 10.289223
C46: Delta — reconcile check | D46: =D44-D45 -> 0
C47: Gate status (PASS if ABS(delta) <= tolerance in Drivers) | D47: =IF(ABS(D46)<=Drivers!C380,"PASS","FAIL") -> PASS

Sheet Consensus Bridge
C2: ="Financial Statement Model - "&Cover!$D$5 -> Financial Statement Model - GATX Corporation
C3: $ mm except per share
C5: Company name | D5: =Cover!$D$5 -> GATX Corporation
C6: Ticker | D6: =Cover!$D$6 -> GATX
C7: Circ break 1=off, 0=on | D7: =Cover!$D$7 -> 1
C8: Latest closing share price | D8: =Cover!$D$8 -> 162.78
C9: Share price date | D9: =Cover!$D$9 -> 46303
C10: Latest fiscal year end | D10: =Cover!$D$10 -> 46022
C11: Shares outstanding (millions) | D11: =Cover!$D$11 -> 35.8
C13: GATX CONSENSUS BRIDGE — Model 2027E EPS $10.37 → FactSet consensus $11.27 ($0.90 gap)
C14: Row = (Our_assumption − Street_implied_assumption) × sensitivity_from_model_cells × (1 − tax_rate) / diluted_shares. Street-implied values are new Drivers rows cited to 02-consensus-anatomy.md.
C16: Reference cells
C17: Model 2027E EPS | D17: ='3 Statement Forecast'!F33 -> 10.17606
C18: Consensus 2027E EPS (FactSet) | D18: =Drivers!C194 -> 11.2706
C19: Target gap ($/sh) | D19: =D18-D17 -> 1.09454
C20: Diluted shares 2027 (M) | D20: =Drivers!C78 -> 35.22652
C21: Effective tax rate 2027 | D21: =Drivers!C76 -> 0.24
C22: (1 − tax) | D22: =1-D21 -> 0.76
C24: Bridge (per share, 2027)
C25: Driver | D25: Our 2027 assumption | E25: Street-implied 2027 | F25: Delta (Street − Our) | G25: $M pretax impact | H25: After-tax $M | I25: $/sh contribution (Street − Our)
C26: 1. Legacy dispositions | D26: ='Disposition Engine'!E44 -> 140.5 | E26: =Drivers!C368 -> 150 | F26: =E26-D26 -> 9.5 | G26: =F26 -> 9.5 | H26: =G26*$D$22 -> 7.22 | I26: =H26/$D$20 -> 0.20495922
C27: 2. GABX dispositions | D27: ='GABX Mini P&L'!H22 -> 70 | E27: =Drivers!C369 -> 75 | F27: =E27-D27 -> 5 | G27: =F27*Drivers!C252 -> 2.02675 | H27: =G27*$D$22 -> 1.54033 | I27: =H27/$D$20 -> 0.043726431
C28: 3. LPI 2027 | D28: =Drivers!C33 -> 0.15 | E28: =Drivers!C370 -> 0.18 | F28: =E28-D28 -> 0.03 | G28: =F28*100*('Thesis Test'!E36-'Thesis Test'!E35)/Drivers!C322*$D$20 -> 3.1675049 | H28: =G28*$D$22 -> 2.4073038 | I28: =H28/$D$20 -> 0.068337825
C29: 4. Wells Fargo second-year accretion (Street incremental) | D29: 0 | E29: =Drivers!C371 -> 0.3 | F29: =E29-D29 -> 0.3 | G29: =H29/$D$22 -> 13.905205 | H29: =F29*$D$20 -> 10.567956 | I29: =H29/$D$20 -> 0.3
C30: 5. Interest expense | D30: ='Debt & Interest'!F31 -> -615.70826 | E30: =Drivers!C372 -> -590 | F30: =E30-D30 -> 25.70826 | G30: =F30 -> 25.70826 | H30: =G30*$D$22 -> 19.538278 | I30: =H30/$D$20 -> 0.55464683
C31: 6. RRPF | D31: =Drivers!C114 -> 150 | E31: =Drivers!C373 -> 160 | F31: =E31-D31 -> 10 | G31: =F31 -> 10 | H31: =G31 -> 10 | I31: =H31/$D$20 -> 0.28387703
C32: 7. Share count | D32: =Drivers!C78 -> 35.22652 | E32: =Drivers!C374 -> 35.5 | F32: =E32-D32 -> 0.27347997 | G32: =-'3 Statement Forecast'!F31*F32/E32 -> -2.7615097 | H32: =G32 -> -2.7615097 | I32: =-'3 Statement Forecast'!F31*F32/(D32*E32) -> -0.078392918
C33: 8. Tax rate | D33: =Drivers!C76 -> 0.24 | E33: =Drivers!C375 -> 0.24 | F33: =E33-D33 -> 0 | G33: =-'3 Statement Forecast'!F26*F33 -> 0 | H33: =G33 -> 0 | I33: =H33/$D$20 -> 0
C34: 9. Other income | D34: =Drivers!C143 -> 10 | E34: =Drivers!C376 -> 12 | F34: =E34-D34 -> 2 | G34: =F34 -> 2 | H34: =G34*$D$22 -> 1.52 | I34: =H34/$D$20 -> 0.043149309
C36: Sum of explained rows (1-9) | I36: =SUM(I26:I34) -> 1.4203037
C37: 10. Residual — unexplained | I37: =D19-I36 -> -0.32576369
C38: Total explained + residual | I38: =I36+I37 -> 1.09454
C40: GATE — Sum (1-9) vs $0.90 target
C41: Target gap ($/sh) | D41: =D19 -> 1.09454
C42: Sum of bridge rows 1-9 ($/sh) | D42: =I36 -> 1.4203037
C43: Residual ($/sh) — reconcile check | D43: =I37 -> -0.32576369
C44: Gate status (PASS if ABS(residual) <= tolerance in Drivers) | D44: =IF(ABS(D43)<=Drivers!C381,"PASS","FAIL") -> FAIL
A50: x | C50: SECTION B — 2026 guidance vs model
C51: Per lessor-benchmark item 4. One row per FY2026 guided item; sources: Q4 2025 earnings release 2026-02-19 and Q2 2026 earnings call transcript 2026-07-30.
C53: Guided item | D53: Guide value | E53: BMG 2026E consolidated | F53: Scope | G53: Model, same scope | H53: Variance (same scope) | I53: Variance % (same scope) | J53: One-line reason | K53: Source
C55: Adjusted EPS 2026 midpoint ($/sh) | D55: 10.1 | E55: ='3 Statement Forecast'!E33 -> 10.289223 | F55: consolidated | G55: =E55 -> 10.289223 | H55: =G55-D55 -> 0.18922302 | I55: =IFERROR(H55/D55,0) -> 0.018734952 | J55: Model above midpoint driven by remarketing gains running ahead in H1. | K55: Q4 2025 release 2026-02-19: $9.50 to $10.10; raised Q2 2026 call to $9.90 to $10.30, midpoint $10.10.
C56: Rail NA lease revenue 2026E ($M) | D56: 1000 | E56: ='Segment P&L'!E19 -> 1618.0657 | F56: legacy-only | G56: ='Segment P&L'!E19-'Segment P&L'!E18 -> 1075.0657 | H56: =G56-D56 -> 75.065654 | I56: =IFERROR(H56/D56,0) -> 0.075065654 | J56: legacy-only guide vs legacy-only model (Rail NA lease revenue ex acquired Wells Fargo pool). | K56: Q2 2026 call: Rail NA lease revenue about $1.0B for 2026.
C57: Remarketing income consolidated 2026E ($M) | D57: 200 | E57: ='3 Statement Forecast'!E23 -> 210.5 | F57: consolidated | G57: =E57 -> 210.5 | H57: =G57-D57 -> 10.5 | I57: =IFERROR(H57/D57,0) -> 0.0525 | J57: Model consolidated dispo gains include legacy plus GABX per Q2 call split. | K57: Q2 2026 call (Bob Lyons): about $200M consolidated remarketing, $130M legacy plus $70M JV.
C58: Interest expense 2026E ($M) | D58: 440 | E58: =-'3 Statement Forecast'!E24 -> 588.82599 | F58: legacy-only | G58: =-'3 Statement Forecast'!E24+'GABX Mini P&L'!G23 -> 435.12599 | H58: =G58-D58 -> -4.87401 | I58: =IFERROR(H58/D58,0) -> -0.011077295 | J58: legacy-only guide vs legacy-only model (consolidated interest minus GABX interest). | K58: Q2 2026 call: interest about $440M for 2026.
C59: Depreciation 2026E ($M) | D59: 520 | E59: =-'3 Statement Forecast'!E19 -> 671.4 | F59: legacy-only | G59: not comparable — GABX depreciation not separately reported on GABX Mini P&L (rolled into row 21 total expenses) | J59: not comparable — no GABX depreciation split | K59: Q2 2026 call: depreciation about $520M for 2026.
C60: Maintenance 2026E ($M) | D60: 500 | E60: =-'3 Statement Forecast'!E18 -> 599.54072 | F60: legacy-only (approximation) | G60: =-'3 Statement Forecast'!E18-2*(-Drivers!C330-Drivers!C774) -> 514.54072 | H60: =G60-D60 -> 14.540717 | I60: =IFERROR(H60/D60,0) -> 0.029081434 | J60: legacy-only approximation: H1 legacy $250M per Ellman × 2; non-legacy portion = 2×(H1 consolidated $292.5M − H1 legacy $250M). | K60: Q2 2026 call: maintenance in the $500M range for 2026.
C61: SG&A 2026E ($M) | D61: 275 | E61: =-'3 Statement Forecast'!E22 -> 288.64001 | F61: consolidated | G61: =E61 -> 288.64001 | H61: =G61-D61 -> 13.640013 | I61: =IFERROR(H61/D61,0) -> 0.049600048 | J61: Model SG&A rate on revenue matches full-year guide. | K61: Q2 2026 call: SG&A about $275M for 2026.
C62: LPI FY2026 band midpoint | D62: 0.2 | E62: =Drivers!C32 -> 0.185 | F62: legacy-only | G62: not comparable — LPI reported on legacy Rail NA renewals only; Wells Fargo pool cohort not in the LPI metric per Q2 call | J62: not comparable — LPI is legacy-fleet metric | K62: Q2 2026 call (Paul Titterton): high teens to low 20s LPI for remainder of 2026 (Q2 was 16.8%, sand-heavy).
C63: Utilization FY2026 (98 to 99%) | D63: 0.985 | E63: =Drivers!C7 -> 0.99 | F63: consolidated | G63: =E63 -> 0.99 | H63: =G63-D63 -> 0.005 | I63: =IFERROR(H63/D63,0) -> 0.0050761421 | J63: Model utilization at reported YE2025 level (99%) held flat forward. | K63: Q2 2026 call: fleet utilization 98% at quarter end; guide implies 98 to 99% range for year.
C65: Gate summary: comparable items where |Variance %| > tolerance (Drivers!C773) | I65: =SUMPRODUCT((ABS(IFERROR(I55:I63,0))>Drivers!$C$773)*ISNUMBER(I55:I63)) -> 2
C66: Rows excluded as not comparable (no same-scope model value) | I66: =SUMPRODUCT(--(NOT(ISNUMBER(G55:G63)))) -> 2
C67: Sources: research/coverage/rail/gatx-filings/GATX-Q4-2025-earnings-release.md; GATX-Q2-2026-earnings-release-2026-07-30.md; GATX-Q2-2026-earnings-call-transcript-2026-07-30.pdf. Guide values in blue; BMG values green-linked to live model cells.

Sheet Rating
C2: ="Financial Statement Model - "&Cover!$D$5 -> Financial Statement Model - GATX Corporation
C3: $ mm except per share
C5: Company name | D5: =Cover!$D$5 -> GATX Corporation
C6: Ticker | D6: =Cover!$D$6 -> GATX
C7: Circ break 1=off, 0=on | D7: =Cover!$D$7 -> 1
C8: Latest closing share price | D8: =Cover!$D$8 -> 162.78
C9: Share price date | D9: =Cover!$D$9 -> 46303
C10: Latest fiscal year end | D10: =Cover!$D$10 -> 46022
C11: Shares outstanding (millions) | D11: =Cover!$D$11 -> 35.8
C13: GATX RATING — expected 12M total return + flip points + kill status
C14: Default rating rule (METHOD.md has no rating threshold as of 2026-09-24): BUY if expected 12M total return > +15%; SELL if < -5%; HOLD otherwise. Pre-registered.
C15: Formula: expected_return = (probability_weighted_target + NTM_dividend − current_price) / current_price. Target from Valuation!G57; current price from Drivers!B179; NTM dividend from Drivers!B181 × current price.
C17: Inputs
C18: Weighted target ($/sh) [Valuation Section H: Valuation!D229] | D18: =Valuation!D229 -> 162.56567 | E18: Published target $165.54 (v32) held until the Q3 2026 review; model target v37 = $166.02 (v36 was $165.94; the $0.08 drift is the price-cascade through buyback share count — no leg logic changed).
C19: Current price ($/sh) [Drivers!B179] | D19: =Drivers!C179 -> 162.78
C20: NTM dividend yield [Drivers!B181] | D20: =Drivers!C181 -> 0.01517
C21: NTM dividend ($/sh) = declared quarterly $0.66 x 4 = $2.64 [v39 2026-10-09; model 2027E full-year DPS = $2.74 from Drivers!C80, used as a footnote only] | D21: =0.66*4 -> 2.64 | E21: Model 2027E DPS = Drivers!C80 = $2.74. Return calc uses $2.64 per the declared quarterly rate per v39 2026-10-09.
C23: Expected 12-month total return
C24: Expected return = (target + dividend − current) / current | D24: =(D18+D21-D19)/D19 -> 0.0149015
C26: Rating
C27: BUY threshold [Drivers!B378] | D27: =Drivers!C378 -> 0.15
C28: SELL threshold [Drivers!B379] | D28: =Drivers!C379 -> -0.05
C29: Rating | D29: =IF(D24>D27,"BUY",IF(D24<D28,"SELL","HOLD")) -> HOLD
C31: Flip points
C32: LPI flip point (BUY→HOLD): what LPI at Street's implied 2027 EPS gives expected_return = +15%? Reads: at what target price does expected_return = 15%? Then back-solve LPI.
C33: Target price to hit BUY threshold (+15% total return) | D33: =D19*(1+D27)-D21 -> 184.557
C34: Base scenario price (Valuation!E54) | D34: =Valuation!G66 -> 166.27682
C35: Base 2027 EPS (Valuation!C54) | D35: =Valuation!E66 -> 10.17606
C36: NTM P/E median multiple (Valuation!B8) | D36: =Valuation!D20 -> 16.34
C37: EPS needed at target price = target_price / NTM P/E median | D37: =D33/D36 -> 11.294798
C38: EPS sensitivity per +1pp LPI 2027 ($/sh) | D38: =('Thesis Test'!E36-'Thesis Test'!E35)/Drivers!C322 -> 0.02997273
C39: Additional EPS needed (base scenario) = EPS_needed − base_EPS | D39: =D37-D35 -> 1.1187381
C40: LPI flip = current LPI + (Additional EPS) / EPS-per-pp × base_prob_weight adjustment
C41: LPI flip point (2027): base LPI + Additional EPS / sensitivity (approximate; base scenario) | D41: =Drivers!C33+D39/D38/100 -> 0.52325198
C43: Disposition flip point (HOLD→SELL): at what legacy disposition level does expected return = -5%? Same algebraic approach: back-solve target price then EPS.
C44: Target price to hit SELL threshold (-5% total return) | D44: =D19*(1+D28)-D21 -> 152.001
C45: EPS at SELL-threshold target price = target_price / NTM P/E median | D45: =D44/D36 -> 9.3023868
C46: Additional EPS delta needed (SELL) = EPS_at_SELL − base_EPS | D46: =D45-D35 -> -0.87367318
C47: Legacy disposition sensitivity: $M dispositions → $/sh after-tax = (1-tax)/shares | D47: =(1-Drivers!C76)/Drivers!C78 -> 0.021574655
C48: Δ legacy disposition needed ($M) = Additional EPS ÷ ($/sh per $M) | D48: =D46/D47 -> -40.49535
C49: Legacy disposition flip point ($M) = current legacy dispo + Δ needed | D49: ='Disposition Engine'!E44+D48 -> 100.00465
C51: Kill-criteria status board (pulled from Thesis Test + Drivers via cell links)
C52: Kill criterion | D52: Threshold | E52: Current | F52: Status
C53: New-issue rate reaches 6.00% (Drivers!B105) | D53: =Drivers!C105 -> 0.06 | E53: =Drivers!C102 -> 0.053 | F53: =IF(E53>=D53,"KILL","OK") -> OK
C54: 2027E EPS at 6.00% new-issue rate (Thesis Test B34) | D54: =Drivers!C53 -> 9.9 | E54: ='Thesis Test'!D46 -> 9.9875687 | F54: =IF(E54<D54,"KILL","OK") -> OK
C55: Break-even LPI 2027 (Thesis Test B33) — kill if model LPI (Drivers!B33) below BE | D55: ='Thesis Test'!D45 -> -0.23330779 | E55: =Drivers!C33 -> 0.15 | F55: =IF(E55<D55,"KILL — model LPI below BE","OK") -> OK
C57: --- v13 addition (2026-09-24) ---
C58: Prob-weighted target INCLUDING DCF (Valuation!G60) | D58: =Valuation!I72 -> 167.66142
C59: Prob-weighted target EXCLUDING DCF (Valuation!G61, same as B6) | D59: =Valuation!I73 -> 167.66142
C60: Price at which SELL returns to HOLD = (target + dividend) / (1 + SELL threshold) | D60: =(D18+D21)/(1+D28) -> 173.9007 | E60: Source: pre-registered rating rule at Rating!D28-D29 and calibration/METHOD.md. SELL rating fires when expected return < Drivers!C379 (-5%). At the price computed here, expected return equals -5% and rating returns from SELL to HOLD.
C61: Expected return INCLUDING DCF weight (Prob_weight_DCF from Drivers) | D61: =(Valuation!I72+D21-D19)/D19 -> 0.046206034

Sheet DCF
C2: ="Discounted Cash Flow Valuation - "&Cover!$D$5 -> Discounted Cash Flow Valuation - GATX Corporation
C3: $ mm except per share
C5: Company name | D5: =Cover!$D$5 -> GATX Corporation
C6: Ticker | D6: =Cover!$D$6 -> GATX
C7: Circ break 1=off, 0=on | D7: =Cover!$D$7 -> 1
C8: Latest closing share price | D8: =Cover!$D$8 -> 162.78
C9: Share price date | D9: =Cover!$D$9 -> 46303
C10: Latest fiscal year end | D10: =Cover!$D$10 -> 46022
C11: Shares outstanding (millions) | D11: =Cover!$D$11 -> 35.8
C13: GATX DCF — Unlevered Two-Stage (v13, 2026-09-24)
C14: Formulas only. Every input is a Drivers cell with source, or a link to another sheet. Methodology: research/methodology/dcf-{mechanics,wacc-and-inputs,judgment-calls}.md.
C16: Year | D16: 2026E | E16: 2027E | F16: 2028E | G16: 2029E | H16: 2030E | I16: 2031E | J16: 2032E | K16: 2033E | L16: 2034E | M16: 2035E | N16: 2036E (term)
A18: x | C18: SECTION 1 — Unlevered Free Cash Flow ($M)
C19: Disposition treatment: gains stay inside EBIT (row 11 of 3SF); we add ONLY the return-of-capital piece (proceeds − gain = Drivers!Dispo_book_202x). RRPF equity dividends shown as SEPARATE memo (valued in bridge). Wells Fargo 2026 acquisition ($4.2B) EXCLUDED from run-rate FCF (memo only).
C21: EBIT ($M) = Pretax (pre-affiliates) + Interest add-back (financing) | D21: ='3 Statement Forecast'!E26-'3 Statement Forecast'!E24 -> 921.75574 | E21: ='3 Statement Forecast'!F26-'3 Statement Forecast'!F24 -> 923.30954 | F21: ='3 Statement Forecast'!G26-'3 Statement Forecast'!G24 -> 971.63426 | G21: ='3 Statement Forecast'!H26-'3 Statement Forecast'!H24 -> 1012.2827 | H21: ='3 Statement Forecast'!I26-'3 Statement Forecast'!I24 -> 1042.0264 | I21: ='3 Statement Forecast'!J26-'3 Statement Forecast'!J24 -> 1074.1204 | J21: ='3 Statement Forecast'!K26-'3 Statement Forecast'!K24 -> 1091.6501 | K21: ='3 Statement Forecast'!L26-'3 Statement Forecast'!L24 -> 1111.8083 | ... M21: ='3 Statement Forecast'!N26-'3 Statement Forecast'!N24 -> 1154.565 | N21: =M21*(1+Drivers!$C$397) -> 1194.9748
C22: Effective tax rate (link) | D22: =Drivers!$C$75 -> 0.263 | E22: =Drivers!$C$76 -> 0.24 | F22: =Drivers!$C$273 -> 0.24 | G22: =Drivers!$C$274 -> 0.24 | H22: =Drivers!$C$275 -> 0.24 | I22: =Drivers!$C$498 -> 0.24 | J22: =Drivers!$C$499 -> 0.24 | K22: =Drivers!$C$500 -> 0.24 | L22: =Drivers!$C$501 -> 0.24 | M22: =Drivers!$C$502 -> 0.24 | N22: =M22 -> 0.24
C23: Less: Taxes on EBIT = EBIT × tax rate | D23: =-D21*D22 -> -242.42176 | E23: =-E21*E22 -> -221.59429 | F23: =-F21*F22 -> -233.19222 | G23: =-G21*G22 -> -242.94784 | H23: =-H21*H22 -> -250.08634 | I23: =-I21*I22 -> -257.78889 | J23: =-J21*J22 -> -261.99603 | K23: =-K21*K22 -> -266.834 | ... N23: =-N21*N22 -> -286.79396
A24: x | C24: NOPAT (EBIAT) | D24: =D21+D23 -> 679.33398 | E24: =E21+E23 -> 701.71525 | F24: =F21+F23 -> 738.44203 | G24: =G21+G23 -> 769.33484 | H24: =H21+H23 -> 791.94007 | I24: =I21+I23 -> 816.33149 | J24: =J21+J23 -> 829.6541 | K24: =K21+K23 -> 844.97434 | ... N24: =N21+N23 -> 908.18086
C25: Plus: D&A (link 3SF row 7, sign-flipped) | D25: =-'3 Statement Forecast'!E19 -> 671.4 | E25: =-'3 Statement Forecast'!F19 -> 720 | F25: =-'3 Statement Forecast'!G19 -> 720 | G25: =-'3 Statement Forecast'!H19 -> 720 | H25: =-'3 Statement Forecast'!I19 -> 720 | I25: =-'3 Statement Forecast'!J19 -> 720 | J25: =-'3 Statement Forecast'!K19 -> 732.8353 | K25: =-'3 Statement Forecast'!L19 -> 743.92318 | ... M25: =-'3 Statement Forecast'!N19 -> 766.43269 | N25: =M25*(1+Drivers!$C$397) -> 793.25783
C26: Less: Organic capex (link 3SF row 63; WFR excluded) | D26: ='3 Statement Forecast'!E75 -> -1041 | E26: ='3 Statement Forecast'!F75 -> -1400 | F26: ='3 Statement Forecast'!G75 -> -1400 | G26: ='3 Statement Forecast'!H75 -> -1400 | H26: ='3 Statement Forecast'!I75 -> -1400 | I26: ='3 Statement Forecast'!J75 -> -1190 | J26: ='3 Statement Forecast'!K75 -> -1159.27 | K26: ='3 Statement Forecast'!L75 -> -1173.1223 | ... M26: ='3 Statement Forecast'!N75 -> -1201.2437 | N26: =-N25 -> -793.25783
C27: Less: Δ Working capital (link 3SF row 57) | D27: ='3 Statement Forecast'!E69 -> 101.29478 | E27: ='3 Statement Forecast'!F69 -> 13.508658 | F27: ='3 Statement Forecast'!G69 -> 12.913214 | G27: ='3 Statement Forecast'!H69 -> 10.861809 | H27: ='3 Statement Forecast'!I69 -> 7.9479246 | I27: ='3 Statement Forecast'!J69 -> 6.6072552 | J27: ='3 Statement Forecast'!K69 -> 7.4363714 | K27: ='3 Statement Forecast'!L69 -> 7.6480829 | ... M27: ='3 Statement Forecast'!N69 -> 8.0949874 | N27: =M27*(1+Drivers!$C$397) -> 8.378312
C28: Plus: Return of capital on dispositions (proceeds − gain) | D28: =Drivers!$C$86 -> 150 | E28: =Drivers!$C$87 -> 150 | F28: =Drivers!$C$288 -> 150 | G28: =Drivers!$C$289 -> 150 | H28: =Drivers!$C$290 -> 150 | I28: =Drivers!$C$553 -> 150 | J28: =Drivers!$C$554 -> 150 | K28: =Drivers!$C$555 -> 150 | L28: =Drivers!$C$556 -> 150 | M28: =Drivers!$C$557 -> 150 | N28: =M28*(1+Drivers!$C$397) -> 155.25
A29: x | C29: UFCF = NOPAT + D&A + Capex + ΔWC + RoC | D29: =D24+D25+D26+D27+D28 -> 561.02876 | E29: =E24+E25+E26+E27+E28 -> 185.22391 | F29: =F24+F25+F26+F27+F28 -> 221.35525 | G29: =G24+G25+G26+G27+G28 -> 250.19665 | H29: =H24+H25+H26+H27+H28 -> 269.888 | I29: =I24+I25+I26+I27+I28 -> 502.93875 | J29: =J24+J25+J26+J27+J28 -> 560.65573 | K29: =K24+K25+K26+K27+K28 -> 573.42333 | ... N29: =N24+N25+N26+N27+N28 -> 1071.8092
C31: MEMO — WFR acquisition ($4.2B, 2026 only; EXCLUDED) | D31: ='3 Statement Forecast'!E76 -> -4200
C32: MEMO — RRPF dividend inflow (valued in bridge, not UFCF) | D32: =Drivers!$C$115 -> 140 | E32: =Drivers!$C$116 -> 130 | F32: =Drivers!$C$297 -> 130 | G32: =Drivers!$C$298 -> 130 | H32: =Drivers!$C$299 -> 130
C34: GATE 1 — UFCF 2026 tie to CFO-based reconciliation
C35: UFCF 2026 (Section 1) | D35: =D29 -> 561.02876
C36: CFO 2026 | D36: ='3 Statement Forecast'!E73 -> 986.92101
C37: + Organic capex | D37: ='3 Statement Forecast'!E75 -> -1041
C38: + Portfolio proceeds | D38: ='3 Statement Forecast'!E77 -> 360.5
C39: = Raw CFO + Capex + Proceeds | D39: =D36+D37+D38 -> 306.42101
C40: Adjustments to convert to unlevered UFCF:
C41: (a) −(1−t) × (Interest + Other income) | D41: =-(1-Drivers!C75)*('3 Statement Forecast'!E24+'3 Statement Forecast'!E25) -> 426.29995
C42: (b) − RRPF earnings (not in UFCF) | D42: =-'3 Statement Forecast'!E28 -> -140
C43: (c) − SBC add-back (embedded in EBIT) | D43: =-'3 Statement Forecast'!E71 -> -28
C44: (d) − Deferred tax change | D44: =-'3 Statement Forecast'!E68 -> -11.957
C45: (e) − ROU/OL amortization | D45: =-'3 Statement Forecast'!E72 -> 0.6
C46: Total adjustments | D46: =SUM(D41:D45) -> 246.94295
C47: Reconciled UFCF | D47: =D39+D46 -> 553.36396
C48: Reconciled delta (UFCF − Reconciled) | D48: =D35-D47 -> 7.6648
C49: Gate status | D49: =IF(ABS(D48)<10,"PASS (±$10M)","FAIL") -> PASS (±$10M)
A51: x | C51: SECTION 2 — WACC Build
C52: Risk-free rate (10y Treasury, 2026-09-23) | D52: =Drivers!$C$384 -> 0.0511
C53: Equity risk premium (Damodaran implied) | D53: =Drivers!$C$385 -> 0.046
C54: Beta — adjusted (Blume, FactSet 3Y) | D54: =Drivers!$C$387 -> 0.85
C55: Beta — raw (derived from Blume) = (adj − w_mkt)/w_raw | D55: =(D54-Drivers!$C$420)/Drivers!$C$419 -> 0.7761194
C56: Beta used in CAPM (Blume-adjusted — default) | D56: =D54 -> 0.85
C57: Ke = Rf + Beta × ERP | D57: =D52+D56*D53 -> 0.0902
C58: Cost of debt pre-tax (2035 bond YTW) | D58: =Drivers!$C$389 -> 0.0595
C59: Tax rate for WACC | D59: =Drivers!$C$390 -> 0.24
C60: Kd after-tax = Kd × (1−t) | D60: =D58*(1-D59) -> 0.04522
C61: Market cap ($M) | D61: =Drivers!$C$391 -> 5827.524
C62: Debt (book, $M) | D62: =Drivers!$C$392 -> 12333.3
C63: W_e = MktCap / (MktCap + Debt) | D63: =D61/(D61+D62) -> 0.32088434
C64: W_d = 1 − W_e | D64: =1-D63 -> 0.67911566
C65: WACC = W_e × Ke + W_d × Kd_at | D65: =D63*D57+D64*D60 -> 0.059653378
A67: x | C67: SECTION 3 — Terminal Value
C68: Terminal-year normalization: capex_terminal = D&A_terminal × (1+g); dispositions grow at g. Note: mean-reversion toggle in Disposition Engine is NOT flipped (task requires no changes there); terminal dispositions extrapolate from Drivers B290 by g. This is an approximation — a true mean-reversion terminal would require flipping the Disposition Engine toggle in a copy.
C70: Method A — Gordon Perpetuity
C71: Terminal g | D71: =Drivers!$C$397 -> 0.035
C72: FCF_2036 (year-11 UFCF, terminal) | D72: =N29 -> 1071.8092
A73: x | C73: TV_Gordon = FCF31 / (WACC − g) | D73: =D72/(D65-D71) -> 43475.145
C75: Method B — Exit multiple on Terminal EBITDA
A76: x | C76: Terminal EBITDA = EBIT_2035 + D&A_2035 | D76: =M21+M25 -> 1920.9977
C77: Exit multiple (GATX 25y median) | D77: =Drivers!$C$398 -> 10.11
C78: TV_Exit = EBITDA × mult | D78: =D76*D77 -> 19421.287
C80: Cross-checks
C81: Implied g from TV_Exit | D81: =D65-D72/D78 -> 0.0044660374
C82: Implied mult from TV_Gordon | D82: =D73/D76 -> 22.631544
A84: x | C84: SECTION 4 — Bridge to Equity Value
C85: Discounted stage-1 UFCF (end-of-year discounting, val date = YE 2025)
C86: Discount period (yr) | D86: =COLUMN()-3 -> 1 | E86: =COLUMN()-3 -> 2 | F86: =COLUMN()-3 -> 3 | G86: =COLUMN()-3 -> 4 | H86: =COLUMN()-3 -> 5 | I86: =COLUMN()-3 -> 6 | J86: =COLUMN()-3 -> 7 | K86: =COLUMN()-3 -> 8 | ... M86: =COLUMN()-3 -> 10
C87: Discount factor | D87: =1/(1+D65)^D86 -> 0.94370482 | E87: =1/(1+D65)^E86 -> 0.89057879 | F87: =1/(1+D65)^F86 -> 0.84044349 | G87: =1/(1+D65)^G86 -> 0.79313058 | H87: =1/(1+D65)^H86 -> 0.74848115 | I87: =1/(1+$D$65)^I86 -> 0.70634527 | J87: =1/(1+$D$65)^J86 -> 0.66658143 | K87: =1/(1+$D$65)^K86 -> 0.62905611 | L87: =1/(1+$D$65)^L86 -> 0.59364328 | M87: =1/(1+$D$65)^M86 -> 0.56022403
A88: x | C88: PV of UFCF | D88: =D29*D87 -> 529.44554 | E88: =E29*E87 -> 164.95648 | F88: =F29*F87 -> 186.03658 | G88: =G29*G87 -> 198.43861 | H88: =H29*H87 -> 202.00608 | I88: =I29*I87 -> 355.2484 | J88: =J29*J87 -> 373.7227 | K88: =K29*K87 -> 360.71545 | ... M88: =M29*M87 -> 336.5565
C89: Sum PV Stage 1 | D89: =SUM(D88:M88) -> 3055.4657
C91: PV of Terminal Value
C92: PV(TV_Gordon) | D92: =D73/(1+D65)^M86 -> 24355.821
A93: x | C93: PV(TV_Exit) | D93: =D78/(1+D65)^M86 -> 10880.272
C95: Enterprise Value ($M)
A96: x | C96: EV — Gordon (PRIMARY) | D96: =D89+D92 -> 27411.287
C97: EV — Exit (cross-check) | D97: =D89+D93 -> 13935.737
C99: TV as % of EV (flag if >75%)
C100: TV%/EV — Gordon | D100: =D92/D96 -> 0.88853257 | E100: =IF(D100>Drivers!$C$423,"FLAG: TV >75% of EV","OK") -> FLAG: TV >75% of EV
A101: x | C101: TV%/EV — Exit | D101: =D93/D97 -> 0.78074603 | E101: =IF(D101>Drivers!$C$423,"FLAG: TV >75% of EV","OK") -> FLAG: TV >75% of EV
C103: Bridge — Gordon EV → Equity
C104: EV (Gordon) | D104: =D96 -> 27411.287
C105: Less: Recourse debt | D105: =-Drivers!$C$396 -> -12289.3
C106: Less: Bank borrowings | D106: =-Drivers!$C$395 -> -44
C107: Less: Operating lease liab | D107: =-Drivers!$C$394 -> -143.8
C108: Less: NCI at sourced 1.547x book (10-Q Note 15) | D108: =-Drivers!$C$401*Drivers!$C$402 -> -1245.8902
C109: MEMO ONLY — prior 1.55x derivation (not comparable to Note 15 basis; see Drivers N403) | D109: =-Drivers!$C$401*Drivers!$C$403 -> -1248.525
C110: Plus: Cash | D110: =Drivers!$C$393 -> 747.1
C111: Plus: RRPF Method (a) — Div_2026 / (Ke − g) [Gordon] | D111: =Drivers!$C$575 -> 1994.302
C112: Plus: RRPF Method (b) — Earnings × NTM P/E median | D112: =Drivers!$C$576 -> 2451
C113: Plus: RRPF selector-driven value (PRIMARY bridge line — method per Drivers!B572) | D113: =Drivers!$C$577 -> 1994.302
C114: Equity value ($M) — PRIMARY (selector-driven RRPF; NCI at sourced 1.547×) | D114: =D104+D105+D106+D107+D108+D110+D113 -> 16429.699
C115: Equity value ($M) — SENSITIVITY (NCI 1.55×, RRPF Method (b)) | D115: =D104+D105+D106+D107+D109+D110+D112 -> 16883.762
C116: Diluted shares (M) | D116: =Drivers!C77 -> 35.8
C117: Note: Treasury stock method NOT applied — no options tranche data in Drivers; assumed immaterial (~35.8M diluted vs 35.3M basic per Q2 2026 → ~1.4% dilution already reflected).
C118: DCF equity value per share — PRIMARY (Gordon TV) | D118: =D114/D116 -> 458.93013
...

Sheet FCFE
C2: ="Discounted Cash Flow Valuation - "&Cover!$D$5 -> Discounted Cash Flow Valuation - GATX Corporation
C3: $ mm except per share
C5: Company name | D5: =Cover!$D$5 -> GATX Corporation
C6: Ticker | D6: =Cover!$D$6 -> GATX
C7: Circ break 1=off, 0=on | D7: =Cover!$D$7 -> 1
C8: Latest closing share price | D8: =Cover!$D$8 -> 162.78
C9: Share price date | D9: =Cover!$D$9 -> 46303
C10: Latest fiscal year end | D10: =Cover!$D$10 -> 46022
C11: Shares outstanding (millions) | D11: =Cover!$D$11 -> 35.8
C13: GATX FCFE — Cash-to-Equity-Holders (v14, 2026-09-24)
C14: Formulas only. Links to 3SF, Drivers, DCF, and Valuation sheets. Stage 1 = 2026E-2030E (5 years). Discount at Ke.
C15: Reference: dcf-mechanics.md §6 (bridge); dcf-judgment-calls.md §7, §8, §10 (lessor FCFE cross-check).
C17: Year | D17: 2026E | E17: 2027E | F17: 2028E | G17: 2029E | H17: 2030E | I17: 2031E | J17: 2032E | K17: 2033E | L17: 2034E | M17: 2035E
A19: x | C19: SECTION 1 — FCFE build ($M)
C20: Convention: positive = cash inflow to common equity; negative = outflow. All non-cash items reversed.
C22: CFO (3SF row 61: consolidated NI + D&A, gains reclass, deferred tax, working capital, affiliates net of dividends, SBC, ROU) | D22: ='3 Statement Forecast'!E73 -> 986.92101 | E22: ='3 Statement Forecast'!F73 -> 925.5622 | F22: ='3 Statement Forecast'!G73 -> 942.33066 | G22: ='3 Statement Forecast'!H73 -> 950.85383 | H22: ='3 Statement Forecast'!I73 -> 935.35084 | I22: ='3 Statement Forecast'!J73 -> 942.22685 | J22: ='3 Statement Forecast'!K73 -> 957.4895 | K22: ='3 Statement Forecast'!L73 -> 974.30364 | ... M22: ='3 Statement Forecast'!N73 -> 1010.6025
C23: − Organic capex (3SF row 63; Wells Fargo acquisition excluded here, see identity block) | D23: ='3 Statement Forecast'!E75 -> -1041 | E23: ='3 Statement Forecast'!F75 -> -1400 | F23: ='3 Statement Forecast'!G75 -> -1400 | G23: ='3 Statement Forecast'!H75 -> -1400 | H23: ='3 Statement Forecast'!I75 -> -1400 | I23: ='3 Statement Forecast'!J75 -> -1190 | J23: ='3 Statement Forecast'!K75 -> -1159.27 | K23: ='3 Statement Forecast'!L75 -> -1173.1223 | ... M23: ='3 Statement Forecast'!N75 -> -1201.2437
C24: + Disposition proceeds + other investing (3SF rows 65, 66) | D24: ='3 Statement Forecast'!E77+'3 Statement Forecast'!E78 -> 360.5 | E24: ='3 Statement Forecast'!F77+'3 Statement Forecast'!F78 -> 360.5 | F24: ='3 Statement Forecast'!G77+'3 Statement Forecast'!G78 -> 360.49926 | G24: ='3 Statement Forecast'!H77+'3 Statement Forecast'!H78 -> 360.49926 | H24: ='3 Statement Forecast'!I77+'3 Statement Forecast'!I78 -> 360.49926 | I24: ='3 Statement Forecast'!J77+'3 Statement Forecast'!J78 -> 367.86674 | J24: ='3 Statement Forecast'!K77+'3 Statement Forecast'!K78 -> 370.40246 | K24: ='3 Statement Forecast'!L77+'3 Statement Forecast'!L78 -> 373.02694 | ... M24: ='3 Statement Forecast'!N77+'3 Statement Forecast'!N78 -> 378.55467
C25: + Net borrowing (3SF rows 69, 70, 72: refi + net new issuance + restricted release) | D25: ='3 Statement Forecast'!E81+'3 Statement Forecast'!E82+'3 Statement Forecast'!E84 -> -16.944005 | E25: ='3 Statement Forecast'!F81+'3 Statement Forecast'!F82+'3 Statement Forecast'!F84 -> 501.01258 | F25: ='3 Statement Forecast'!G81+'3 Statement Forecast'!G82+'3 Statement Forecast'!G84 -> 475.72665 | G25: ='3 Statement Forecast'!H81+'3 Statement Forecast'!H82+'3 Statement Forecast'!H84 -> 458.73662 | H25: ='3 Statement Forecast'!I81+'3 Statement Forecast'!I82+'3 Statement Forecast'!I84 -> 465.82236 | I25: ='3 Statement Forecast'!J81+'3 Statement Forecast'!J82+'3 Statement Forecast'!J84 -> 242.88898 | J25: ='3 Statement Forecast'!K81+'3 Statement Forecast'!K82+'3 Statement Forecast'!K84 -> 190.57389 | K25: ='3 Statement Forecast'!L81+'3 Statement Forecast'!L82+'3 Statement Forecast'!L84 -> 184.05498 | ... M25: ='3 Statement Forecast'!N81+'3 Statement Forecast'!N82+'3 Statement Forecast'!N84 -> 172.30919
C26: − NCI tranche purchases, cash to Brookfield (3SF row 71) | D26: ='3 Statement Forecast'!E83 -> -66.2 | E26: ='3 Statement Forecast'!F83 -> -131.08911 | F26: ='3 Statement Forecast'!G83 -> -131.08911 | G26: ='3 Statement Forecast'!H83 -> -131.08911 | H26: ='3 Statement Forecast'!I83 -> -131.08911 | I26: ='3 Statement Forecast'!J83 -> -131.08911 | J26: ='3 Statement Forecast'!K83 -> -131.08911 | K26: ='3 Statement Forecast'!L83 -> -131.08911 | ... M26: ='3 Statement Forecast'!N83 -> -131.08911
C27: + NCI equity contributions − distributions to NCI (3SF rows 75, 76) | D27: ='3 Statement Forecast'!E87+'3 Statement Forecast'!E88 -> -66.465 | E27: ='3 Statement Forecast'!F87+'3 Statement Forecast'!F88 -> -59.465 | F27: ='3 Statement Forecast'!G87+'3 Statement Forecast'!G88 -> -52.465 | G27: ='3 Statement Forecast'!H87+'3 Statement Forecast'!H88 -> -45.465 | H27: ='3 Statement Forecast'!I87+'3 Statement Forecast'!I88 -> -38.465 | I27: ='3 Statement Forecast'!J87+'3 Statement Forecast'!J88 -> -31.465 | J27: ='3 Statement Forecast'!K87+'3 Statement Forecast'!K88 -> -24.465 | K27: ='3 Statement Forecast'!L87+'3 Statement Forecast'!L88 -> -17.465 | ... M27: ='3 Statement Forecast'!N87+'3 Statement Forecast'!N88 -> -3.465
C28: − SBC treated as a cash-equivalent cost for valuation (reverses the 3SF row 59 add-back; work order item 5) | D28: =-'3 Statement Forecast'!E71 -> -28 | E28: =-'3 Statement Forecast'!F71 -> -28 | F28: =-'3 Statement Forecast'!G71 -> -28 | G28: =-'3 Statement Forecast'!H71 -> -28 | H28: =-'3 Statement Forecast'!I71 -> -28 | I28: =-'3 Statement Forecast'!J71 -> -28 | J28: =-'3 Statement Forecast'!K71 -> -28 | K28: =-'3 Statement Forecast'!L71 -> -28 | ... M28: =-'3 Statement Forecast'!N71 -> -28
C29: (memo) Acquisitions excluded from valuation FCFE; included in the cash identity below | D29: 0 | E29: 0 | F29: 0 | G29: 0 | H29: 0 | I29: 0 | J29: 0 | K29: 0 | L29: 0 | M29: 0
C30: FCFE for valuation ($M) = sum of rows 10 to 17 (ex-acquisition, SBC as cost) | D30: =SUM(D22:D29) -> 128.812 | E30: =SUM(E22:E29) -> 168.52066 | F30: =SUM(F22:F29) -> 167.00247 | G30: =SUM(G22:G29) -> 165.53561 | H30: =SUM(H22:H29) -> 164.11835 | I30: =SUM(I22:I29) -> 172.42846 | J30: =SUM(J22:J29) -> 175.64169 | K30: =SUM(K22:K29) -> 181.70917 | ... M30: =SUM(M22:M29) -> 197.66861
A32: x | C32: SECTION 2 — Cash identity: FCFE (cash basis) = Dividends + Buybacks + ΔCash. Cash-basis FCFE = row 18 + SBC add-back (row 16 reversed) + acquisition (3SF row 64).
C33: This ties by construction of the cash flow statement: CFO + CFI + all financing except dividends and buybacks.
C34: Dividends paid ($M; 3SF!row 74 is negative, flip sign for "use of cash" convention) | D34: =-'3 Statement Forecast'!E86 -> 94.512 | E34: =-'3 Statement Forecast'!F86 -> 96.520665 | F34: =-'3 Statement Forecast'!G86 -> 95.002467 | G34: =-'3 Statement Forecast'!H86 -> 93.535609 | H34: =-'3 Statement Forecast'!I86 -> 92.118354 | I34: =-'3 Statement Forecast'!J86 -> 96.102945 | J34: =-'3 Statement Forecast'!K86 -> 97.64365 | K34: =-'3 Statement Forecast'!L86 -> 100.55293 | ... M34: =-'3 Statement Forecast'!N86 -> 108.20528
C35: Buybacks ($M; 3SF!row 73 negative, flip sign) | D35: =-'3 Statement Forecast'!E85 -> 100 | E35: =-'3 Statement Forecast'!F85 -> 100 | F35: =-'3 Statement Forecast'!G85 -> 100 | G35: =-'3 Statement Forecast'!H85 -> 100 | H35: =-'3 Statement Forecast'!I85 -> 100 | I35: =-'3 Statement Forecast'!J85 -> 104.32551 | J35: =-'3 Statement Forecast'!K85 -> 105.99804 | K35: =-'3 Statement Forecast'!L85 -> 109.15624 | ... M35: =-'3 Statement Forecast'!N85 -> 117.46333
C36: ΔCash+Restricted (3SF!row 81 EOP − row 80 BOP) | D36: ='3 Statement Forecast'!E93-'3 Statement Forecast'!E92 -> -4237.7 | E36: ='3 Statement Forecast'!F93-'3 Statement Forecast'!F92 -> 0 | F36: ='3 Statement Forecast'!G93-'3 Statement Forecast'!G92 -> 0 | G36: ='3 Statement Forecast'!H93-'3 Statement Forecast'!H92 -> 0 | H36: ='3 Statement Forecast'!I93-'3 Statement Forecast'!I92 -> 0 | I36: ='3 Statement Forecast'!J93-'3 Statement Forecast'!J92 -> 0 | J36: ='3 Statement Forecast'!K93-'3 Statement Forecast'!K92 -> 0 | K36: ='3 Statement Forecast'!L93-'3 Statement Forecast'!L92 -> 0 | ... M36: ='3 Statement Forecast'!N93-'3 Statement Forecast'!N92 -> 0
C37: Sum: Div + BB + ΔCash | D37: =D34+D35+D36 -> -4043.188 | E37: =E34+E35+E36 -> 196.52066 | F37: =F34+F35+F36 -> 195.00247 | G37: =G34+G35+G36 -> 193.53561 | H37: =H34+H35+H36 -> 192.11835 | I37: =I34+I35+I36 -> 200.42846 | J37: =J34+J35+J36 -> 203.64169 | K37: =K34+K35+K36 -> 209.70917 | ... M37: =M34+M35+M36 -> 225.66861
C38: Δ = cash-basis FCFE − (Div + BB + ΔCash); must be 0.00 | D38: =(D30-D28+'3 Statement Forecast'!E76)-D37 -> 0 | E38: =(E30-E28+'3 Statement Forecast'!F76)-E37 -> 0 | F38: =(F30-F28+'3 Statement Forecast'!G76)-F37 -> 0 | G38: =(G30-G28+'3 Statement Forecast'!H76)-G37 -> 0 | H38: =(H30-H28+'3 Statement Forecast'!I76)-H37 -> 0 | I38: =(I30-I28+'3 Statement Forecast'!J76)-I37 -> 0 | J38: =(J30-J28+'3 Statement Forecast'!K76)-J37 -> 0 | K38: =(K30-K28+'3 Statement Forecast'!L76)-K37 -> 0 | ... M38: =(M30-M28+'3 Statement Forecast'!N76)-M37 -> 0
C39: Gate status per year (|Δ| < $0.5M = PASS) | D39: =IF(ABS(D38)<0.5,"PASS","FAIL") -> PASS | E39: =IF(ABS(E38)<0.5,"PASS","FAIL") -> PASS | F39: =IF(ABS(F38)<0.5,"PASS","FAIL") -> PASS | G39: =IF(ABS(G38)<0.5,"PASS","FAIL") -> PASS | H39: =IF(ABS(H38)<0.5,"PASS","FAIL") -> PASS | I39: =IF(ABS(I38)<0.5,"PASS","FAIL") -> PASS | J39: =IF(ABS(J38)<0.5,"PASS","FAIL") -> PASS | K39: =IF(ABS(K38)<0.5,"PASS","FAIL") -> PASS | ... M39: =IF(ABS(M38)<0.5,"PASS","FAIL") -> PASS
A41: x | C41: SECTION 3 — Cost of equity (Ke)
C42: Ke (from DCF!B45 — CAPM: Rf + Beta_adj × ERP) | D42: =Drivers!$C$435 -> 0.0902
A44: x | C44: SECTION 4 — Terminal value
C45: Method (a) — Perpetuity growth on year-10 FCFE (2035)
C46: Terminal g (link Drivers!B433) | D46: =Drivers!$C$433 -> 0.035
A47: x | C47: FCFE_2036 (year-10 FCFE × (1+g)) | D47: =M30*(1+D46) -> 204.58701
C48: TV_perpetuity = FCFE_2031 / (Ke − g) | D48: =D47/(D42-D46) -> 3706.2865
C50: Method (b) — P/B multiple on year-10 book equity (2035)
C51: Book equity (GATX excl NCI) 2035E ($M) — link 3SF!L46 | D51: ='3 Statement Forecast'!N58 -> 4403.9178
C52: Diluted shares 2035E (M) — link Drivers!Diluted_shares_2035 | D52: =Drivers!$C$507 -> 31.056618
A53: x | C53: BVPS 2030E ($/sh) | D53: =D51/D52 -> 141.80288
C54: P/B multiple (link Drivers!B434 = Valuation!B15 25y median) | D54: =Drivers!$C$434 -> 1.632152
C55: TV_PB per share ($) | D55: =D53*D54 -> 231.44385
C56: TV_PB total ($M) = TV_PB × shares | D56: =D55*D52 -> 7187.8633
A58: x | C58: SECTION 5 — Present value at Ke
